begin_compilation
  name " HotSpotCompilation-349[JavaExamples.exampleSimpleCall(JavaExamples$ExampleObject, int)]"
  method "HotSpotCompilation-349[JavaExamples.exampleSimpleCall(JavaExamples$ExampleObject, int)]"
  date 1583364091813
end_compilation
begin_cfg
  name "Final HIR schedule"
  begin_block
    name "B0"
    from_bci -1
    to_bci -1
    predecessors 
    successors 
    xhandlers
    flags 
    probability 4607182418800017408
    begin_IR
      HIR
f <@#|@fixed with next>@ <|@
tid v0 <|@
d <@d|@=== Debug Properties ===
stamp: void
withSpeculationFence: false
=== Inputs ===
stateAfter: - 
=== Succesors ===
next: v18 
=== Usages ===
=== Predecessor ===
- >@ <|@
instruction <@StartNode|@org.graalvm.compiler.nodes.StartNode>@ stateAfter: - #next: v18  <|@  <|@
f <@~|@floating>@ <|@
tid a17 <|@
d <@d|@=== Debug Properties ===
isDefaultStable: false
rawvalue: null
stableDimension: 0
stamp: a - NULL
stampKind: a -
value: Object[null]
=== Inputs ===
=== Succesors ===
=== Usages ===
?3 
=== Predecessor ===
- >@ <|@
instruction <@Constant|@org.graalvm.compiler.nodes.ConstantNode>@  <|@  <|@
f <@~|@floating>@ <|@
tid i2 <|@
d <@d|@=== Debug Properties ===
index: 1
stamp: i32
uncheckedStamp: [null]
=== Inputs ===
=== Succesors ===
=== Usages ===
?3 v11 
=== Predecessor ===
- >@ <|@
instruction <@Parameter|@org.graalvm.compiler.nodes.ParameterNode>@  <|@  <|@
tid ?3 <|@
d <@d|@=== Debug Properties ===
bci: 0
code: ResolvedJavaMethodBytecode<JavaExamples.exampleSimpleCall(JavaExamples$ExampleObject, int)>
duringCall: false
localsSize: 2
locksSize: 0
rethrowException: false
sourceFile: JavaExamples.java
sourceLine: 104
stackSize: 0
=== Inputs ===
outerFrameState: - 
values: a17 i2 
=== Succesors ===
=== Usages ===
v18 
=== Predecessor ===
- >@ <|@
instruction <@FrameState|@org.graalvm.compiler.nodes.FrameState>@ outerFrameState: - values: a17 i2  <|@  <|@
f <@~|@floating>@ <|@
tid a1 <|@
d <@d|@=== Debug Properties ===
index: 0
stamp: a# LJavaExamples$ExampleObject;
uncheckedStamp: [null]
=== Inputs ===
=== Succesors ===
=== Usages ===
v18 v11 
=== Predecessor ===
- >@ <|@
instruction <@Parameter|@org.graalvm.compiler.nodes.ParameterNode>@  <|@  <|@
f <@#|@fixed with next>@ <|@
tid v18 <|@
d <@d|@=== Debug Properties ===
stamp: void
=== Inputs ===
stateBefore: ?3 
object: a1 
=== Succesors ===
next: i5 
=== Usages ===
=== Predecessor ===
v0 >@ <|@
instruction <@NullCheck|@org.graalvm.compiler.nodes.extended.NullCheckNode>@ stateBefore: ?3 object: a1 #next: i5  <|@  <|@
tid v11 <|@
d <@d|@=== Debug Properties ===
callType: JavaCall
invokeKind: Special
nodeSourcePosition: at JavaExamples.exampleSimpleCall(JavaExamples.java:104) [bci: 2]
returnStamp: i32
signature: [Ljdk.vm.ci.meta.JavaType;@13e6c9308
stamp: void
targetMethod: HotSpotMethod<JavaExamples$ExampleObject.instanceCall(int)>
=== Inputs ===
arguments: a1 i2 
=== Succesors ===
=== Usages ===
i5 
=== Predecessor ===
- >@ <|@
instruction <@HotSpotDirectCallTarget|@org.graalvm.compiler.hotspot.nodes.HotSpotDirectCallTargetNode>@ arguments: a1 i2  <|@  <|@
tid ?16 <|@
d <@d|@=== Debug Properties ===
bci: 2
code: ResolvedJavaMethodBytecode<JavaExamples.exampleSimpleCall(JavaExamples$ExampleObject, int)>
duringCall: true
localsSize: 2
locksSize: 0
rethrowException: false
sourceFile: JavaExamples.java
sourceLine: 104
stackSize: 0
=== Inputs ===
outerFrameState: - 
values: - - 
=== Succesors ===
=== Usages ===
i5 
=== Predecessor ===
- >@ <|@
instruction <@FrameState|@org.graalvm.compiler.nodes.FrameState>@ outerFrameState: - values: - -  <|@  <|@
f <@#|@fixed with next>@ <|@
tid i5 <|@
d <@d|@=== Debug Properties ===
bci: 2
identity: ANY_LOCATION
nodeSourcePosition: at JavaExamples.exampleSimpleCall(JavaExamples.java:104) [bci: 2]
polymorphic: false
stamp: i32
targetMethod: Direct#JavaExamples$ExampleObject.instanceCall
useForInlining: true
=== Inputs ===
stateAfter: - 
classInit: - 
callTarget: v11 
stateDuring: ?16 
=== Succesors ===
next: v7 
=== Usages ===
v7 
=== Predecessor ===
v18 >@ <|@
instruction <@Invoke|@org.graalvm.compiler.nodes.InvokeNode>@ stateAfter: - classInit: - callTarget: v11 stateDuring: ?16 #next: v7  <|@  <|@
f <@*|@fixed>@ <|@
tid v7 <|@
d <@d|@=== Debug Properties ===
nodeSourcePosition: at JavaExamples.exampleSimpleCall(JavaExamples.java:104) [bci: 5]
stamp: void
=== Inputs ===
result: i5 
memoryMap: - 
=== Succesors ===
=== Usages ===
=== Predecessor ===
i5 >@ <|@
instruction <@Return|@org.graalvm.compiler.nodes.ReturnNode>@ result: i5 memoryMap: -  <|@  <|@
    end_IR
  end_block
end_cfg
begin_cfg
  name "After LIRGeneration"
  begin_block
    name "B0"
    from_bci -1
    to_bci -1
    predecessors 
    successors 
    xhandlers
    flags 
    probability 4607182418800017408
    begin_IR
      LIR
      nr   -1  <|@ instruction [rsi|QWORD[.], rdx|DWORD, rbp|QWORD] = LABEL numbPhis: 0 align: false label: ? <|@ <|@
      nr   -1  <|@ instruction stack:16|QWORD = MOVE rbp|QWORD moveKind: QWORD <|@ <|@
      nr   -1  <|@ instruction [] = HOTSPOTLOCKSTACK frameMapBuilder: org.graalvm.compiler.lir.amd64.AMD64FrameMapBuilder@13f368da8 slotKind: QWORD <|@ <|@
      nr   -1  <|@ instruction v0|QWORD[.] = MOVE rsi|QWORD[.] moveKind: QWORD <|@ <|@
      nr   -1  <|@ instruction v1|DWORD = MOVE rdx|DWORD moveKind: DWORD <|@ <|@
      nr   -1  <|@ st <@st|@JavaExamples.exampleSimpleCall(JavaExamples.java:104) [bci: 0]
locals: Object[null] v1|DWORD 
>@ <|@ instruction NULLCHECK [v0|QWORD[.]] state [bci:0] <|@ <|@
      nr   -1  <|@ instruction rsi|QWORD[.] = MOVE v0|QWORD[.] moveKind: QWORD <|@ <|@
      nr   -1  <|@ instruction rdx|DWORD = MOVE v1|DWORD moveKind: DWORD <|@ <|@
      nr   -1  <|@ st <@st|@JavaExamples.exampleSimpleCall(JavaExamples.java:104) [bci: 2]
locals: - - 
>@ <|@ instruction rax|DWORD = CALL_DIRECT [rsi|QWORD[.], rdx|DWORD] [] callTarget: HotSpotMethod<JavaExamples$ExampleObject.instanceCall(int)> invokeKind: Special config: org.graalvm.compiler.hotspot.GraalHotSpotVMConfig@147e07170 state [bci:2] <|@ <|@
      nr   -1  <|@ instruction v2|DWORD = MOVE rax|DWORD moveKind: DWORD <|@ <|@
      nr   -1  <|@ instruction rax|DWORD = MOVE v2|DWORD moveKind: DWORD <|@ <|@
      nr   -1  <|@ instruction RETURN (savedRbp: stack:16|QWORD, value: rax|DWORD) isStub: false requiresReservedStackAccessCheck: false thread: r15 scratchForSafepointOnReturn: rcx config: org.graalvm.compiler.hotspot.GraalHotSpotVMConfig@147e07170 <|@ <|@
    end_IR
  end_block
end_cfg
begin_bytecodes
     0: aload_0       
     1: iload_1       
     2: invokevirtual #50         // JavaExamples$ExampleObject.instanceCall:(int)int
     5: ireturn       
   <|@
end_bytecodes
begin_cfg
  name "After LIR generation"
  begin_block
    name "B0"
    from_bci -1
    to_bci -1
    predecessors 
    successors 
    xhandlers
    flags 
    probability 4607182418800017408
    begin_IR
      HIR
f <@#|@fixed with next>@ <|@
tid v0 <|@
d <@d|@=== Debug Properties ===
stamp: void
withSpeculationFence: false
=== Inputs ===
stateAfter: - 
=== Succesors ===
next: v18 
=== Usages ===
=== Predecessor ===
- >@ <|@
instruction <@StartNode|@org.graalvm.compiler.nodes.StartNode>@ stateAfter: - #next: v18  <|@  <|@
f <@~|@floating>@ <|@
tid a17 <|@
result Object[null] <|@
d <@d|@=== Debug Properties ===
isDefaultStable: false
rawvalue: null
stableDimension: 0
stamp: a - NULL
stampKind: a -
value: Object[null]
=== Inputs ===
=== Succesors ===
=== Usages ===
?3 
=== Predecessor ===
- >@ <|@
instruction <@Constant|@org.graalvm.compiler.nodes.ConstantNode>@  <|@  <|@
f <@~|@floating>@ <|@
tid i2 <|@
result v1|DWORD <|@
d <@d|@=== Debug Properties ===
index: 1
stamp: i32
uncheckedStamp: [null]
=== Inputs ===
=== Succesors ===
=== Usages ===
?3 v11 
=== Predecessor ===
- >@ <|@
instruction <@Parameter|@org.graalvm.compiler.nodes.ParameterNode>@  <|@  <|@
tid ?3 <|@
d <@d|@=== Debug Properties ===
bci: 0
code: ResolvedJavaMethodBytecode<JavaExamples.exampleSimpleCall(JavaExamples$ExampleObject, int)>
duringCall: false
localsSize: 2
locksSize: 0
rethrowException: false
sourceFile: JavaExamples.java
sourceLine: 104
stackSize: 0
=== Inputs ===
outerFrameState: - 
values: a17 i2 
=== Succesors ===
=== Usages ===
v18 
=== Predecessor ===
- >@ <|@
instruction <@FrameState|@org.graalvm.compiler.nodes.FrameState>@ outerFrameState: - values: a17 i2  <|@  <|@
f <@~|@floating>@ <|@
tid a1 <|@
result v0|QWORD[.] <|@
d <@d|@=== Debug Properties ===
index: 0
stamp: a# LJavaExamples$ExampleObject;
uncheckedStamp: [null]
=== Inputs ===
=== Succesors ===
=== Usages ===
v18 v11 
=== Predecessor ===
- >@ <|@
instruction <@Parameter|@org.graalvm.compiler.nodes.ParameterNode>@  <|@  <|@
f <@#|@fixed with next>@ <|@
tid v18 <|@
d <@d|@=== Debug Properties ===
stamp: void
=== Inputs ===
stateBefore: ?3 
object: a1 
=== Succesors ===
next: i5 
=== Usages ===
=== Predecessor ===
v0 >@ <|@
instruction <@NullCheck|@org.graalvm.compiler.nodes.extended.NullCheckNode>@ stateBefore: ?3 object: a1 #next: i5  <|@  <|@
tid v11 <|@
d <@d|@=== Debug Properties ===
callType: JavaCall
invokeKind: Special
nodeSourcePosition: at JavaExamples.exampleSimpleCall(JavaExamples.java:104) [bci: 2]
returnStamp: i32
signature: [Ljdk.vm.ci.meta.JavaType;@13e6c9308
stamp: void
targetMethod: HotSpotMethod<JavaExamples$ExampleObject.instanceCall(int)>
=== Inputs ===
arguments: a1 i2 
=== Succesors ===
=== Usages ===
i5 
=== Predecessor ===
- >@ <|@
instruction <@HotSpotDirectCallTarget|@org.graalvm.compiler.hotspot.nodes.HotSpotDirectCallTargetNode>@ arguments: a1 i2  <|@  <|@
tid ?16 <|@
d <@d|@=== Debug Properties ===
bci: 2
code: ResolvedJavaMethodBytecode<JavaExamples.exampleSimpleCall(JavaExamples$ExampleObject, int)>
duringCall: true
localsSize: 2
locksSize: 0
rethrowException: false
sourceFile: JavaExamples.java
sourceLine: 104
stackSize: 0
=== Inputs ===
outerFrameState: - 
values: - - 
=== Succesors ===
=== Usages ===
i5 
=== Predecessor ===
- >@ <|@
instruction <@FrameState|@org.graalvm.compiler.nodes.FrameState>@ outerFrameState: - values: - -  <|@  <|@
f <@#|@fixed with next>@ <|@
tid i5 <|@
result v2|DWORD <|@
d <@d|@=== Debug Properties ===
bci: 2
identity: ANY_LOCATION
nodeSourcePosition: at JavaExamples.exampleSimpleCall(JavaExamples.java:104) [bci: 2]
polymorphic: false
stamp: i32
targetMethod: Direct#JavaExamples$ExampleObject.instanceCall
useForInlining: true
=== Inputs ===
stateAfter: - 
classInit: - 
callTarget: v11 
stateDuring: ?16 
=== Succesors ===
next: v7 
=== Usages ===
v7 
=== Predecessor ===
v18 >@ <|@
instruction <@Invoke|@org.graalvm.compiler.nodes.InvokeNode>@ stateAfter: - classInit: - callTarget: v11 stateDuring: ?16 #next: v7  <|@  <|@
f <@*|@fixed>@ <|@
tid v7 <|@
d <@d|@=== Debug Properties ===
nodeSourcePosition: at JavaExamples.exampleSimpleCall(JavaExamples.java:104) [bci: 5]
stamp: void
=== Inputs ===
result: i5 
memoryMap: - 
=== Succesors ===
=== Usages ===
=== Predecessor ===
i5 >@ <|@
instruction <@Return|@org.graalvm.compiler.nodes.ReturnNode>@ result: i5 memoryMap: -  <|@  <|@
    end_IR
    begin_IR
      LIR
      nr   -1  <|@ instruction [rsi|QWORD[.], rdx|DWORD, rbp|QWORD] = LABEL numbPhis: 0 align: false label: ? <|@ <|@
      nr   -1  <|@ instruction stack:16|QWORD = MOVE rbp|QWORD moveKind: QWORD <|@ <|@
      nr   -1  <|@ instruction [] = HOTSPOTLOCKSTACK frameMapBuilder: org.graalvm.compiler.lir.amd64.AMD64FrameMapBuilder@13f368da8 slotKind: QWORD <|@ <|@
      nr   -1  <|@ instruction v0|QWORD[.] = MOVE rsi|QWORD[.] moveKind: QWORD <|@ <|@
      nr   -1  <|@ instruction v1|DWORD = MOVE rdx|DWORD moveKind: DWORD <|@ <|@
      nr   -1  <|@ st <@st|@JavaExamples.exampleSimpleCall(JavaExamples.java:104) [bci: 0]
locals: Object[null] v1|DWORD 
>@ <|@ instruction NULLCHECK [v0|QWORD[.]] state [bci:0] <|@ <|@
      nr   -1  <|@ instruction rsi|QWORD[.] = MOVE v0|QWORD[.] moveKind: QWORD <|@ <|@
      nr   -1  <|@ instruction rdx|DWORD = MOVE v1|DWORD moveKind: DWORD <|@ <|@
      nr   -1  <|@ st <@st|@JavaExamples.exampleSimpleCall(JavaExamples.java:104) [bci: 2]
locals: - - 
>@ <|@ instruction rax|DWORD = CALL_DIRECT [rsi|QWORD[.], rdx|DWORD] [] callTarget: HotSpotMethod<JavaExamples$ExampleObject.instanceCall(int)> invokeKind: Special config: org.graalvm.compiler.hotspot.GraalHotSpotVMConfig@147e07170 state [bci:2] <|@ <|@
      nr   -1  <|@ instruction v2|DWORD = MOVE rax|DWORD moveKind: DWORD <|@ <|@
      nr   -1  <|@ instruction rax|DWORD = MOVE v2|DWORD moveKind: DWORD <|@ <|@
      nr   -1  <|@ instruction RETURN (savedRbp: stack:16|QWORD, value: rax|DWORD) isStub: false requiresReservedStackAccessCheck: false thread: r15 scratchForSafepointOnReturn: rcx config: org.graalvm.compiler.hotspot.GraalHotSpotVMConfig@147e07170 <|@ <|@
    end_IR
  end_block
end_cfg
begin_cfg
  name "After ConstantLoadOptimization"
  begin_block
    name "B0"
    from_bci -1
    to_bci -1
    predecessors 
    successors 
    xhandlers
    flags 
    probability 4607182418800017408
    begin_IR
      LIR
      nr   -1  <|@ instruction [rsi|QWORD[.], rdx|DWORD, rbp|QWORD] = LABEL numbPhis: 0 align: false label: ? <|@ <|@
      nr   -1  <|@ instruction stack:16|QWORD = MOVE rbp|QWORD moveKind: QWORD <|@ <|@
      nr   -1  <|@ instruction [] = HOTSPOTLOCKSTACK frameMapBuilder: org.graalvm.compiler.lir.amd64.AMD64FrameMapBuilder@13f368da8 slotKind: QWORD <|@ <|@
      nr   -1  <|@ instruction v0|QWORD[.] = MOVE rsi|QWORD[.] moveKind: QWORD <|@ <|@
      nr   -1  <|@ instruction v1|DWORD = MOVE rdx|DWORD moveKind: DWORD <|@ <|@
      nr   -1  <|@ st <@st|@JavaExamples.exampleSimpleCall(JavaExamples.java:104) [bci: 0]
locals: Object[null] v1|DWORD 
>@ <|@ instruction NULLCHECK [v0|QWORD[.]] state [bci:0] <|@ <|@
      nr   -1  <|@ instruction rsi|QWORD[.] = MOVE v0|QWORD[.] moveKind: QWORD <|@ <|@
      nr   -1  <|@ instruction rdx|DWORD = MOVE v1|DWORD moveKind: DWORD <|@ <|@
      nr   -1  <|@ st <@st|@JavaExamples.exampleSimpleCall(JavaExamples.java:104) [bci: 2]
locals: - - 
>@ <|@ instruction rax|DWORD = CALL_DIRECT [rsi|QWORD[.], rdx|DWORD] [] callTarget: HotSpotMethod<JavaExamples$ExampleObject.instanceCall(int)> invokeKind: Special config: org.graalvm.compiler.hotspot.GraalHotSpotVMConfig@147e07170 state [bci:2] <|@ <|@
      nr   -1  <|@ instruction v2|DWORD = MOVE rax|DWORD moveKind: DWORD <|@ <|@
      nr   -1  <|@ instruction rax|DWORD = MOVE v2|DWORD moveKind: DWORD <|@ <|@
      nr   -1  <|@ instruction RETURN (savedRbp: stack:16|QWORD, value: rax|DWORD) isStub: false requiresReservedStackAccessCheck: false thread: r15 scratchForSafepointOnReturn: rcx config: org.graalvm.compiler.hotspot.GraalHotSpotVMConfig@147e07170 <|@ <|@
    end_IR
  end_block
end_cfg
begin_bytecodes
     0: aload_0       
     1: iload_1       
     2: invokevirtual #50         // JavaExamples$ExampleObject.instanceCall:(int)int
     5: ireturn       
   <|@
end_bytecodes
begin_cfg
  name "After SaveCalleeSaveRegisters"
  begin_block
    name "B0"
    from_bci -1
    to_bci -1
    predecessors 
    successors 
    xhandlers
    flags 
    probability 4607182418800017408
    begin_IR
      LIR
      nr   -1  <|@ instruction [rsi|QWORD[.], rdx|DWORD, rbp|QWORD] = LABEL numbPhis: 0 align: false label: ? <|@ <|@
      nr   -1  <|@ instruction stack:16|QWORD = MOVE rbp|QWORD moveKind: QWORD <|@ <|@
      nr   -1  <|@ instruction [] = HOTSPOTLOCKSTACK frameMapBuilder: org.graalvm.compiler.lir.amd64.AMD64FrameMapBuilder@13f368da8 slotKind: QWORD <|@ <|@
      nr   -1  <|@ instruction v0|QWORD[.] = MOVE rsi|QWORD[.] moveKind: QWORD <|@ <|@
      nr   -1  <|@ instruction v1|DWORD = MOVE rdx|DWORD moveKind: DWORD <|@ <|@
      nr   -1  <|@ st <@st|@JavaExamples.exampleSimpleCall(JavaExamples.java:104) [bci: 0]
locals: Object[null] v1|DWORD 
>@ <|@ instruction NULLCHECK [v0|QWORD[.]] state [bci:0] <|@ <|@
      nr   -1  <|@ instruction rsi|QWORD[.] = MOVE v0|QWORD[.] moveKind: QWORD <|@ <|@
      nr   -1  <|@ instruction rdx|DWORD = MOVE v1|DWORD moveKind: DWORD <|@ <|@
      nr   -1  <|@ st <@st|@JavaExamples.exampleSimpleCall(JavaExamples.java:104) [bci: 2]
locals: - - 
>@ <|@ instruction rax|DWORD = CALL_DIRECT [rsi|QWORD[.], rdx|DWORD] [] callTarget: HotSpotMethod<JavaExamples$ExampleObject.instanceCall(int)> invokeKind: Special config: org.graalvm.compiler.hotspot.GraalHotSpotVMConfig@147e07170 state [bci:2] <|@ <|@
      nr   -1  <|@ instruction v2|DWORD = MOVE rax|DWORD moveKind: DWORD <|@ <|@
      nr   -1  <|@ instruction rax|DWORD = MOVE v2|DWORD moveKind: DWORD <|@ <|@
      nr   -1  <|@ instruction RETURN (savedRbp: stack:16|QWORD, value: rax|DWORD) isStub: false requiresReservedStackAccessCheck: false thread: r15 scratchForSafepointOnReturn: rcx config: org.graalvm.compiler.hotspot.GraalHotSpotVMConfig@147e07170 <|@ <|@
    end_IR
  end_block
end_cfg
begin_bytecodes
     0: aload_0       
     1: iload_1       
     2: invokevirtual #50         // JavaExamples$ExampleObject.instanceCall:(int)int
     5: ireturn       
   <|@
end_bytecodes
begin_cfg
  name "After PreAllocationOptimizationStage"
  begin_block
    name "B0"
    from_bci -1
    to_bci -1
    predecessors 
    successors 
    xhandlers
    flags 
    probability 4607182418800017408
    begin_IR
      LIR
      nr   -1  <|@ instruction [rsi|QWORD[.], rdx|DWORD, rbp|QWORD] = LABEL numbPhis: 0 align: false label: ? <|@ <|@
      nr   -1  <|@ instruction stack:16|QWORD = MOVE rbp|QWORD moveKind: QWORD <|@ <|@
      nr   -1  <|@ instruction [] = HOTSPOTLOCKSTACK frameMapBuilder: org.graalvm.compiler.lir.amd64.AMD64FrameMapBuilder@13f368da8 slotKind: QWORD <|@ <|@
      nr   -1  <|@ instruction v0|QWORD[.] = MOVE rsi|QWORD[.] moveKind: QWORD <|@ <|@
      nr   -1  <|@ instruction v1|DWORD = MOVE rdx|DWORD moveKind: DWORD <|@ <|@
      nr   -1  <|@ st <@st|@JavaExamples.exampleSimpleCall(JavaExamples.java:104) [bci: 0]
locals: Object[null] v1|DWORD 
>@ <|@ instruction NULLCHECK [v0|QWORD[.]] state [bci:0] <|@ <|@
      nr   -1  <|@ instruction rsi|QWORD[.] = MOVE v0|QWORD[.] moveKind: QWORD <|@ <|@
      nr   -1  <|@ instruction rdx|DWORD = MOVE v1|DWORD moveKind: DWORD <|@ <|@
      nr   -1  <|@ st <@st|@JavaExamples.exampleSimpleCall(JavaExamples.java:104) [bci: 2]
locals: - - 
>@ <|@ instruction rax|DWORD = CALL_DIRECT [rsi|QWORD[.], rdx|DWORD] [] callTarget: HotSpotMethod<JavaExamples$ExampleObject.instanceCall(int)> invokeKind: Special config: org.graalvm.compiler.hotspot.GraalHotSpotVMConfig@147e07170 state [bci:2] <|@ <|@
      nr   -1  <|@ instruction v2|DWORD = MOVE rax|DWORD moveKind: DWORD <|@ <|@
      nr   -1  <|@ instruction rax|DWORD = MOVE v2|DWORD moveKind: DWORD <|@ <|@
      nr   -1  <|@ instruction RETURN (savedRbp: stack:16|QWORD, value: rax|DWORD) isStub: false requiresReservedStackAccessCheck: false thread: r15 scratchForSafepointOnReturn: rcx config: org.graalvm.compiler.hotspot.GraalHotSpotVMConfig@147e07170 <|@ <|@
    end_IR
  end_block
end_cfg
begin_bytecodes
     0: aload_0       
     1: iload_1       
     2: invokevirtual #50         // JavaExamples$ExampleObject.instanceCall:(int)int
     5: ireturn       
   <|@
end_bytecodes
begin_cfg
  name "After MarkBasePointers"
  begin_block
    name "B0"
    from_bci -1
    to_bci -1
    predecessors 
    successors 
    xhandlers
    flags 
    probability 4607182418800017408
    begin_IR
      LIR
      nr   -1  <|@ instruction [rsi|QWORD[.], rdx|DWORD, rbp|QWORD] = LABEL numbPhis: 0 align: false label: ? <|@ <|@
      nr   -1  <|@ instruction stack:16|QWORD = MOVE rbp|QWORD moveKind: QWORD <|@ <|@
      nr   -1  <|@ instruction [] = HOTSPOTLOCKSTACK frameMapBuilder: org.graalvm.compiler.lir.amd64.AMD64FrameMapBuilder@13f368da8 slotKind: QWORD <|@ <|@
      nr   -1  <|@ instruction v0|QWORD[.] = MOVE rsi|QWORD[.] moveKind: QWORD <|@ <|@
      nr   -1  <|@ instruction v1|DWORD = MOVE rdx|DWORD moveKind: DWORD <|@ <|@
      nr   -1  <|@ st <@st|@live-base-pointers: []
JavaExamples.exampleSimpleCall(JavaExamples.java:104) [bci: 0]
locals: Object[null] v1|DWORD 
>@ <|@ instruction NULLCHECK [v0|QWORD[.]] state [bci:0] <|@ <|@
      nr   -1  <|@ instruction rsi|QWORD[.] = MOVE v0|QWORD[.] moveKind: QWORD <|@ <|@
      nr   -1  <|@ instruction rdx|DWORD = MOVE v1|DWORD moveKind: DWORD <|@ <|@
      nr   -1  <|@ st <@st|@live-base-pointers: []
JavaExamples.exampleSimpleCall(JavaExamples.java:104) [bci: 2]
locals: - - 
>@ <|@ instruction rax|DWORD = CALL_DIRECT [rsi|QWORD[.], rdx|DWORD] [] callTarget: HotSpotMethod<JavaExamples$ExampleObject.instanceCall(int)> invokeKind: Special config: org.graalvm.compiler.hotspot.GraalHotSpotVMConfig@147e07170 state [bci:2] <|@ <|@
      nr   -1  <|@ instruction v2|DWORD = MOVE rax|DWORD moveKind: DWORD <|@ <|@
      nr   -1  <|@ instruction rax|DWORD = MOVE v2|DWORD moveKind: DWORD <|@ <|@
      nr   -1  <|@ instruction RETURN (savedRbp: stack:16|QWORD, value: rax|DWORD) isStub: false requiresReservedStackAccessCheck: false thread: r15 scratchForSafepointOnReturn: rcx config: org.graalvm.compiler.hotspot.GraalHotSpotVMConfig@147e07170 <|@ <|@
    end_IR
  end_block
end_cfg
begin_bytecodes
     0: aload_0       
     1: iload_1       
     2: invokevirtual #50         // JavaExamples$ExampleObject.instanceCall:(int)int
     5: ireturn       
   <|@
end_bytecodes
begin_cfg
  name "Before register allocation"
  begin_block
    name "B0"
    from_bci -1
    to_bci -1
    predecessors 
    successors 
    xhandlers
    flags 
    probability 4607182418800017408
    begin_IR
      LIR
      nr    0  <|@ instruction [rsi|QWORD[.], rdx|DWORD, rbp|QWORD] = LABEL numbPhis: 0 align: false label: ? <|@ <|@
      nr    2  <|@ instruction stack:16|QWORD = MOVE rbp|QWORD moveKind: QWORD <|@ <|@
      nr    4  <|@ instruction [] = HOTSPOTLOCKSTACK frameMapBuilder: org.graalvm.compiler.lir.amd64.AMD64FrameMapBuilder@13f368da8 slotKind: QWORD <|@ <|@
      nr    6  <|@ instruction v0|QWORD[.] = MOVE rsi|QWORD[.] moveKind: QWORD <|@ <|@
      nr    8  <|@ instruction v1|DWORD = MOVE rdx|DWORD moveKind: DWORD <|@ <|@
      nr   10  <|@ st <@st|@live-base-pointers: []
JavaExamples.exampleSimpleCall(JavaExamples.java:104) [bci: 0]
locals: Object[null] v1|DWORD 
>@ <|@ instruction NULLCHECK [v0|QWORD[.]] state [bci:0] <|@ <|@
      nr   12  <|@ instruction rsi|QWORD[.] = MOVE v0|QWORD[.] moveKind: QWORD <|@ <|@
      nr   14  <|@ instruction rdx|DWORD = MOVE v1|DWORD moveKind: DWORD <|@ <|@
      nr   16  <|@ st <@st|@live-base-pointers: []
JavaExamples.exampleSimpleCall(JavaExamples.java:104) [bci: 2]
locals: - - 
>@ <|@ instruction rax|DWORD = CALL_DIRECT [rsi|QWORD[.], rdx|DWORD] [] callTarget: HotSpotMethod<JavaExamples$ExampleObject.instanceCall(int)> invokeKind: Special config: org.graalvm.compiler.hotspot.GraalHotSpotVMConfig@147e07170 state [bci:2] <|@ <|@
      nr   18  <|@ instruction v2|DWORD = MOVE rax|DWORD moveKind: DWORD <|@ <|@
      nr   20  <|@ instruction rax|DWORD = MOVE v2|DWORD moveKind: DWORD <|@ <|@
      nr   22  <|@ instruction RETURN (savedRbp: stack:16|QWORD, value: rax|DWORD) isStub: false requiresReservedStackAccessCheck: false thread: r15 scratchForSafepointOnReturn: rcx config: org.graalvm.compiler.hotspot.GraalHotSpotVMConfig@147e07170 <|@ <|@
    end_IR
  end_block
end_cfg
begin_bytecodes
     0: aload_0       
     1: iload_1       
     2: invokevirtual #50         // JavaExamples$ExampleObject.instanceCall:(int)int
     5: ireturn       
   <|@
end_bytecodes
begin_cfg
  name "After SSALinearScanLifetimeAnalysis"
  begin_block
    name "B0"
    from_bci -1
    to_bci -1
    predecessors 
    successors 
    xhandlers
    flags 
    probability 4607182418800017408
    begin_IR
      LIR
      nr    0  <|@ instruction [rsi|QWORD[.], rdx|DWORD, rbp|QWORD] = LABEL numbPhis: 0 align: false label: ? <|@ <|@
      nr    2  <|@ instruction stack:16|QWORD = MOVE rbp|QWORD moveKind: QWORD <|@ <|@
      nr    4  <|@ instruction [] = HOTSPOTLOCKSTACK frameMapBuilder: org.graalvm.compiler.lir.amd64.AMD64FrameMapBuilder@13f368da8 slotKind: QWORD <|@ <|@
      nr    6  <|@ instruction v0|QWORD[.] = MOVE rsi|QWORD[.] moveKind: QWORD <|@ <|@
      nr    8  <|@ instruction v1|DWORD = MOVE rdx|DWORD moveKind: DWORD <|@ <|@
      nr   10  <|@ st <@st|@live-base-pointers: []
JavaExamples.exampleSimpleCall(JavaExamples.java:104) [bci: 0]
locals: Object[null] v1|DWORD 
>@ <|@ instruction NULLCHECK [v0|QWORD[.]] state [bci:0] <|@ <|@
      nr   12  <|@ instruction rsi|QWORD[.] = MOVE v0|QWORD[.] moveKind: QWORD <|@ <|@
      nr   14  <|@ instruction rdx|DWORD = MOVE v1|DWORD moveKind: DWORD <|@ <|@
      nr   16  <|@ st <@st|@live-base-pointers: []
JavaExamples.exampleSimpleCall(JavaExamples.java:104) [bci: 2]
locals: - - 
>@ <|@ instruction rax|DWORD = CALL_DIRECT [rsi|QWORD[.], rdx|DWORD] [] callTarget: HotSpotMethod<JavaExamples$ExampleObject.instanceCall(int)> invokeKind: Special config: org.graalvm.compiler.hotspot.GraalHotSpotVMConfig@147e07170 state [bci:2] <|@ <|@
      nr   18  <|@ instruction v2|DWORD = MOVE rax|DWORD moveKind: DWORD <|@ <|@
      nr   20  <|@ instruction rax|DWORD = MOVE v2|DWORD moveKind: DWORD <|@ <|@
      nr   22  <|@ instruction RETURN (savedRbp: stack:16|QWORD, value: rax|DWORD) isStub: false requiresReservedStackAccessCheck: false thread: r15 scratchForSafepointOnReturn: rcx config: org.graalvm.compiler.hotspot.GraalHotSpotVMConfig@147e07170 <|@ <|@
    end_IR
  end_block
end_cfg
begin_bytecodes
     0: aload_0       
     1: iload_1       
     2: invokevirtual #50         // JavaExamples$ExampleObject.instanceCall:(int)int
     5: ireturn       
   <|@
end_bytecodes
begin_intervals
  name "Before register allocation"
  rax|d fixed "[rax|d]" rax|d v2|d [0, 1[[16, 18[[20, 22[ "NoOptimization"
  rcx|- fixed "[rcx|-]" rcx|- -1 [0, 1[[16, 17[ "NoDefinitionFound"
  rdx|- fixed "[rdx|-]" rdx|- v1|d [0, 8[[14, 17[ "NoOptimization"
  rbx|- fixed "[rbx|-]" rbx|- -1 [0, 1[[16, 17[ "NoDefinitionFound"
  rbp|- fixed "[rbp|-]" rbp|- -1 [0, 2[[16, 17[ "NoSpillStore"
  rsi|- fixed "[rsi|-]" rsi|- v0|q [0, 6[[12, 17[ "NoOptimization"
  rdi|- fixed "[rdi|-]" rdi|- -1 [0, 1[[16, 17[ "NoDefinitionFound"
  r8|- fixed "[r8|-]" r8|- -1 [0, 1[[16, 17[ "NoDefinitionFound"
  r9|- fixed "[r9|-]" r9|- -1 [0, 1[[16, 17[ "NoDefinitionFound"
  r10|- fixed "[r10|-]" r10|- -1 [0, 1[[16, 17[ "NoDefinitionFound"
  r11|- fixed "[r11|-]" r11|- -1 [0, 1[[16, 17[ "NoDefinitionFound"
  r13|- fixed "[r13|-]" r13|- -1 [0, 1[[16, 17[ "NoDefinitionFound"
  r14|- fixed "[r14|-]" r14|- -1 [0, 1[[16, 17[ "NoDefinitionFound"
  xmm0|- fixed "[xmm0|-]" xmm0|- -1 [0, 1[[16, 17[ "NoDefinitionFound"
  xmm1|- fixed "[xmm1|-]" xmm1|- -1 [0, 1[[16, 17[ "NoDefinitionFound"
  xmm2|- fixed "[xmm2|-]" xmm2|- -1 [0, 1[[16, 17[ "NoDefinitionFound"
  xmm3|- fixed "[xmm3|-]" xmm3|- -1 [0, 1[[16, 17[ "NoDefinitionFound"
  xmm4|- fixed "[xmm4|-]" xmm4|- -1 [0, 1[[16, 17[ "NoDefinitionFound"
  xmm5|- fixed "[xmm5|-]" xmm5|- -1 [0, 1[[16, 17[ "NoDefinitionFound"
  xmm6|- fixed "[xmm6|-]" xmm6|- -1 [0, 1[[16, 17[ "NoDefinitionFound"
  xmm7|- fixed "[xmm7|-]" xmm7|- -1 [0, 1[[16, 17[ "NoDefinitionFound"
  xmm8|- fixed "[xmm8|-]" xmm8|- -1 [0, 1[[16, 17[ "NoDefinitionFound"
  xmm9|- fixed "[xmm9|-]" xmm9|- -1 [0, 1[[16, 17[ "NoDefinitionFound"
  xmm10|- fixed "[xmm10|-]" xmm10|- -1 [0, 1[[16, 17[ "NoDefinitionFound"
  xmm11|- fixed "[xmm11|-]" xmm11|- -1 [0, 1[[16, 17[ "NoDefinitionFound"
  xmm12|- fixed "[xmm12|-]" xmm12|- -1 [0, 1[[16, 17[ "NoDefinitionFound"
  xmm13|- fixed "[xmm13|-]" xmm13|- -1 [0, 1[[16, 17[ "NoDefinitionFound"
  xmm14|- fixed "[xmm14|-]" xmm14|- -1 [0, 1[[16, 17[ "NoDefinitionFound"
  xmm15|- fixed "[xmm15|-]" xmm15|- -1 [0, 1[[16, 17[ "NoDefinitionFound"
  v0|q QWORD "[v0|q]" v0|q rsi|- [6, 12[6 MustHaveRegister 10 MustHaveRegister 12 ShouldHaveRegister  "NoSpillStore"
  v1|d DWORD "[v1|d]" v1|d rdx|- [8, 14[8 MustHaveRegister 14 ShouldHaveRegister  "NoSpillStore"
  v2|d DWORD "[v2|d]" v2|d rax|d [18, 20[18 MustHaveRegister 20 ShouldHaveRegister  "NoSpillStore"
end_intervals
begin_intervals
  name "After register allocation"
  rax|d fixed "[rax|d]" rax|d v2|d [0, 1[[16, 18[[20, 22[ "NoOptimization"
  rcx|- fixed "[rcx|-]" rcx|- -1 [0, 1[[16, 17[ "NoDefinitionFound"
  rdx|- fixed "[rdx|-]" rdx|- v1|d [0, 8[[14, 17[ "NoOptimization"
  rbx|- fixed "[rbx|-]" rbx|- -1 [0, 1[[16, 17[ "NoDefinitionFound"
  rbp|- fixed "[rbp|-]" rbp|- -1 [0, 2[[16, 17[ "NoSpillStore"
  rsi|- fixed "[rsi|-]" rsi|- v0|q [0, 6[[12, 17[ "NoOptimization"
  rdi|- fixed "[rdi|-]" rdi|- -1 [0, 1[[16, 17[ "NoDefinitionFound"
  r8|- fixed "[r8|-]" r8|- -1 [0, 1[[16, 17[ "NoDefinitionFound"
  r9|- fixed "[r9|-]" r9|- -1 [0, 1[[16, 17[ "NoDefinitionFound"
  r10|- fixed "[r10|-]" r10|- -1 [0, 1[[16, 17[ "NoDefinitionFound"
  r11|- fixed "[r11|-]" r11|- -1 [0, 1[[16, 17[ "NoDefinitionFound"
  r13|- fixed "[r13|-]" r13|- -1 [0, 1[[16, 17[ "NoDefinitionFound"
  r14|- fixed "[r14|-]" r14|- -1 [0, 1[[16, 17[ "NoDefinitionFound"
  xmm0|- fixed "[xmm0|-]" xmm0|- -1 [0, 1[[16, 17[ "NoDefinitionFound"
  xmm1|- fixed "[xmm1|-]" xmm1|- -1 [0, 1[[16, 17[ "NoDefinitionFound"
  xmm2|- fixed "[xmm2|-]" xmm2|- -1 [0, 1[[16, 17[ "NoDefinitionFound"
  xmm3|- fixed "[xmm3|-]" xmm3|- -1 [0, 1[[16, 17[ "NoDefinitionFound"
  xmm4|- fixed "[xmm4|-]" xmm4|- -1 [0, 1[[16, 17[ "NoDefinitionFound"
  xmm5|- fixed "[xmm5|-]" xmm5|- -1 [0, 1[[16, 17[ "NoDefinitionFound"
  xmm6|- fixed "[xmm6|-]" xmm6|- -1 [0, 1[[16, 17[ "NoDefinitionFound"
  xmm7|- fixed "[xmm7|-]" xmm7|- -1 [0, 1[[16, 17[ "NoDefinitionFound"
  xmm8|- fixed "[xmm8|-]" xmm8|- -1 [0, 1[[16, 17[ "NoDefinitionFound"
  xmm9|- fixed "[xmm9|-]" xmm9|- -1 [0, 1[[16, 17[ "NoDefinitionFound"
  xmm10|- fixed "[xmm10|-]" xmm10|- -1 [0, 1[[16, 17[ "NoDefinitionFound"
  xmm11|- fixed "[xmm11|-]" xmm11|- -1 [0, 1[[16, 17[ "NoDefinitionFound"
  xmm12|- fixed "[xmm12|-]" xmm12|- -1 [0, 1[[16, 17[ "NoDefinitionFound"
  xmm13|- fixed "[xmm13|-]" xmm13|- -1 [0, 1[[16, 17[ "NoDefinitionFound"
  xmm14|- fixed "[xmm14|-]" xmm14|- -1 [0, 1[[16, 17[ "NoDefinitionFound"
  xmm15|- fixed "[xmm15|-]" xmm15|- -1 [0, 1[[16, 17[ "NoDefinitionFound"
  v0|q QWORD "[rsi|q]" v0|q rsi|- [6, 12[6 MustHaveRegister 10 MustHaveRegister 12 ShouldHaveRegister  "NoSpillStore"
  v1|d DWORD "[rdx|d]" v1|d rdx|- [8, 14[8 MustHaveRegister 14 ShouldHaveRegister  "NoSpillStore"
  v2|d DWORD "[rax|d]" v2|d rax|d [18, 20[18 MustHaveRegister 20 ShouldHaveRegister  "NoSpillStore"
end_intervals
begin_cfg
  name "After LinearScanRegisterAllocation"
  begin_block
    name "B0"
    from_bci -1
    to_bci -1
    predecessors 
    successors 
    xhandlers
    flags 
    probability 4607182418800017408
    begin_IR
      LIR
      nr    0  <|@ instruction [rsi|QWORD[.], rdx|DWORD, rbp|QWORD] = LABEL numbPhis: 0 align: false label: ? <|@ <|@
      nr    2  <|@ instruction stack:16|QWORD = MOVE rbp|QWORD moveKind: QWORD <|@ <|@
      nr    4  <|@ instruction [] = HOTSPOTLOCKSTACK frameMapBuilder: org.graalvm.compiler.lir.amd64.AMD64FrameMapBuilder@13f368da8 slotKind: QWORD <|@ <|@
      nr    6  <|@ instruction v0|QWORD[.] = MOVE rsi|QWORD[.] moveKind: QWORD <|@ <|@
      nr    8  <|@ instruction v1|DWORD = MOVE rdx|DWORD moveKind: DWORD <|@ <|@
      nr   10  <|@ st <@st|@live-base-pointers: []
JavaExamples.exampleSimpleCall(JavaExamples.java:104) [bci: 0]
locals: Object[null] v1|DWORD 
>@ <|@ instruction NULLCHECK [v0|QWORD[.]] state [bci:0] <|@ <|@
      nr   12  <|@ instruction rsi|QWORD[.] = MOVE v0|QWORD[.] moveKind: QWORD <|@ <|@
      nr   14  <|@ instruction rdx|DWORD = MOVE v1|DWORD moveKind: DWORD <|@ <|@
      nr   16  <|@ st <@st|@live-base-pointers: []
JavaExamples.exampleSimpleCall(JavaExamples.java:104) [bci: 2]
locals: - - 
>@ <|@ instruction rax|DWORD = CALL_DIRECT [rsi|QWORD[.], rdx|DWORD] [] callTarget: HotSpotMethod<JavaExamples$ExampleObject.instanceCall(int)> invokeKind: Special config: org.graalvm.compiler.hotspot.GraalHotSpotVMConfig@147e07170 state [bci:2] <|@ <|@
      nr   18  <|@ instruction v2|DWORD = MOVE rax|DWORD moveKind: DWORD <|@ <|@
      nr   20  <|@ instruction rax|DWORD = MOVE v2|DWORD moveKind: DWORD <|@ <|@
      nr   22  <|@ instruction RETURN (savedRbp: stack:16|QWORD, value: rax|DWORD) isStub: false requiresReservedStackAccessCheck: false thread: r15 scratchForSafepointOnReturn: rcx config: org.graalvm.compiler.hotspot.GraalHotSpotVMConfig@147e07170 <|@ <|@
    end_IR
  end_block
end_cfg
begin_bytecodes
     0: aload_0       
     1: iload_1       
     2: invokevirtual #50         // JavaExamples$ExampleObject.instanceCall:(int)int
     5: ireturn       
   <|@
end_bytecodes
begin_intervals
  name "After optimize spill position"
  rax|d fixed "[rax|d]" rax|d v2|d [0, 1[[16, 18[[20, 22[ "NoOptimization"
  rcx|- fixed "[rcx|-]" rcx|- -1 [0, 1[[16, 17[ "NoDefinitionFound"
  rdx|- fixed "[rdx|-]" rdx|- v1|d [0, 8[[14, 17[ "NoOptimization"
  rbx|- fixed "[rbx|-]" rbx|- -1 [0, 1[[16, 17[ "NoDefinitionFound"
  rbp|- fixed "[rbp|-]" rbp|- -1 [0, 2[[16, 17[ "NoSpillStore"
  rsi|- fixed "[rsi|-]" rsi|- v0|q [0, 6[[12, 17[ "NoOptimization"
  rdi|- fixed "[rdi|-]" rdi|- -1 [0, 1[[16, 17[ "NoDefinitionFound"
  r8|- fixed "[r8|-]" r8|- -1 [0, 1[[16, 17[ "NoDefinitionFound"
  r9|- fixed "[r9|-]" r9|- -1 [0, 1[[16, 17[ "NoDefinitionFound"
  r10|- fixed "[r10|-]" r10|- -1 [0, 1[[16, 17[ "NoDefinitionFound"
  r11|- fixed "[r11|-]" r11|- -1 [0, 1[[16, 17[ "NoDefinitionFound"
  r13|- fixed "[r13|-]" r13|- -1 [0, 1[[16, 17[ "NoDefinitionFound"
  r14|- fixed "[r14|-]" r14|- -1 [0, 1[[16, 17[ "NoDefinitionFound"
  xmm0|- fixed "[xmm0|-]" xmm0|- -1 [0, 1[[16, 17[ "NoDefinitionFound"
  xmm1|- fixed "[xmm1|-]" xmm1|- -1 [0, 1[[16, 17[ "NoDefinitionFound"
  xmm2|- fixed "[xmm2|-]" xmm2|- -1 [0, 1[[16, 17[ "NoDefinitionFound"
  xmm3|- fixed "[xmm3|-]" xmm3|- -1 [0, 1[[16, 17[ "NoDefinitionFound"
  xmm4|- fixed "[xmm4|-]" xmm4|- -1 [0, 1[[16, 17[ "NoDefinitionFound"
  xmm5|- fixed "[xmm5|-]" xmm5|- -1 [0, 1[[16, 17[ "NoDefinitionFound"
  xmm6|- fixed "[xmm6|-]" xmm6|- -1 [0, 1[[16, 17[ "NoDefinitionFound"
  xmm7|- fixed "[xmm7|-]" xmm7|- -1 [0, 1[[16, 17[ "NoDefinitionFound"
  xmm8|- fixed "[xmm8|-]" xmm8|- -1 [0, 1[[16, 17[ "NoDefinitionFound"
  xmm9|- fixed "[xmm9|-]" xmm9|- -1 [0, 1[[16, 17[ "NoDefinitionFound"
  xmm10|- fixed "[xmm10|-]" xmm10|- -1 [0, 1[[16, 17[ "NoDefinitionFound"
  xmm11|- fixed "[xmm11|-]" xmm11|- -1 [0, 1[[16, 17[ "NoDefinitionFound"
  xmm12|- fixed "[xmm12|-]" xmm12|- -1 [0, 1[[16, 17[ "NoDefinitionFound"
  xmm13|- fixed "[xmm13|-]" xmm13|- -1 [0, 1[[16, 17[ "NoDefinitionFound"
  xmm14|- fixed "[xmm14|-]" xmm14|- -1 [0, 1[[16, 17[ "NoDefinitionFound"
  xmm15|- fixed "[xmm15|-]" xmm15|- -1 [0, 1[[16, 17[ "NoDefinitionFound"
  v0|q QWORD "[rsi|q]" v0|q rsi|- [6, 12[6 MustHaveRegister 10 MustHaveRegister 12 ShouldHaveRegister  "NoSpillStore"
  v1|d DWORD "[rdx|d]" v1|d rdx|- [8, 14[8 MustHaveRegister 14 ShouldHaveRegister  "NoSpillStore"
  v2|d DWORD "[rax|d]" v2|d rax|d [18, 20[18 MustHaveRegister 20 ShouldHaveRegister  "NoSpillStore"
end_intervals
begin_cfg
  name "After LinearScanOptimizeSpillPosition"
  begin_block
    name "B0"
    from_bci -1
    to_bci -1
    predecessors 
    successors 
    xhandlers
    flags 
    probability 4607182418800017408
    begin_IR
      LIR
      nr    0  <|@ instruction [rsi|QWORD[.], rdx|DWORD, rbp|QWORD] = LABEL numbPhis: 0 align: false label: ? <|@ <|@
      nr    2  <|@ instruction stack:16|QWORD = MOVE rbp|QWORD moveKind: QWORD <|@ <|@
      nr    4  <|@ instruction [] = HOTSPOTLOCKSTACK frameMapBuilder: org.graalvm.compiler.lir.amd64.AMD64FrameMapBuilder@13f368da8 slotKind: QWORD <|@ <|@
      nr    6  <|@ instruction v0|QWORD[.] = MOVE rsi|QWORD[.] moveKind: QWORD <|@ <|@
      nr    8  <|@ instruction v1|DWORD = MOVE rdx|DWORD moveKind: DWORD <|@ <|@
      nr   10  <|@ st <@st|@live-base-pointers: []
JavaExamples.exampleSimpleCall(JavaExamples.java:104) [bci: 0]
locals: Object[null] v1|DWORD 
>@ <|@ instruction NULLCHECK [v0|QWORD[.]] state [bci:0] <|@ <|@
      nr   12  <|@ instruction rsi|QWORD[.] = MOVE v0|QWORD[.] moveKind: QWORD <|@ <|@
      nr   14  <|@ instruction rdx|DWORD = MOVE v1|DWORD moveKind: DWORD <|@ <|@
      nr   16  <|@ st <@st|@live-base-pointers: []
JavaExamples.exampleSimpleCall(JavaExamples.java:104) [bci: 2]
locals: - - 
>@ <|@ instruction rax|DWORD = CALL_DIRECT [rsi|QWORD[.], rdx|DWORD] [] callTarget: HotSpotMethod<JavaExamples$ExampleObject.instanceCall(int)> invokeKind: Special config: org.graalvm.compiler.hotspot.GraalHotSpotVMConfig@147e07170 state [bci:2] <|@ <|@
      nr   18  <|@ instruction v2|DWORD = MOVE rax|DWORD moveKind: DWORD <|@ <|@
      nr   20  <|@ instruction rax|DWORD = MOVE v2|DWORD moveKind: DWORD <|@ <|@
      nr   22  <|@ instruction RETURN (savedRbp: stack:16|QWORD, value: rax|DWORD) isStub: false requiresReservedStackAccessCheck: false thread: r15 scratchForSafepointOnReturn: rcx config: org.graalvm.compiler.hotspot.GraalHotSpotVMConfig@147e07170 <|@ <|@
    end_IR
  end_block
end_cfg
begin_bytecodes
     0: aload_0       
     1: iload_1       
     2: invokevirtual #50         // JavaExamples$ExampleObject.instanceCall:(int)int
     5: ireturn       
   <|@
end_bytecodes
begin_intervals
  name "After resolve data flow"
  rax|d fixed "[rax|d]" rax|d v2|d [0, 1[[16, 18[[20, 22[ "NoOptimization"
  rcx|- fixed "[rcx|-]" rcx|- -1 [0, 1[[16, 17[ "NoDefinitionFound"
  rdx|- fixed "[rdx|-]" rdx|- v1|d [0, 8[[14, 17[ "NoOptimization"
  rbx|- fixed "[rbx|-]" rbx|- -1 [0, 1[[16, 17[ "NoDefinitionFound"
  rbp|- fixed "[rbp|-]" rbp|- -1 [0, 2[[16, 17[ "NoSpillStore"
  rsi|- fixed "[rsi|-]" rsi|- v0|q [0, 6[[12, 17[ "NoOptimization"
  rdi|- fixed "[rdi|-]" rdi|- -1 [0, 1[[16, 17[ "NoDefinitionFound"
  r8|- fixed "[r8|-]" r8|- -1 [0, 1[[16, 17[ "NoDefinitionFound"
  r9|- fixed "[r9|-]" r9|- -1 [0, 1[[16, 17[ "NoDefinitionFound"
  r10|- fixed "[r10|-]" r10|- -1 [0, 1[[16, 17[ "NoDefinitionFound"
  r11|- fixed "[r11|-]" r11|- -1 [0, 1[[16, 17[ "NoDefinitionFound"
  r13|- fixed "[r13|-]" r13|- -1 [0, 1[[16, 17[ "NoDefinitionFound"
  r14|- fixed "[r14|-]" r14|- -1 [0, 1[[16, 17[ "NoDefinitionFound"
  xmm0|- fixed "[xmm0|-]" xmm0|- -1 [0, 1[[16, 17[ "NoDefinitionFound"
  xmm1|- fixed "[xmm1|-]" xmm1|- -1 [0, 1[[16, 17[ "NoDefinitionFound"
  xmm2|- fixed "[xmm2|-]" xmm2|- -1 [0, 1[[16, 17[ "NoDefinitionFound"
  xmm3|- fixed "[xmm3|-]" xmm3|- -1 [0, 1[[16, 17[ "NoDefinitionFound"
  xmm4|- fixed "[xmm4|-]" xmm4|- -1 [0, 1[[16, 17[ "NoDefinitionFound"
  xmm5|- fixed "[xmm5|-]" xmm5|- -1 [0, 1[[16, 17[ "NoDefinitionFound"
  xmm6|- fixed "[xmm6|-]" xmm6|- -1 [0, 1[[16, 17[ "NoDefinitionFound"
  xmm7|- fixed "[xmm7|-]" xmm7|- -1 [0, 1[[16, 17[ "NoDefinitionFound"
  xmm8|- fixed "[xmm8|-]" xmm8|- -1 [0, 1[[16, 17[ "NoDefinitionFound"
  xmm9|- fixed "[xmm9|-]" xmm9|- -1 [0, 1[[16, 17[ "NoDefinitionFound"
  xmm10|- fixed "[xmm10|-]" xmm10|- -1 [0, 1[[16, 17[ "NoDefinitionFound"
  xmm11|- fixed "[xmm11|-]" xmm11|- -1 [0, 1[[16, 17[ "NoDefinitionFound"
  xmm12|- fixed "[xmm12|-]" xmm12|- -1 [0, 1[[16, 17[ "NoDefinitionFound"
  xmm13|- fixed "[xmm13|-]" xmm13|- -1 [0, 1[[16, 17[ "NoDefinitionFound"
  xmm14|- fixed "[xmm14|-]" xmm14|- -1 [0, 1[[16, 17[ "NoDefinitionFound"
  xmm15|- fixed "[xmm15|-]" xmm15|- -1 [0, 1[[16, 17[ "NoDefinitionFound"
  v0|q QWORD "[rsi|q]" v0|q rsi|- [6, 12[6 MustHaveRegister 10 MustHaveRegister 12 ShouldHaveRegister  "NoSpillStore"
  v1|d DWORD "[rdx|d]" v1|d rdx|- [8, 14[8 MustHaveRegister 14 ShouldHaveRegister  "NoSpillStore"
  v2|d DWORD "[rax|d]" v2|d rax|d [18, 20[18 MustHaveRegister 20 ShouldHaveRegister  "NoSpillStore"
end_intervals
begin_cfg
  name "After SSALinearScanResolveDataFlow"
  begin_block
    name "B0"
    from_bci -1
    to_bci -1
    predecessors 
    successors 
    xhandlers
    flags 
    probability 4607182418800017408
    begin_IR
      LIR
      nr    0  <|@ instruction [rsi|QWORD[.], rdx|DWORD, rbp|QWORD] = LABEL numbPhis: 0 align: false label: ? <|@ <|@
      nr    2  <|@ instruction stack:16|QWORD = MOVE rbp|QWORD moveKind: QWORD <|@ <|@
      nr    4  <|@ instruction [] = HOTSPOTLOCKSTACK frameMapBuilder: org.graalvm.compiler.lir.amd64.AMD64FrameMapBuilder@13f368da8 slotKind: QWORD <|@ <|@
      nr    6  <|@ instruction v0|QWORD[.] = MOVE rsi|QWORD[.] moveKind: QWORD <|@ <|@
      nr    8  <|@ instruction v1|DWORD = MOVE rdx|DWORD moveKind: DWORD <|@ <|@
      nr   10  <|@ st <@st|@live-base-pointers: []
JavaExamples.exampleSimpleCall(JavaExamples.java:104) [bci: 0]
locals: Object[null] v1|DWORD 
>@ <|@ instruction NULLCHECK [v0|QWORD[.]] state [bci:0] <|@ <|@
      nr   12  <|@ instruction rsi|QWORD[.] = MOVE v0|QWORD[.] moveKind: QWORD <|@ <|@
      nr   14  <|@ instruction rdx|DWORD = MOVE v1|DWORD moveKind: DWORD <|@ <|@
      nr   16  <|@ st <@st|@live-base-pointers: []
JavaExamples.exampleSimpleCall(JavaExamples.java:104) [bci: 2]
locals: - - 
>@ <|@ instruction rax|DWORD = CALL_DIRECT [rsi|QWORD[.], rdx|DWORD] [] callTarget: HotSpotMethod<JavaExamples$ExampleObject.instanceCall(int)> invokeKind: Special config: org.graalvm.compiler.hotspot.GraalHotSpotVMConfig@147e07170 state [bci:2] <|@ <|@
      nr   18  <|@ instruction v2|DWORD = MOVE rax|DWORD moveKind: DWORD <|@ <|@
      nr   20  <|@ instruction rax|DWORD = MOVE v2|DWORD moveKind: DWORD <|@ <|@
      nr   22  <|@ instruction RETURN (savedRbp: stack:16|QWORD, value: rax|DWORD) isStub: false requiresReservedStackAccessCheck: false thread: r15 scratchForSafepointOnReturn: rcx config: org.graalvm.compiler.hotspot.GraalHotSpotVMConfig@147e07170 <|@ <|@
    end_IR
  end_block
end_cfg
begin_bytecodes
     0: aload_0       
     1: iload_1       
     2: invokevirtual #50         // JavaExamples$ExampleObject.instanceCall:(int)int
     5: ireturn       
   <|@
end_bytecodes
begin_cfg
  name "After SSALinearScanEliminateSpillMove"
  begin_block
    name "B0"
    from_bci -1
    to_bci -1
    predecessors 
    successors 
    xhandlers
    flags 
    probability 4607182418800017408
    begin_IR
      LIR
      nr    0  <|@ instruction [rsi|QWORD[.], rdx|DWORD, rbp|QWORD] = LABEL numbPhis: 0 align: false label: ? <|@ <|@
      nr    2  <|@ instruction stack:16|QWORD = MOVE rbp|QWORD moveKind: QWORD <|@ <|@
      nr    4  <|@ instruction [] = HOTSPOTLOCKSTACK frameMapBuilder: org.graalvm.compiler.lir.amd64.AMD64FrameMapBuilder@13f368da8 slotKind: QWORD <|@ <|@
      nr    6  <|@ instruction v0|QWORD[.] = MOVE rsi|QWORD[.] moveKind: QWORD <|@ <|@
      nr    8  <|@ instruction v1|DWORD = MOVE rdx|DWORD moveKind: DWORD <|@ <|@
      nr   10  <|@ st <@st|@live-base-pointers: []
JavaExamples.exampleSimpleCall(JavaExamples.java:104) [bci: 0]
locals: Object[null] v1|DWORD 
>@ <|@ instruction NULLCHECK [v0|QWORD[.]] state [bci:0] <|@ <|@
      nr   12  <|@ instruction rsi|QWORD[.] = MOVE v0|QWORD[.] moveKind: QWORD <|@ <|@
      nr   14  <|@ instruction rdx|DWORD = MOVE v1|DWORD moveKind: DWORD <|@ <|@
      nr   16  <|@ st <@st|@live-base-pointers: []
JavaExamples.exampleSimpleCall(JavaExamples.java:104) [bci: 2]
locals: - - 
>@ <|@ instruction rax|DWORD = CALL_DIRECT [rsi|QWORD[.], rdx|DWORD] [] callTarget: HotSpotMethod<JavaExamples$ExampleObject.instanceCall(int)> invokeKind: Special config: org.graalvm.compiler.hotspot.GraalHotSpotVMConfig@147e07170 state [bci:2] <|@ <|@
      nr   18  <|@ instruction v2|DWORD = MOVE rax|DWORD moveKind: DWORD <|@ <|@
      nr   20  <|@ instruction rax|DWORD = MOVE v2|DWORD moveKind: DWORD <|@ <|@
      nr   22  <|@ instruction RETURN (savedRbp: stack:16|QWORD, value: rax|DWORD) isStub: false requiresReservedStackAccessCheck: false thread: r15 scratchForSafepointOnReturn: rcx config: org.graalvm.compiler.hotspot.GraalHotSpotVMConfig@147e07170 <|@ <|@
    end_IR
  end_block
end_cfg
begin_bytecodes
     0: aload_0       
     1: iload_1       
     2: invokevirtual #50         // JavaExamples$ExampleObject.instanceCall:(int)int
     5: ireturn       
   <|@
end_bytecodes
begin_cfg
  name "After LinearScanAssignLocations"
  begin_block
    name "B0"
    from_bci -1
    to_bci -1
    predecessors 
    successors 
    xhandlers
    flags 
    probability 4607182418800017408
    begin_IR
      LIR
      nr    0  <|@ instruction [rsi|QWORD[.], rdx|DWORD, rbp|QWORD] = LABEL numbPhis: 0 align: false label: ? <|@ <|@
      nr    2  <|@ instruction stack:16|QWORD = MOVE rbp|QWORD moveKind: QWORD <|@ <|@
      nr    4  <|@ instruction [] = HOTSPOTLOCKSTACK frameMapBuilder: org.graalvm.compiler.lir.amd64.AMD64FrameMapBuilder@13f368da8 slotKind: QWORD <|@ <|@
      nr   10  <|@ st <@st|@live-base-pointers: []
JavaExamples.exampleSimpleCall(JavaExamples.java:104) [bci: 0]
locals: Object[null] rdx|DWORD 
>@ <|@ instruction NULLCHECK [rsi|QWORD[.]] state [bci:0] <|@ <|@
      nr   16  <|@ st <@st|@live-base-pointers: []
JavaExamples.exampleSimpleCall(JavaExamples.java:104) [bci: 2]
locals: - - 
>@ <|@ instruction rax|DWORD = CALL_DIRECT [rsi|QWORD[.], rdx|DWORD] [] callTarget: HotSpotMethod<JavaExamples$ExampleObject.instanceCall(int)> invokeKind: Special config: org.graalvm.compiler.hotspot.GraalHotSpotVMConfig@147e07170 state [bci:2] <|@ <|@
      nr   22  <|@ instruction RETURN (savedRbp: stack:16|QWORD, value: rax|DWORD) isStub: false requiresReservedStackAccessCheck: false thread: r15 scratchForSafepointOnReturn: rcx config: org.graalvm.compiler.hotspot.GraalHotSpotVMConfig@147e07170 <|@ <|@
    end_IR
  end_block
end_cfg
begin_bytecodes
     0: aload_0       
     1: iload_1       
     2: invokevirtual #50         // JavaExamples$ExampleObject.instanceCall:(int)int
     5: ireturn       
   <|@
end_bytecodes
begin_cfg
  name "After LinearScan"
  begin_block
    name "B0"
    from_bci -1
    to_bci -1
    predecessors 
    successors 
    xhandlers
    flags 
    probability 4607182418800017408
    begin_IR
      LIR
      nr    0  <|@ instruction [rsi|QWORD[.], rdx|DWORD, rbp|QWORD] = LABEL numbPhis: 0 align: false label: ? <|@ <|@
      nr    2  <|@ instruction stack:16|QWORD = MOVE rbp|QWORD moveKind: QWORD <|@ <|@
      nr    4  <|@ instruction [] = HOTSPOTLOCKSTACK frameMapBuilder: org.graalvm.compiler.lir.amd64.AMD64FrameMapBuilder@13f368da8 slotKind: QWORD <|@ <|@
      nr   10  <|@ st <@st|@live-base-pointers: []
JavaExamples.exampleSimpleCall(JavaExamples.java:104) [bci: 0]
locals: Object[null] rdx|DWORD 
>@ <|@ instruction NULLCHECK [rsi|QWORD[.]] state [bci:0] <|@ <|@
      nr   16  <|@ st <@st|@live-base-pointers: []
JavaExamples.exampleSimpleCall(JavaExamples.java:104) [bci: 2]
locals: - - 
>@ <|@ instruction rax|DWORD = CALL_DIRECT [rsi|QWORD[.], rdx|DWORD] [] callTarget: HotSpotMethod<JavaExamples$ExampleObject.instanceCall(int)> invokeKind: Special config: org.graalvm.compiler.hotspot.GraalHotSpotVMConfig@147e07170 state [bci:2] <|@ <|@
      nr   22  <|@ instruction RETURN (savedRbp: stack:16|QWORD, value: rax|DWORD) isStub: false requiresReservedStackAccessCheck: false thread: r15 scratchForSafepointOnReturn: rcx config: org.graalvm.compiler.hotspot.GraalHotSpotVMConfig@147e07170 <|@ <|@
    end_IR
  end_block
end_cfg
begin_bytecodes
     0: aload_0       
     1: iload_1       
     2: invokevirtual #50         // JavaExamples$ExampleObject.instanceCall:(int)int
     5: ireturn       
   <|@
end_bytecodes
begin_cfg
  name "After LSStackSlotAllocator"
  begin_block
    name "B0"
    from_bci -1
    to_bci -1
    predecessors 
    successors 
    xhandlers
    flags 
    probability 4607182418800017408
    begin_IR
      LIR
      nr    0  <|@ instruction [rsi|QWORD[.], rdx|DWORD, rbp|QWORD] = LABEL numbPhis: 0 align: false label: ? <|@ <|@
      nr    2  <|@ instruction stack:16|QWORD = MOVE rbp|QWORD moveKind: QWORD <|@ <|@
      nr    4  <|@ instruction [] = HOTSPOTLOCKSTACK frameMapBuilder: org.graalvm.compiler.lir.amd64.AMD64FrameMapBuilder@13f368da8 slotKind: QWORD <|@ <|@
      nr   10  <|@ st <@st|@live-base-pointers: []
JavaExamples.exampleSimpleCall(JavaExamples.java:104) [bci: 0]
locals: Object[null] rdx|DWORD 
>@ <|@ instruction NULLCHECK [rsi|QWORD[.]] state [bci:0] <|@ <|@
      nr   16  <|@ st <@st|@live-base-pointers: []
JavaExamples.exampleSimpleCall(JavaExamples.java:104) [bci: 2]
locals: - - 
>@ <|@ instruction rax|DWORD = CALL_DIRECT [rsi|QWORD[.], rdx|DWORD] [] callTarget: HotSpotMethod<JavaExamples$ExampleObject.instanceCall(int)> invokeKind: Special config: org.graalvm.compiler.hotspot.GraalHotSpotVMConfig@147e07170 state [bci:2] <|@ <|@
      nr   22  <|@ instruction RETURN (savedRbp: stack:16|QWORD, value: rax|DWORD) isStub: false requiresReservedStackAccessCheck: false thread: r15 scratchForSafepointOnReturn: rcx config: org.graalvm.compiler.hotspot.GraalHotSpotVMConfig@147e07170 <|@ <|@
    end_IR
  end_block
end_cfg
begin_bytecodes
     0: aload_0       
     1: iload_1       
     2: invokevirtual #50         // JavaExamples$ExampleObject.instanceCall:(int)int
     5: ireturn       
   <|@
end_bytecodes
begin_cfg
  name "After LocationMarker"
  begin_block
    name "B0"
    from_bci -1
    to_bci -1
    predecessors 
    successors 
    xhandlers
    flags 
    probability 4607182418800017408
    begin_IR
      LIR
      nr    0  <|@ instruction [rsi|QWORD[.], rdx|DWORD, rbp|QWORD] = LABEL numbPhis: 0 align: false label: ? <|@ <|@
      nr    2  <|@ instruction stack:16|QWORD = MOVE rbp|QWORD moveKind: QWORD <|@ <|@
      nr    4  <|@ instruction [] = HOTSPOTLOCKSTACK frameMapBuilder: org.graalvm.compiler.lir.amd64.AMD64FrameMapBuilder@13f368da8 slotKind: QWORD <|@ <|@
      nr   10  <|@ st <@st|@reference-map: [rsi:0]
live-base-pointers: []
JavaExamples.exampleSimpleCall(JavaExamples.java:104) [bci: 0]
locals: Object[null] rdx|DWORD 
>@ <|@ instruction NULLCHECK [rsi|QWORD[.]] state [bci:0] <|@ <|@
      nr   16  <|@ st <@st|@reference-map: []
live-base-pointers: []
JavaExamples.exampleSimpleCall(JavaExamples.java:104) [bci: 2]
locals: - - 
>@ <|@ instruction rax|DWORD = CALL_DIRECT [rsi|QWORD[.], rdx|DWORD] [] callTarget: HotSpotMethod<JavaExamples$ExampleObject.instanceCall(int)> invokeKind: Special config: org.graalvm.compiler.hotspot.GraalHotSpotVMConfig@147e07170 state [bci:2] <|@ <|@
      nr   22  <|@ instruction RETURN (savedRbp: stack:16|QWORD, value: rax|DWORD) isStub: false requiresReservedStackAccessCheck: false thread: r15 scratchForSafepointOnReturn: rcx config: org.graalvm.compiler.hotspot.GraalHotSpotVMConfig@147e07170 <|@ <|@
    end_IR
  end_block
end_cfg
begin_bytecodes
     0: aload_0       
     1: iload_1       
     2: invokevirtual #50         // JavaExamples$ExampleObject.instanceCall:(int)int
     5: ireturn       
   <|@
end_bytecodes
begin_cfg
  name "After AllocationStage"
  begin_block
    name "B0"
    from_bci -1
    to_bci -1
    predecessors 
    successors 
    xhandlers
    flags 
    probability 4607182418800017408
    begin_IR
      LIR
      nr    0  <|@ instruction [rsi|QWORD[.], rdx|DWORD, rbp|QWORD] = LABEL numbPhis: 0 align: false label: ? <|@ <|@
      nr    2  <|@ instruction stack:16|QWORD = MOVE rbp|QWORD moveKind: QWORD <|@ <|@
      nr    4  <|@ instruction [] = HOTSPOTLOCKSTACK frameMapBuilder: org.graalvm.compiler.lir.amd64.AMD64FrameMapBuilder@13f368da8 slotKind: QWORD <|@ <|@
      nr   10  <|@ st <@st|@reference-map: [rsi:0]
live-base-pointers: []
JavaExamples.exampleSimpleCall(JavaExamples.java:104) [bci: 0]
locals: Object[null] rdx|DWORD 
>@ <|@ instruction NULLCHECK [rsi|QWORD[.]] state [bci:0] <|@ <|@
      nr   16  <|@ st <@st|@reference-map: []
live-base-pointers: []
JavaExamples.exampleSimpleCall(JavaExamples.java:104) [bci: 2]
locals: - - 
>@ <|@ instruction rax|DWORD = CALL_DIRECT [rsi|QWORD[.], rdx|DWORD] [] callTarget: HotSpotMethod<JavaExamples$ExampleObject.instanceCall(int)> invokeKind: Special config: org.graalvm.compiler.hotspot.GraalHotSpotVMConfig@147e07170 state [bci:2] <|@ <|@
      nr   22  <|@ instruction RETURN (savedRbp: stack:16|QWORD, value: rax|DWORD) isStub: false requiresReservedStackAccessCheck: false thread: r15 scratchForSafepointOnReturn: rcx config: org.graalvm.compiler.hotspot.GraalHotSpotVMConfig@147e07170 <|@ <|@
    end_IR
  end_block
end_cfg
begin_bytecodes
     0: aload_0       
     1: iload_1       
     2: invokevirtual #50         // JavaExamples$ExampleObject.instanceCall:(int)int
     5: ireturn       
   <|@
end_bytecodes
begin_cfg
  name "After EdgeMoveOptimizer"
  begin_block
    name "B0"
    from_bci -1
    to_bci -1
    predecessors 
    successors 
    xhandlers
    flags 
    probability 4607182418800017408
    begin_IR
      LIR
      nr    0  <|@ instruction [rsi|QWORD[.], rdx|DWORD, rbp|QWORD] = LABEL numbPhis: 0 align: false label: ? <|@ <|@
      nr    2  <|@ instruction stack:16|QWORD = MOVE rbp|QWORD moveKind: QWORD <|@ <|@
      nr    4  <|@ instruction [] = HOTSPOTLOCKSTACK frameMapBuilder: org.graalvm.compiler.lir.amd64.AMD64FrameMapBuilder@13f368da8 slotKind: QWORD <|@ <|@
      nr   10  <|@ st <@st|@reference-map: [rsi:0]
live-base-pointers: []
JavaExamples.exampleSimpleCall(JavaExamples.java:104) [bci: 0]
locals: Object[null] rdx|DWORD 
>@ <|@ instruction NULLCHECK [rsi|QWORD[.]] state [bci:0] <|@ <|@
      nr   16  <|@ st <@st|@reference-map: []
live-base-pointers: []
JavaExamples.exampleSimpleCall(JavaExamples.java:104) [bci: 2]
locals: - - 
>@ <|@ instruction rax|DWORD = CALL_DIRECT [rsi|QWORD[.], rdx|DWORD] [] callTarget: HotSpotMethod<JavaExamples$ExampleObject.instanceCall(int)> invokeKind: Special config: org.graalvm.compiler.hotspot.GraalHotSpotVMConfig@147e07170 state [bci:2] <|@ <|@
      nr   22  <|@ instruction RETURN (savedRbp: stack:16|QWORD, value: rax|DWORD) isStub: false requiresReservedStackAccessCheck: false thread: r15 scratchForSafepointOnReturn: rcx config: org.graalvm.compiler.hotspot.GraalHotSpotVMConfig@147e07170 <|@ <|@
    end_IR
  end_block
end_cfg
begin_bytecodes
     0: aload_0       
     1: iload_1       
     2: invokevirtual #50         // JavaExamples$ExampleObject.instanceCall:(int)int
     5: ireturn       
   <|@
end_bytecodes
begin_cfg
  name "After ControlFlowOptimizer"
  begin_block
    name "B0"
    from_bci -1
    to_bci -1
    predecessors 
    successors 
    xhandlers
    flags 
    probability 4607182418800017408
    begin_IR
      LIR
      nr    0  <|@ instruction [rsi|QWORD[.], rdx|DWORD, rbp|QWORD] = LABEL numbPhis: 0 align: false label: ? <|@ <|@
      nr    2  <|@ instruction stack:16|QWORD = MOVE rbp|QWORD moveKind: QWORD <|@ <|@
      nr    4  <|@ instruction [] = HOTSPOTLOCKSTACK frameMapBuilder: org.graalvm.compiler.lir.amd64.AMD64FrameMapBuilder@13f368da8 slotKind: QWORD <|@ <|@
      nr   10  <|@ st <@st|@reference-map: [rsi:0]
live-base-pointers: []
JavaExamples.exampleSimpleCall(JavaExamples.java:104) [bci: 0]
locals: Object[null] rdx|DWORD 
>@ <|@ instruction NULLCHECK [rsi|QWORD[.]] state [bci:0] <|@ <|@
      nr   16  <|@ st <@st|@reference-map: []
live-base-pointers: []
JavaExamples.exampleSimpleCall(JavaExamples.java:104) [bci: 2]
locals: - - 
>@ <|@ instruction rax|DWORD = CALL_DIRECT [rsi|QWORD[.], rdx|DWORD] [] callTarget: HotSpotMethod<JavaExamples$ExampleObject.instanceCall(int)> invokeKind: Special config: org.graalvm.compiler.hotspot.GraalHotSpotVMConfig@147e07170 state [bci:2] <|@ <|@
      nr   22  <|@ instruction RETURN (savedRbp: stack:16|QWORD, value: rax|DWORD) isStub: false requiresReservedStackAccessCheck: false thread: r15 scratchForSafepointOnReturn: rcx config: org.graalvm.compiler.hotspot.GraalHotSpotVMConfig@147e07170 <|@ <|@
    end_IR
  end_block
end_cfg
begin_bytecodes
     0: aload_0       
     1: iload_1       
     2: invokevirtual #50         // JavaExamples$ExampleObject.instanceCall:(int)int
     5: ireturn       
   <|@
end_bytecodes
begin_cfg
  name "After RedundantMoveElimination"
  begin_block
    name "B0"
    from_bci -1
    to_bci -1
    predecessors 
    successors 
    xhandlers
    flags 
    probability 4607182418800017408
    begin_IR
      LIR
      nr    0  <|@ instruction [rsi|QWORD[.], rdx|DWORD, rbp|QWORD] = LABEL numbPhis: 0 align: false label: ? <|@ <|@
      nr    2  <|@ instruction stack:16|QWORD = MOVE rbp|QWORD moveKind: QWORD <|@ <|@
      nr    4  <|@ instruction [] = HOTSPOTLOCKSTACK frameMapBuilder: org.graalvm.compiler.lir.amd64.AMD64FrameMapBuilder@13f368da8 slotKind: QWORD <|@ <|@
      nr   10  <|@ st <@st|@reference-map: [rsi:0]
live-base-pointers: []
JavaExamples.exampleSimpleCall(JavaExamples.java:104) [bci: 0]
locals: Object[null] rdx|DWORD 
>@ <|@ instruction NULLCHECK [rsi|QWORD[.]] state [bci:0] <|@ <|@
      nr   16  <|@ st <@st|@reference-map: []
live-base-pointers: []
JavaExamples.exampleSimpleCall(JavaExamples.java:104) [bci: 2]
locals: - - 
>@ <|@ instruction rax|DWORD = CALL_DIRECT [rsi|QWORD[.], rdx|DWORD] [] callTarget: HotSpotMethod<JavaExamples$ExampleObject.instanceCall(int)> invokeKind: Special config: org.graalvm.compiler.hotspot.GraalHotSpotVMConfig@147e07170 state [bci:2] <|@ <|@
      nr   22  <|@ instruction RETURN (savedRbp: stack:16|QWORD, value: rax|DWORD) isStub: false requiresReservedStackAccessCheck: false thread: r15 scratchForSafepointOnReturn: rcx config: org.graalvm.compiler.hotspot.GraalHotSpotVMConfig@147e07170 <|@ <|@
    end_IR
  end_block
end_cfg
begin_bytecodes
     0: aload_0       
     1: iload_1       
     2: invokevirtual #50         // JavaExamples$ExampleObject.instanceCall:(int)int
     5: ireturn       
   <|@
end_bytecodes
begin_cfg
  name "After NullCheckOptimizer"
  begin_block
    name "B0"
    from_bci -1
    to_bci -1
    predecessors 
    successors 
    xhandlers
    flags 
    probability 4607182418800017408
    begin_IR
      LIR
      nr    0  <|@ instruction [rsi|QWORD[.], rdx|DWORD, rbp|QWORD] = LABEL numbPhis: 0 align: false label: ? <|@ <|@
      nr    2  <|@ instruction stack:16|QWORD = MOVE rbp|QWORD moveKind: QWORD <|@ <|@
      nr    4  <|@ instruction [] = HOTSPOTLOCKSTACK frameMapBuilder: org.graalvm.compiler.lir.amd64.AMD64FrameMapBuilder@13f368da8 slotKind: QWORD <|@ <|@
      nr   10  <|@ st <@st|@reference-map: [rsi:0]
live-base-pointers: []
JavaExamples.exampleSimpleCall(JavaExamples.java:104) [bci: 0]
locals: Object[null] rdx|DWORD 
>@ <|@ instruction NULLCHECK [rsi|QWORD[.]] state [bci:0] <|@ <|@
      nr   16  <|@ st <@st|@reference-map: []
live-base-pointers: []
JavaExamples.exampleSimpleCall(JavaExamples.java:104) [bci: 2]
locals: - - 
>@ <|@ instruction rax|DWORD = CALL_DIRECT [rsi|QWORD[.], rdx|DWORD] [] callTarget: HotSpotMethod<JavaExamples$ExampleObject.instanceCall(int)> invokeKind: Special config: org.graalvm.compiler.hotspot.GraalHotSpotVMConfig@147e07170 state [bci:2] <|@ <|@
      nr   22  <|@ instruction RETURN (savedRbp: stack:16|QWORD, value: rax|DWORD) isStub: false requiresReservedStackAccessCheck: false thread: r15 scratchForSafepointOnReturn: rcx config: org.graalvm.compiler.hotspot.GraalHotSpotVMConfig@147e07170 <|@ <|@
    end_IR
  end_block
end_cfg
begin_bytecodes
     0: aload_0       
     1: iload_1       
     2: invokevirtual #50         // JavaExamples$ExampleObject.instanceCall:(int)int
     5: ireturn       
   <|@
end_bytecodes
begin_cfg
  name "After StackMoveOptimization"
  begin_block
    name "B0"
    from_bci -1
    to_bci -1
    predecessors 
    successors 
    xhandlers
    flags 
    probability 4607182418800017408
    begin_IR
      LIR
      nr    0  <|@ instruction [rsi|QWORD[.], rdx|DWORD, rbp|QWORD] = LABEL numbPhis: 0 align: false label: ? <|@ <|@
      nr    2  <|@ instruction stack:16|QWORD = MOVE rbp|QWORD moveKind: QWORD <|@ <|@
      nr    4  <|@ instruction [] = HOTSPOTLOCKSTACK frameMapBuilder: org.graalvm.compiler.lir.amd64.AMD64FrameMapBuilder@13f368da8 slotKind: QWORD <|@ <|@
      nr   10  <|@ st <@st|@reference-map: [rsi:0]
live-base-pointers: []
JavaExamples.exampleSimpleCall(JavaExamples.java:104) [bci: 0]
locals: Object[null] rdx|DWORD 
>@ <|@ instruction NULLCHECK [rsi|QWORD[.]] state [bci:0] <|@ <|@
      nr   16  <|@ st <@st|@reference-map: []
live-base-pointers: []
JavaExamples.exampleSimpleCall(JavaExamples.java:104) [bci: 2]
locals: - - 
>@ <|@ instruction rax|DWORD = CALL_DIRECT [rsi|QWORD[.], rdx|DWORD] [] callTarget: HotSpotMethod<JavaExamples$ExampleObject.instanceCall(int)> invokeKind: Special config: org.graalvm.compiler.hotspot.GraalHotSpotVMConfig@147e07170 state [bci:2] <|@ <|@
      nr   22  <|@ instruction RETURN (savedRbp: stack:16|QWORD, value: rax|DWORD) isStub: false requiresReservedStackAccessCheck: false thread: r15 scratchForSafepointOnReturn: rcx config: org.graalvm.compiler.hotspot.GraalHotSpotVMConfig@147e07170 <|@ <|@
    end_IR
  end_block
end_cfg
begin_bytecodes
     0: aload_0       
     1: iload_1       
     2: invokevirtual #50         // JavaExamples$ExampleObject.instanceCall:(int)int
     5: ireturn       
   <|@
end_bytecodes
begin_cfg
  name "After PostAllocationOptimizationStage"
  begin_block
    name "B0"
    from_bci -1
    to_bci -1
    predecessors 
    successors 
    xhandlers
    flags 
    probability 4607182418800017408
    begin_IR
      LIR
      nr    0  <|@ instruction [rsi|QWORD[.], rdx|DWORD, rbp|QWORD] = LABEL numbPhis: 0 align: false label: ? <|@ <|@
      nr    2  <|@ instruction stack:16|QWORD = MOVE rbp|QWORD moveKind: QWORD <|@ <|@
      nr    4  <|@ instruction [] = HOTSPOTLOCKSTACK frameMapBuilder: org.graalvm.compiler.lir.amd64.AMD64FrameMapBuilder@13f368da8 slotKind: QWORD <|@ <|@
      nr   10  <|@ st <@st|@reference-map: [rsi:0]
live-base-pointers: []
JavaExamples.exampleSimpleCall(JavaExamples.java:104) [bci: 0]
locals: Object[null] rdx|DWORD 
>@ <|@ instruction NULLCHECK [rsi|QWORD[.]] state [bci:0] <|@ <|@
      nr   16  <|@ st <@st|@reference-map: []
live-base-pointers: []
JavaExamples.exampleSimpleCall(JavaExamples.java:104) [bci: 2]
locals: - - 
>@ <|@ instruction rax|DWORD = CALL_DIRECT [rsi|QWORD[.], rdx|DWORD] [] callTarget: HotSpotMethod<JavaExamples$ExampleObject.instanceCall(int)> invokeKind: Special config: org.graalvm.compiler.hotspot.GraalHotSpotVMConfig@147e07170 state [bci:2] <|@ <|@
      nr   22  <|@ instruction RETURN (savedRbp: stack:16|QWORD, value: rax|DWORD) isStub: false requiresReservedStackAccessCheck: false thread: r15 scratchForSafepointOnReturn: rcx config: org.graalvm.compiler.hotspot.GraalHotSpotVMConfig@147e07170 <|@ <|@
    end_IR
  end_block
end_cfg
begin_bytecodes
     0: aload_0       
     1: iload_1       
     2: invokevirtual #50         // JavaExamples$ExampleObject.instanceCall:(int)int
     5: ireturn       
   <|@
end_bytecodes
begin_cfg
  name "After code generation"
end_cfg
begin_nmethod
  <<<HexCodeFile
  Platform AMD64 64  <||@
  HexCode 0 89842400c0feff4883ec1848896c241085060f1f440000e80000000090488b6c24104883c418850500000000c5f877c3e80000000090e80000000090  <||@
  Comment 0 [stack overflow check]  <||@
  Comment 0 3  <||@
  Comment 0 1  <||@
  Comment 11 block B0 null  <||@
  Comment 11 0 [rsi|QWORD[.], rdx|DWORD, rbp|QWORD] = LABEL numbPhis: 0 align: false label: ?  <||@
  Comment 11 2 stack:16|QWORD = MOVE rbp|QWORD moveKind: QWORD  <||@
  Comment 16 4 [] = HOTSPOTLOCKSTACK frameMapBuilder: org.graalvm.compiler.lir.amd64.AMD64FrameMapBuilder@13f368da8 slotKind: QWORD  <||@
  Comment 16 10 NULLCHECK [rsi|QWORD[.]] state [bci:0]  <||@
  Comment 16 [rsi:0]at JavaExamples.exampleSimpleCall(JavaExamples.java:104) [bci: 0, duringCall: false, rethrow: false]
              |0             |1         
     locals:  |Object[null]  |rdx|DWORD   <||@
  Comment 16 {infopoint: IMPLICIT_EXCEPTION}  <||@
  Comment 18 16 rax|DWORD = CALL_DIRECT [rsi|QWORD[.], rdx|DWORD] [] callTarget: HotSpotMethod<JavaExamples$ExampleObject.instanceCall(int)> invokeKind: Special config: org.graalvm.compiler.hotspot.GraalHotSpotVMConfig@147e07170 state [bci:2]  <||@
  Comment 18 9  <||@
  Comment 23 {HotSpotMethod<JavaExamples$ExampleObject.instanceCall(int)>}  <||@
  Comment 28 []at JavaExamples.exampleSimpleCall(JavaExamples.java:104) [bci: 2, duringCall: true, rethrow: false]
              |0  |1 
     locals:  |-  |-   <||@
  Comment 29 22 RETURN (savedRbp: stack:16|QWORD, value: rax|DWORD) isStub: false requiresReservedStackAccessCheck: false thread: r15 scratchForSafepointOnReturn: rcx config: org.graalvm.compiler.hotspot.GraalHotSpotVMConfig@147e07170  <||@
  Comment 38 12  <||@
  Comment 48 {Stub<ExceptionHandlerStub.exceptionHandler>@0x112e24320:CallingConvention[rax|QWORD[.], rdx|QWORD]:CallingConvention[rax|QWORD[.], rdx|QWORD]; temps=rdi|ILLEGAL,xmm14|ILLEGAL,xmm15|ILLEGAL,xmm12|ILLEGAL,xmm13|ILLEGAL,xmm10|ILLEGAL,xmm11|ILLEGAL,xmm7|ILLEGAL,xmm8|ILLEGAL,xmm9|ILLEGAL,xmm0|ILLEGAL,xmm1|ILLEGAL,xmm2|ILLEGAL,xmm3|ILLEGAL,xmm4|ILLEGAL,xmm5|ILLEGAL,xmm6|ILLEGAL,rax|ILLEGAL,rcx|ILLEGAL,rdx|ILLEGAL,rsi|ILLEGAL,r8|ILLEGAL,r9|ILLEGAL,r10|ILLEGAL,r11|ILLEGAL}  <||@
  Comment 48 4  <||@
  Comment 54 {Field[name=CompilerToVM::Data::SharedRuntime_deopt_blob_unpack, type=address, offset=0, address=0x1108bc128, value=4610474560]:0x112ce4240}  <||@
  Comment 54 5  <||@
  HexCodeFile>>> <|@
end_nmethod
begin_compilation
  name " HotSpotCompilation-349[JavaExamples.exampleSimpleCall(JavaExamples$ExampleObject, int)]"
  method "HotSpotCompilation-349[JavaExamples.exampleSimpleCall(JavaExamples$ExampleObject, int)]"
  date 1583364091828
end_compilation
begin_cfg
  name "After code installation"
end_cfg
begin_nmethod
  <<<HexCodeFile
  Platform AMD64 64  <||@
  HexCode 112e34560 89842400c0feff4883ec1848896c241085060f1f440000e884d2ffff90488b6c24104883c41885057a6a93fbc5f877c3e88bfdfeff90e8a5fceaff90f4f4f4f448bb0000000000000000e9fbfffffff4  <||@
  Comment 0 [stack overflow check]  <||@
  Comment 0 3  <||@
  Comment 0 1  <||@
  Comment 11 block B0 null  <||@
  Comment 11 0 [rsi|QWORD[.], rdx|DWORD, rbp|QWORD] = LABEL numbPhis: 0 align: false label: ?  <||@
  Comment 11 2 stack:16|QWORD = MOVE rbp|QWORD moveKind: QWORD  <||@
  Comment 16 4 [] = HOTSPOTLOCKSTACK frameMapBuilder: org.graalvm.compiler.lir.amd64.AMD64FrameMapBuilder@13f368da8 slotKind: QWORD  <||@
  Comment 16 10 NULLCHECK [rsi|QWORD[.]] state [bci:0]  <||@
  Comment 16 [rsi:0]at JavaExamples.exampleSimpleCall(JavaExamples.java:104) [bci: 0, duringCall: false, rethrow: false]
              |0             |1         
     locals:  |Object[null]  |rdx|DWORD   <||@
  Comment 16 {infopoint: IMPLICIT_EXCEPTION}  <||@
  Comment 18 16 rax|DWORD = CALL_DIRECT [rsi|QWORD[.], rdx|DWORD] [] callTarget: HotSpotMethod<JavaExamples$ExampleObject.instanceCall(int)> invokeKind: Special config: org.graalvm.compiler.hotspot.GraalHotSpotVMConfig@147e07170 state [bci:2]  <||@
  Comment 18 9  <||@
  Comment 23 {HotSpotMethod<JavaExamples$ExampleObject.instanceCall(int)>}  <||@
  Comment 28 []at JavaExamples.exampleSimpleCall(JavaExamples.java:104) [bci: 2, duringCall: true, rethrow: false]
              |0  |1 
     locals:  |-  |-   <||@
  Comment 29 22 RETURN (savedRbp: stack:16|QWORD, value: rax|DWORD) isStub: false requiresReservedStackAccessCheck: false thread: r15 scratchForSafepointOnReturn: rcx config: org.graalvm.compiler.hotspot.GraalHotSpotVMConfig@147e07170  <||@
  Comment 38 12  <||@
  Comment 48 {Stub<ExceptionHandlerStub.exceptionHandler>@0x112e24320:CallingConvention[rax|QWORD[.], rdx|QWORD]:CallingConvention[rax|QWORD[.], rdx|QWORD]; temps=rdi|ILLEGAL,xmm14|ILLEGAL,xmm15|ILLEGAL,xmm12|ILLEGAL,xmm13|ILLEGAL,xmm10|ILLEGAL,xmm11|ILLEGAL,xmm7|ILLEGAL,xmm8|ILLEGAL,xmm9|ILLEGAL,xmm0|ILLEGAL,xmm1|ILLEGAL,xmm2|ILLEGAL,xmm3|ILLEGAL,xmm4|ILLEGAL,xmm5|ILLEGAL,xmm6|ILLEGAL,rax|ILLEGAL,rcx|ILLEGAL,rdx|ILLEGAL,rsi|ILLEGAL,r8|ILLEGAL,r9|ILLEGAL,r10|ILLEGAL,r11|ILLEGAL}  <||@
  Comment 48 4  <||@
  Comment 54 {Field[name=CompilerToVM::Data::SharedRuntime_deopt_blob_unpack, type=address, offset=0, address=0x1108bc128, value=4610474560]:0x112ce4240}  <||@
  Comment 54 5  <||@
  HexCodeFile>>> <|@
end_nmethod
