begin_compilation
  name " HotSpotCompilation-138[JavaExamples.exampleFieldWrite(JavaExamples$ExampleObject, int)]"
  method "HotSpotCompilation-138[JavaExamples.exampleFieldWrite(JavaExamples$ExampleObject, int)]"
  date 1612307469635
end_compilation
begin_cfg
  name "Final HIR schedule"
  begin_block
    name "B0"
    from_bci -1
    to_bci -1
    predecessors 
    successors 
    xhandlers
    flags 
    probability 4607182418800017408
    begin_IR
      HIR
f <@#|@fixed with next>@ <|@
tid v0 <|@
d <@d|@=== Debug Properties ===
hasSpeculationFence: false
stamp: void
=== Inputs ===
stateAfter: - 
=== Succesors ===
next: v12 
=== Usages ===
=== Predecessor ===
- >@ <|@
instruction <@StartNode|@org.graalvm.compiler.nodes.StartNode>@ stateAfter: - #next: v12  <|@  <|@
f <@~|@floating>@ <|@
tid a17 <|@
d <@d|@=== Debug Properties ===
isDefaultStable: false
rawvalue: null
stableDimension: 0
stamp: a - NULL
stampKind: a -
value: Object[null]
=== Inputs ===
=== Succesors ===
=== Usages ===
?3 
=== Predecessor ===
- >@ <|@
instruction <@Constant|@org.graalvm.compiler.nodes.ConstantNode>@  <|@  <|@
f <@~|@floating>@ <|@
tid i2 <|@
d <@d|@=== Debug Properties ===
index: 1
stamp: i32
uncheckedStamp: [null]
=== Inputs ===
=== Succesors ===
=== Usages ===
?3 v12 
=== Predecessor ===
- >@ <|@
instruction <@Parameter|@org.graalvm.compiler.nodes.ParameterNode>@  <|@  <|@
tid ?3 <|@
d <@d|@=== Debug Properties ===
bci: 0
code: ResolvedJavaMethodBytecode<JavaExamples.exampleFieldWrite(JavaExamples$ExampleObject, int)>
duringCall: false
localsSize: 2
locksSize: 0
rethrowException: false
sourceFile: JavaExamples.java
sourceLine: 304
stackSize: 0
=== Inputs ===
outerFrameState: - 
values: a17 i2 
=== Succesors ===
=== Usages ===
v12 
=== Predecessor ===
- >@ <|@
instruction <@FrameState|@org.graalvm.compiler.nodes.FrameState>@ outerFrameState: - values: a17 i2  <|@  <|@
f <@~|@floating>@ <|@
tid a1 <|@
d <@d|@=== Debug Properties ===
index: 0
stamp: a# LJavaExamples$ExampleObject;
uncheckedStamp: [null]
=== Inputs ===
=== Succesors ===
=== Usages ===
v20 
=== Predecessor ===
- >@ <|@
instruction <@Parameter|@org.graalvm.compiler.nodes.ParameterNode>@  <|@  <|@
f <@~|@floating>@ <|@
tid v20 <|@
d <@d|@=== Debug Properties ===
displacement: 12
scale: Times1
stamp: void*
=== Inputs ===
base: a1 
index: - 
=== Succesors ===
=== Usages ===
v12 
=== Predecessor ===
- >@ <|@
instruction <@AMD64Address|@org.graalvm.compiler.core.amd64.AMD64AddressNode>@ base: a1 index: -  <|@  <|@
f <@#|@fixed with next>@ <|@
tid v12 <|@
d <@d|@=== Debug Properties ===
barrierType: NONE
deoptReasonAndAction: int[-2059|0xfffffffffffff7f5]
deoptSpeculation: long[0|0x0]
location: JavaExamples$ExampleObject.x
nodeSourcePosition: at JavaExamples.exampleFieldWrite(JavaExamples.java:304) [bci: 2]
nullCheck: true
stamp: void
=== Inputs ===
stateBefore: ?3 
guard: - 
address: v20 
lastLocationAccess: - 
value: i2 
stateAfter: - 
=== Succesors ===
next: v6 
=== Usages ===
=== Predecessor ===
v0 >@ <|@
instruction <@Write|@org.graalvm.compiler.nodes.memory.WriteNode>@ stateBefore: ?3 guard: - address: v20 lastLocationAccess: - value: i2 stateAfter: - #next: v6  <|@  <|@
f <@*|@fixed>@ <|@
tid v6 <|@
d <@d|@=== Debug Properties ===
nodeSourcePosition: at JavaExamples.exampleFieldWrite(JavaExamples.java:305) [bci: 5]
stamp: void
=== Inputs ===
result: - 
memoryMap: - 
=== Succesors ===
=== Usages ===
=== Predecessor ===
v12 >@ <|@
instruction <@Return|@org.graalvm.compiler.nodes.ReturnNode>@ result: - memoryMap: -  <|@  <|@
    end_IR
  end_block
end_cfg
begin_cfg
  name "After LIRGeneration"
  begin_block
    name "B0"
    from_bci -1
    to_bci -1
    predecessors 
    successors 
    xhandlers
    flags 
    probability 4607182418800017408
    begin_IR
      LIR
      nr   -1  <|@ instruction [rsi|QWORD[.], rdx|DWORD, rbp|QWORD] = LABEL numbPhis: 0 align: false label: ? <|@ <|@
      nr   -1  <|@ instruction stack:16|QWORD = MOVE rbp|QWORD moveKind: QWORD <|@ <|@
      nr   -1  <|@ instruction [] = HOTSPOTLOCKSTACK frameMapBuilder: org.graalvm.compiler.lir.amd64.AMD64FrameMapBuilder@7a6ad383 slotKind: QWORD <|@ <|@
      nr   -1  <|@ instruction v0|QWORD[.] = MOVE rsi|QWORD[.] moveKind: QWORD <|@ <|@
      nr   -1  <|@ instruction v1|DWORD = MOVE rdx|DWORD moveKind: DWORD <|@ <|@
      nr   -1  <|@ st <@st|@JavaExamples.exampleFieldWrite(JavaExamples.java:304) [bci: 0]
locals: Object[null] v1|DWORD 
>@ <|@ instruction MOV (x: [v0|QWORD[.] + 12], y: v1|DWORD) size: DWORD state [bci:0] <|@ <|@
      nr   -1  <|@ instruction RETURN (savedRbp: stack:16|QWORD, value: -) isStub: false requiresReservedStackAccessCheck: false thread: r15 scratchForSafepointOnReturn: rcx config: org.graalvm.compiler.hotspot.GraalHotSpotVMConfig@384cadad <|@ <|@
    end_IR
  end_block
end_cfg
begin_bytecodes
     0: aload_0       
     1: iload_1       
     2: putfield      #63         // JavaExamples$ExampleObject.x:int
     5: return        
   <|@
end_bytecodes
begin_cfg
  name "After LIR generation"
  begin_block
    name "B0"
    from_bci -1
    to_bci -1
    predecessors 
    successors 
    xhandlers
    flags 
    probability 4607182418800017408
    begin_IR
      HIR
f <@#|@fixed with next>@ <|@
tid v0 <|@
d <@d|@=== Debug Properties ===
hasSpeculationFence: false
stamp: void
=== Inputs ===
stateAfter: - 
=== Succesors ===
next: v12 
=== Usages ===
=== Predecessor ===
- >@ <|@
instruction <@StartNode|@org.graalvm.compiler.nodes.StartNode>@ stateAfter: - #next: v12  <|@  <|@
f <@~|@floating>@ <|@
tid a17 <|@
result Object[null] <|@
d <@d|@=== Debug Properties ===
isDefaultStable: false
rawvalue: null
stableDimension: 0
stamp: a - NULL
stampKind: a -
value: Object[null]
=== Inputs ===
=== Succesors ===
=== Usages ===
?3 
=== Predecessor ===
- >@ <|@
instruction <@Constant|@org.graalvm.compiler.nodes.ConstantNode>@  <|@  <|@
f <@~|@floating>@ <|@
tid i2 <|@
result v1|DWORD <|@
d <@d|@=== Debug Properties ===
index: 1
stamp: i32
uncheckedStamp: [null]
=== Inputs ===
=== Succesors ===
=== Usages ===
?3 v12 
=== Predecessor ===
- >@ <|@
instruction <@Parameter|@org.graalvm.compiler.nodes.ParameterNode>@  <|@  <|@
tid ?3 <|@
d <@d|@=== Debug Properties ===
bci: 0
code: ResolvedJavaMethodBytecode<JavaExamples.exampleFieldWrite(JavaExamples$ExampleObject, int)>
duringCall: false
localsSize: 2
locksSize: 0
rethrowException: false
sourceFile: JavaExamples.java
sourceLine: 304
stackSize: 0
=== Inputs ===
outerFrameState: - 
values: a17 i2 
=== Succesors ===
=== Usages ===
v12 
=== Predecessor ===
- >@ <|@
instruction <@FrameState|@org.graalvm.compiler.nodes.FrameState>@ outerFrameState: - values: a17 i2  <|@  <|@
f <@~|@floating>@ <|@
tid a1 <|@
result v0|QWORD[.] <|@
d <@d|@=== Debug Properties ===
index: 0
stamp: a# LJavaExamples$ExampleObject;
uncheckedStamp: [null]
=== Inputs ===
=== Succesors ===
=== Usages ===
v20 
=== Predecessor ===
- >@ <|@
instruction <@Parameter|@org.graalvm.compiler.nodes.ParameterNode>@  <|@  <|@
f <@~|@floating>@ <|@
tid v20 <|@
result [v0|QWORD[.] + 12] <|@
d <@d|@=== Debug Properties ===
displacement: 12
scale: Times1
stamp: void*
=== Inputs ===
base: a1 
index: - 
=== Succesors ===
=== Usages ===
v12 
=== Predecessor ===
- >@ <|@
instruction <@AMD64Address|@org.graalvm.compiler.core.amd64.AMD64AddressNode>@ base: a1 index: -  <|@  <|@
f <@#|@fixed with next>@ <|@
tid v12 <|@
d <@d|@=== Debug Properties ===
barrierType: NONE
deoptReasonAndAction: int[-2059|0xfffffffffffff7f5]
deoptSpeculation: long[0|0x0]
location: JavaExamples$ExampleObject.x
nodeSourcePosition: at JavaExamples.exampleFieldWrite(JavaExamples.java:304) [bci: 2]
nullCheck: true
stamp: void
=== Inputs ===
stateBefore: ?3 
guard: - 
address: v20 
lastLocationAccess: - 
value: i2 
stateAfter: - 
=== Succesors ===
next: v6 
=== Usages ===
=== Predecessor ===
v0 >@ <|@
instruction <@Write|@org.graalvm.compiler.nodes.memory.WriteNode>@ stateBefore: ?3 guard: - address: v20 lastLocationAccess: - value: i2 stateAfter: - #next: v6  <|@  <|@
f <@*|@fixed>@ <|@
tid v6 <|@
d <@d|@=== Debug Properties ===
nodeSourcePosition: at JavaExamples.exampleFieldWrite(JavaExamples.java:305) [bci: 5]
stamp: void
=== Inputs ===
result: - 
memoryMap: - 
=== Succesors ===
=== Usages ===
=== Predecessor ===
v12 >@ <|@
instruction <@Return|@org.graalvm.compiler.nodes.ReturnNode>@ result: - memoryMap: -  <|@  <|@
    end_IR
    begin_IR
      LIR
      nr   -1  <|@ instruction [rsi|QWORD[.], rdx|DWORD, rbp|QWORD] = LABEL numbPhis: 0 align: false label: ? <|@ <|@
      nr   -1  <|@ instruction stack:16|QWORD = MOVE rbp|QWORD moveKind: QWORD <|@ <|@
      nr   -1  <|@ instruction [] = HOTSPOTLOCKSTACK frameMapBuilder: org.graalvm.compiler.lir.amd64.AMD64FrameMapBuilder@7a6ad383 slotKind: QWORD <|@ <|@
      nr   -1  <|@ instruction v0|QWORD[.] = MOVE rsi|QWORD[.] moveKind: QWORD <|@ <|@
      nr   -1  <|@ instruction v1|DWORD = MOVE rdx|DWORD moveKind: DWORD <|@ <|@
      nr   -1  <|@ st <@st|@JavaExamples.exampleFieldWrite(JavaExamples.java:304) [bci: 0]
locals: Object[null] v1|DWORD 
>@ <|@ instruction MOV (x: [v0|QWORD[.] + 12], y: v1|DWORD) size: DWORD state [bci:0] <|@ <|@
      nr   -1  <|@ instruction RETURN (savedRbp: stack:16|QWORD, value: -) isStub: false requiresReservedStackAccessCheck: false thread: r15 scratchForSafepointOnReturn: rcx config: org.graalvm.compiler.hotspot.GraalHotSpotVMConfig@384cadad <|@ <|@
    end_IR
  end_block
end_cfg
begin_cfg
  name "After ConstantLoadOptimization"
  begin_block
    name "B0"
    from_bci -1
    to_bci -1
    predecessors 
    successors 
    xhandlers
    flags 
    probability 4607182418800017408
    begin_IR
      LIR
      nr   -1  <|@ instruction [rsi|QWORD[.], rdx|DWORD, rbp|QWORD] = LABEL numbPhis: 0 align: false label: ? <|@ <|@
      nr   -1  <|@ instruction stack:16|QWORD = MOVE rbp|QWORD moveKind: QWORD <|@ <|@
      nr   -1  <|@ instruction [] = HOTSPOTLOCKSTACK frameMapBuilder: org.graalvm.compiler.lir.amd64.AMD64FrameMapBuilder@7a6ad383 slotKind: QWORD <|@ <|@
      nr   -1  <|@ instruction v0|QWORD[.] = MOVE rsi|QWORD[.] moveKind: QWORD <|@ <|@
      nr   -1  <|@ instruction v1|DWORD = MOVE rdx|DWORD moveKind: DWORD <|@ <|@
      nr   -1  <|@ st <@st|@JavaExamples.exampleFieldWrite(JavaExamples.java:304) [bci: 0]
locals: Object[null] v1|DWORD 
>@ <|@ instruction MOV (x: [v0|QWORD[.] + 12], y: v1|DWORD) size: DWORD state [bci:0] <|@ <|@
      nr   -1  <|@ instruction RETURN (savedRbp: stack:16|QWORD, value: -) isStub: false requiresReservedStackAccessCheck: false thread: r15 scratchForSafepointOnReturn: rcx config: org.graalvm.compiler.hotspot.GraalHotSpotVMConfig@384cadad <|@ <|@
    end_IR
  end_block
end_cfg
begin_bytecodes
     0: aload_0       
     1: iload_1       
     2: putfield      #63         // JavaExamples$ExampleObject.x:int
     5: return        
   <|@
end_bytecodes
begin_cfg
  name "After SaveCalleeSaveRegisters"
  begin_block
    name "B0"
    from_bci -1
    to_bci -1
    predecessors 
    successors 
    xhandlers
    flags 
    probability 4607182418800017408
    begin_IR
      LIR
      nr   -1  <|@ instruction [rsi|QWORD[.], rdx|DWORD, rbp|QWORD] = LABEL numbPhis: 0 align: false label: ? <|@ <|@
      nr   -1  <|@ instruction stack:16|QWORD = MOVE rbp|QWORD moveKind: QWORD <|@ <|@
      nr   -1  <|@ instruction [] = HOTSPOTLOCKSTACK frameMapBuilder: org.graalvm.compiler.lir.amd64.AMD64FrameMapBuilder@7a6ad383 slotKind: QWORD <|@ <|@
      nr   -1  <|@ instruction v0|QWORD[.] = MOVE rsi|QWORD[.] moveKind: QWORD <|@ <|@
      nr   -1  <|@ instruction v1|DWORD = MOVE rdx|DWORD moveKind: DWORD <|@ <|@
      nr   -1  <|@ st <@st|@JavaExamples.exampleFieldWrite(JavaExamples.java:304) [bci: 0]
locals: Object[null] v1|DWORD 
>@ <|@ instruction MOV (x: [v0|QWORD[.] + 12], y: v1|DWORD) size: DWORD state [bci:0] <|@ <|@
      nr   -1  <|@ instruction RETURN (savedRbp: stack:16|QWORD, value: -) isStub: false requiresReservedStackAccessCheck: false thread: r15 scratchForSafepointOnReturn: rcx config: org.graalvm.compiler.hotspot.GraalHotSpotVMConfig@384cadad <|@ <|@
    end_IR
  end_block
end_cfg
begin_bytecodes
     0: aload_0       
     1: iload_1       
     2: putfield      #63         // JavaExamples$ExampleObject.x:int
     5: return        
   <|@
end_bytecodes
begin_cfg
  name "After PreAllocationOptimizationStage"
  begin_block
    name "B0"
    from_bci -1
    to_bci -1
    predecessors 
    successors 
    xhandlers
    flags 
    probability 4607182418800017408
    begin_IR
      LIR
      nr   -1  <|@ instruction [rsi|QWORD[.], rdx|DWORD, rbp|QWORD] = LABEL numbPhis: 0 align: false label: ? <|@ <|@
      nr   -1  <|@ instruction stack:16|QWORD = MOVE rbp|QWORD moveKind: QWORD <|@ <|@
      nr   -1  <|@ instruction [] = HOTSPOTLOCKSTACK frameMapBuilder: org.graalvm.compiler.lir.amd64.AMD64FrameMapBuilder@7a6ad383 slotKind: QWORD <|@ <|@
      nr   -1  <|@ instruction v0|QWORD[.] = MOVE rsi|QWORD[.] moveKind: QWORD <|@ <|@
      nr   -1  <|@ instruction v1|DWORD = MOVE rdx|DWORD moveKind: DWORD <|@ <|@
      nr   -1  <|@ st <@st|@JavaExamples.exampleFieldWrite(JavaExamples.java:304) [bci: 0]
locals: Object[null] v1|DWORD 
>@ <|@ instruction MOV (x: [v0|QWORD[.] + 12], y: v1|DWORD) size: DWORD state [bci:0] <|@ <|@
      nr   -1  <|@ instruction RETURN (savedRbp: stack:16|QWORD, value: -) isStub: false requiresReservedStackAccessCheck: false thread: r15 scratchForSafepointOnReturn: rcx config: org.graalvm.compiler.hotspot.GraalHotSpotVMConfig@384cadad <|@ <|@
    end_IR
  end_block
end_cfg
begin_bytecodes
     0: aload_0       
     1: iload_1       
     2: putfield      #63         // JavaExamples$ExampleObject.x:int
     5: return        
   <|@
end_bytecodes
begin_cfg
  name "After MarkBasePointers"
  begin_block
    name "B0"
    from_bci -1
    to_bci -1
    predecessors 
    successors 
    xhandlers
    flags 
    probability 4607182418800017408
    begin_IR
      LIR
      nr   -1  <|@ instruction [rsi|QWORD[.], rdx|DWORD, rbp|QWORD] = LABEL numbPhis: 0 align: false label: ? <|@ <|@
      nr   -1  <|@ instruction stack:16|QWORD = MOVE rbp|QWORD moveKind: QWORD <|@ <|@
      nr   -1  <|@ instruction [] = HOTSPOTLOCKSTACK frameMapBuilder: org.graalvm.compiler.lir.amd64.AMD64FrameMapBuilder@7a6ad383 slotKind: QWORD <|@ <|@
      nr   -1  <|@ instruction v0|QWORD[.] = MOVE rsi|QWORD[.] moveKind: QWORD <|@ <|@
      nr   -1  <|@ instruction v1|DWORD = MOVE rdx|DWORD moveKind: DWORD <|@ <|@
      nr   -1  <|@ st <@st|@live-base-pointers: []
JavaExamples.exampleFieldWrite(JavaExamples.java:304) [bci: 0]
locals: Object[null] v1|DWORD 
>@ <|@ instruction MOV (x: [v0|QWORD[.] + 12], y: v1|DWORD) size: DWORD state [bci:0] <|@ <|@
      nr   -1  <|@ instruction RETURN (savedRbp: stack:16|QWORD, value: -) isStub: false requiresReservedStackAccessCheck: false thread: r15 scratchForSafepointOnReturn: rcx config: org.graalvm.compiler.hotspot.GraalHotSpotVMConfig@384cadad <|@ <|@
    end_IR
  end_block
end_cfg
begin_bytecodes
     0: aload_0       
     1: iload_1       
     2: putfield      #63         // JavaExamples$ExampleObject.x:int
     5: return        
   <|@
end_bytecodes
begin_cfg
  name "Before register allocation"
  begin_block
    name "B0"
    from_bci -1
    to_bci -1
    predecessors 
    successors 
    xhandlers
    flags 
    probability 4607182418800017408
    begin_IR
      LIR
      nr    0  <|@ instruction [rsi|QWORD[.], rdx|DWORD, rbp|QWORD] = LABEL numbPhis: 0 align: false label: ? <|@ <|@
      nr    2  <|@ instruction stack:16|QWORD = MOVE rbp|QWORD moveKind: QWORD <|@ <|@
      nr    4  <|@ instruction [] = HOTSPOTLOCKSTACK frameMapBuilder: org.graalvm.compiler.lir.amd64.AMD64FrameMapBuilder@7a6ad383 slotKind: QWORD <|@ <|@
      nr    6  <|@ instruction v0|QWORD[.] = MOVE rsi|QWORD[.] moveKind: QWORD <|@ <|@
      nr    8  <|@ instruction v1|DWORD = MOVE rdx|DWORD moveKind: DWORD <|@ <|@
      nr   10  <|@ st <@st|@live-base-pointers: []
JavaExamples.exampleFieldWrite(JavaExamples.java:304) [bci: 0]
locals: Object[null] v1|DWORD 
>@ <|@ instruction MOV (x: [v0|QWORD[.] + 12], y: v1|DWORD) size: DWORD state [bci:0] <|@ <|@
      nr   12  <|@ instruction RETURN (savedRbp: stack:16|QWORD, value: -) isStub: false requiresReservedStackAccessCheck: false thread: r15 scratchForSafepointOnReturn: rcx config: org.graalvm.compiler.hotspot.GraalHotSpotVMConfig@384cadad <|@ <|@
    end_IR
  end_block
end_cfg
begin_bytecodes
     0: aload_0       
     1: iload_1       
     2: putfield      #63         // JavaExamples$ExampleObject.x:int
     5: return        
   <|@
end_bytecodes
begin_cfg
  name "After SSALinearScanLifetimeAnalysis"
  begin_block
    name "B0"
    from_bci -1
    to_bci -1
    predecessors 
    successors 
    xhandlers
    flags 
    probability 4607182418800017408
    begin_IR
      LIR
      nr    0  <|@ instruction [rsi|QWORD[.], rdx|DWORD, rbp|QWORD] = LABEL numbPhis: 0 align: false label: ? <|@ <|@
      nr    2  <|@ instruction stack:16|QWORD = MOVE rbp|QWORD moveKind: QWORD <|@ <|@
      nr    4  <|@ instruction [] = HOTSPOTLOCKSTACK frameMapBuilder: org.graalvm.compiler.lir.amd64.AMD64FrameMapBuilder@7a6ad383 slotKind: QWORD <|@ <|@
      nr    6  <|@ instruction v0|QWORD[.] = MOVE rsi|QWORD[.] moveKind: QWORD <|@ <|@
      nr    8  <|@ instruction v1|DWORD = MOVE rdx|DWORD moveKind: DWORD <|@ <|@
      nr   10  <|@ st <@st|@live-base-pointers: []
JavaExamples.exampleFieldWrite(JavaExamples.java:304) [bci: 0]
locals: Object[null] v1|DWORD 
>@ <|@ instruction MOV (x: [v0|QWORD[.] + 12], y: v1|DWORD) size: DWORD state [bci:0] <|@ <|@
      nr   12  <|@ instruction RETURN (savedRbp: stack:16|QWORD, value: -) isStub: false requiresReservedStackAccessCheck: false thread: r15 scratchForSafepointOnReturn: rcx config: org.graalvm.compiler.hotspot.GraalHotSpotVMConfig@384cadad <|@ <|@
    end_IR
  end_block
end_cfg
begin_bytecodes
     0: aload_0       
     1: iload_1       
     2: putfield      #63         // JavaExamples$ExampleObject.x:int
     5: return        
   <|@
end_bytecodes
begin_intervals
  name "Before register allocation"
  rdx|d fixed "[rdx|d]" rdx|d -1 [0, 8[ "NoSpillStore"
  rbp|q fixed "[rbp|q]" rbp|q -1 [0, 2[ "NoSpillStore"
  rsi|q fixed "[rsi|q]" rsi|q -1 [0, 6[ "NoSpillStore"
  v0|q QWORD "[v0|q]" v0|q rsi|q [6, 10[6 MustHaveRegister 10 MustHaveRegister  "NoSpillStore"
  v1|d DWORD "[v1|d]" v1|d rdx|d [8, 11[8 MustHaveRegister 10 MustHaveRegister  "NoSpillStore"
end_intervals
begin_intervals
  name "After register allocation"
  rdx|d fixed "[rdx|d]" rdx|d -1 [0, 8[ "NoSpillStore"
  rbp|q fixed "[rbp|q]" rbp|q -1 [0, 2[ "NoSpillStore"
  rsi|q fixed "[rsi|q]" rsi|q -1 [0, 6[ "NoSpillStore"
  v0|q QWORD "[rsi|q]" v0|q rsi|q [6, 10[6 MustHaveRegister 10 MustHaveRegister  "NoSpillStore"
  v1|d DWORD "[rdx|d]" v1|d rdx|d [8, 11[8 MustHaveRegister 10 MustHaveRegister  "NoSpillStore"
end_intervals
begin_cfg
  name "After LinearScanRegisterAllocation"
  begin_block
    name "B0"
    from_bci -1
    to_bci -1
    predecessors 
    successors 
    xhandlers
    flags 
    probability 4607182418800017408
    begin_IR
      LIR
      nr    0  <|@ instruction [rsi|QWORD[.], rdx|DWORD, rbp|QWORD] = LABEL numbPhis: 0 align: false label: ? <|@ <|@
      nr    2  <|@ instruction stack:16|QWORD = MOVE rbp|QWORD moveKind: QWORD <|@ <|@
      nr    4  <|@ instruction [] = HOTSPOTLOCKSTACK frameMapBuilder: org.graalvm.compiler.lir.amd64.AMD64FrameMapBuilder@7a6ad383 slotKind: QWORD <|@ <|@
      nr    6  <|@ instruction v0|QWORD[.] = MOVE rsi|QWORD[.] moveKind: QWORD <|@ <|@
      nr    8  <|@ instruction v1|DWORD = MOVE rdx|DWORD moveKind: DWORD <|@ <|@
      nr   10  <|@ st <@st|@live-base-pointers: []
JavaExamples.exampleFieldWrite(JavaExamples.java:304) [bci: 0]
locals: Object[null] v1|DWORD 
>@ <|@ instruction MOV (x: [v0|QWORD[.] + 12], y: v1|DWORD) size: DWORD state [bci:0] <|@ <|@
      nr   12  <|@ instruction RETURN (savedRbp: stack:16|QWORD, value: -) isStub: false requiresReservedStackAccessCheck: false thread: r15 scratchForSafepointOnReturn: rcx config: org.graalvm.compiler.hotspot.GraalHotSpotVMConfig@384cadad <|@ <|@
    end_IR
  end_block
end_cfg
begin_bytecodes
     0: aload_0       
     1: iload_1       
     2: putfield      #63         // JavaExamples$ExampleObject.x:int
     5: return        
   <|@
end_bytecodes
begin_intervals
  name "After optimize spill position"
  rdx|d fixed "[rdx|d]" rdx|d -1 [0, 8[ "NoSpillStore"
  rbp|q fixed "[rbp|q]" rbp|q -1 [0, 2[ "NoSpillStore"
  rsi|q fixed "[rsi|q]" rsi|q -1 [0, 6[ "NoSpillStore"
  v0|q QWORD "[rsi|q]" v0|q rsi|q [6, 10[6 MustHaveRegister 10 MustHaveRegister  "NoSpillStore"
  v1|d DWORD "[rdx|d]" v1|d rdx|d [8, 11[8 MustHaveRegister 10 MustHaveRegister  "NoSpillStore"
end_intervals
begin_cfg
  name "After LinearScanOptimizeSpillPosition"
  begin_block
    name "B0"
    from_bci -1
    to_bci -1
    predecessors 
    successors 
    xhandlers
    flags 
    probability 4607182418800017408
    begin_IR
      LIR
      nr    0  <|@ instruction [rsi|QWORD[.], rdx|DWORD, rbp|QWORD] = LABEL numbPhis: 0 align: false label: ? <|@ <|@
      nr    2  <|@ instruction stack:16|QWORD = MOVE rbp|QWORD moveKind: QWORD <|@ <|@
      nr    4  <|@ instruction [] = HOTSPOTLOCKSTACK frameMapBuilder: org.graalvm.compiler.lir.amd64.AMD64FrameMapBuilder@7a6ad383 slotKind: QWORD <|@ <|@
      nr    6  <|@ instruction v0|QWORD[.] = MOVE rsi|QWORD[.] moveKind: QWORD <|@ <|@
      nr    8  <|@ instruction v1|DWORD = MOVE rdx|DWORD moveKind: DWORD <|@ <|@
      nr   10  <|@ st <@st|@live-base-pointers: []
JavaExamples.exampleFieldWrite(JavaExamples.java:304) [bci: 0]
locals: Object[null] v1|DWORD 
>@ <|@ instruction MOV (x: [v0|QWORD[.] + 12], y: v1|DWORD) size: DWORD state [bci:0] <|@ <|@
      nr   12  <|@ instruction RETURN (savedRbp: stack:16|QWORD, value: -) isStub: false requiresReservedStackAccessCheck: false thread: r15 scratchForSafepointOnReturn: rcx config: org.graalvm.compiler.hotspot.GraalHotSpotVMConfig@384cadad <|@ <|@
    end_IR
  end_block
end_cfg
begin_bytecodes
     0: aload_0       
     1: iload_1       
     2: putfield      #63         // JavaExamples$ExampleObject.x:int
     5: return        
   <|@
end_bytecodes
begin_intervals
  name "After resolve data flow"
  rdx|d fixed "[rdx|d]" rdx|d -1 [0, 8[ "NoSpillStore"
  rbp|q fixed "[rbp|q]" rbp|q -1 [0, 2[ "NoSpillStore"
  rsi|q fixed "[rsi|q]" rsi|q -1 [0, 6[ "NoSpillStore"
  v0|q QWORD "[rsi|q]" v0|q rsi|q [6, 10[6 MustHaveRegister 10 MustHaveRegister  "NoSpillStore"
  v1|d DWORD "[rdx|d]" v1|d rdx|d [8, 11[8 MustHaveRegister 10 MustHaveRegister  "NoSpillStore"
end_intervals
begin_cfg
  name "After SSALinearScanResolveDataFlow"
  begin_block
    name "B0"
    from_bci -1
    to_bci -1
    predecessors 
    successors 
    xhandlers
    flags 
    probability 4607182418800017408
    begin_IR
      LIR
      nr    0  <|@ instruction [rsi|QWORD[.], rdx|DWORD, rbp|QWORD] = LABEL numbPhis: 0 align: false label: ? <|@ <|@
      nr    2  <|@ instruction stack:16|QWORD = MOVE rbp|QWORD moveKind: QWORD <|@ <|@
      nr    4  <|@ instruction [] = HOTSPOTLOCKSTACK frameMapBuilder: org.graalvm.compiler.lir.amd64.AMD64FrameMapBuilder@7a6ad383 slotKind: QWORD <|@ <|@
      nr    6  <|@ instruction v0|QWORD[.] = MOVE rsi|QWORD[.] moveKind: QWORD <|@ <|@
      nr    8  <|@ instruction v1|DWORD = MOVE rdx|DWORD moveKind: DWORD <|@ <|@
      nr   10  <|@ st <@st|@live-base-pointers: []
JavaExamples.exampleFieldWrite(JavaExamples.java:304) [bci: 0]
locals: Object[null] v1|DWORD 
>@ <|@ instruction MOV (x: [v0|QWORD[.] + 12], y: v1|DWORD) size: DWORD state [bci:0] <|@ <|@
      nr   12  <|@ instruction RETURN (savedRbp: stack:16|QWORD, value: -) isStub: false requiresReservedStackAccessCheck: false thread: r15 scratchForSafepointOnReturn: rcx config: org.graalvm.compiler.hotspot.GraalHotSpotVMConfig@384cadad <|@ <|@
    end_IR
  end_block
end_cfg
begin_bytecodes
     0: aload_0       
     1: iload_1       
     2: putfield      #63         // JavaExamples$ExampleObject.x:int
     5: return        
   <|@
end_bytecodes
begin_cfg
  name "After SSALinearScanEliminateSpillMove"
  begin_block
    name "B0"
    from_bci -1
    to_bci -1
    predecessors 
    successors 
    xhandlers
    flags 
    probability 4607182418800017408
    begin_IR
      LIR
      nr    0  <|@ instruction [rsi|QWORD[.], rdx|DWORD, rbp|QWORD] = LABEL numbPhis: 0 align: false label: ? <|@ <|@
      nr    2  <|@ instruction stack:16|QWORD = MOVE rbp|QWORD moveKind: QWORD <|@ <|@
      nr    4  <|@ instruction [] = HOTSPOTLOCKSTACK frameMapBuilder: org.graalvm.compiler.lir.amd64.AMD64FrameMapBuilder@7a6ad383 slotKind: QWORD <|@ <|@
      nr    6  <|@ instruction v0|QWORD[.] = MOVE rsi|QWORD[.] moveKind: QWORD <|@ <|@
      nr    8  <|@ instruction v1|DWORD = MOVE rdx|DWORD moveKind: DWORD <|@ <|@
      nr   10  <|@ st <@st|@live-base-pointers: []
JavaExamples.exampleFieldWrite(JavaExamples.java:304) [bci: 0]
locals: Object[null] v1|DWORD 
>@ <|@ instruction MOV (x: [v0|QWORD[.] + 12], y: v1|DWORD) size: DWORD state [bci:0] <|@ <|@
      nr   12  <|@ instruction RETURN (savedRbp: stack:16|QWORD, value: -) isStub: false requiresReservedStackAccessCheck: false thread: r15 scratchForSafepointOnReturn: rcx config: org.graalvm.compiler.hotspot.GraalHotSpotVMConfig@384cadad <|@ <|@
    end_IR
  end_block
end_cfg
begin_bytecodes
     0: aload_0       
     1: iload_1       
     2: putfield      #63         // JavaExamples$ExampleObject.x:int
     5: return        
   <|@
end_bytecodes
begin_cfg
  name "After LinearScanAssignLocations"
  begin_block
    name "B0"
    from_bci -1
    to_bci -1
    predecessors 
    successors 
    xhandlers
    flags 
    probability 4607182418800017408
    begin_IR
      LIR
      nr    0  <|@ instruction [rsi|QWORD[.], rdx|DWORD, rbp|QWORD] = LABEL numbPhis: 0 align: false label: ? <|@ <|@
      nr    2  <|@ instruction stack:16|QWORD = MOVE rbp|QWORD moveKind: QWORD <|@ <|@
      nr    4  <|@ instruction [] = HOTSPOTLOCKSTACK frameMapBuilder: org.graalvm.compiler.lir.amd64.AMD64FrameMapBuilder@7a6ad383 slotKind: QWORD <|@ <|@
      nr   10  <|@ st <@st|@live-base-pointers: []
JavaExamples.exampleFieldWrite(JavaExamples.java:304) [bci: 0]
locals: Object[null] rdx|DWORD 
>@ <|@ instruction MOV (x: [rsi|QWORD[.] + 12], y: rdx|DWORD) size: DWORD state [bci:0] <|@ <|@
      nr   12  <|@ instruction RETURN (savedRbp: stack:16|QWORD, value: -) isStub: false requiresReservedStackAccessCheck: false thread: r15 scratchForSafepointOnReturn: rcx config: org.graalvm.compiler.hotspot.GraalHotSpotVMConfig@384cadad <|@ <|@
    end_IR
  end_block
end_cfg
begin_bytecodes
     0: aload_0       
     1: iload_1       
     2: putfield      #63         // JavaExamples$ExampleObject.x:int
     5: return        
   <|@
end_bytecodes
begin_cfg
  name "After LinearScan"
  begin_block
    name "B0"
    from_bci -1
    to_bci -1
    predecessors 
    successors 
    xhandlers
    flags 
    probability 4607182418800017408
    begin_IR
      LIR
      nr    0  <|@ instruction [rsi|QWORD[.], rdx|DWORD, rbp|QWORD] = LABEL numbPhis: 0 align: false label: ? <|@ <|@
      nr    2  <|@ instruction stack:16|QWORD = MOVE rbp|QWORD moveKind: QWORD <|@ <|@
      nr    4  <|@ instruction [] = HOTSPOTLOCKSTACK frameMapBuilder: org.graalvm.compiler.lir.amd64.AMD64FrameMapBuilder@7a6ad383 slotKind: QWORD <|@ <|@
      nr   10  <|@ st <@st|@live-base-pointers: []
JavaExamples.exampleFieldWrite(JavaExamples.java:304) [bci: 0]
locals: Object[null] rdx|DWORD 
>@ <|@ instruction MOV (x: [rsi|QWORD[.] + 12], y: rdx|DWORD) size: DWORD state [bci:0] <|@ <|@
      nr   12  <|@ instruction RETURN (savedRbp: stack:16|QWORD, value: -) isStub: false requiresReservedStackAccessCheck: false thread: r15 scratchForSafepointOnReturn: rcx config: org.graalvm.compiler.hotspot.GraalHotSpotVMConfig@384cadad <|@ <|@
    end_IR
  end_block
end_cfg
begin_bytecodes
     0: aload_0       
     1: iload_1       
     2: putfield      #63         // JavaExamples$ExampleObject.x:int
     5: return        
   <|@
end_bytecodes
begin_cfg
  name "After LSStackSlotAllocator"
  begin_block
    name "B0"
    from_bci -1
    to_bci -1
    predecessors 
    successors 
    xhandlers
    flags 
    probability 4607182418800017408
    begin_IR
      LIR
      nr    0  <|@ instruction [rsi|QWORD[.], rdx|DWORD, rbp|QWORD] = LABEL numbPhis: 0 align: false label: ? <|@ <|@
      nr    2  <|@ instruction stack:16|QWORD = MOVE rbp|QWORD moveKind: QWORD <|@ <|@
      nr    4  <|@ instruction [] = HOTSPOTLOCKSTACK frameMapBuilder: org.graalvm.compiler.lir.amd64.AMD64FrameMapBuilder@7a6ad383 slotKind: QWORD <|@ <|@
      nr   10  <|@ st <@st|@live-base-pointers: []
JavaExamples.exampleFieldWrite(JavaExamples.java:304) [bci: 0]
locals: Object[null] rdx|DWORD 
>@ <|@ instruction MOV (x: [rsi|QWORD[.] + 12], y: rdx|DWORD) size: DWORD state [bci:0] <|@ <|@
      nr   12  <|@ instruction RETURN (savedRbp: stack:16|QWORD, value: -) isStub: false requiresReservedStackAccessCheck: false thread: r15 scratchForSafepointOnReturn: rcx config: org.graalvm.compiler.hotspot.GraalHotSpotVMConfig@384cadad <|@ <|@
    end_IR
  end_block
end_cfg
begin_bytecodes
     0: aload_0       
     1: iload_1       
     2: putfield      #63         // JavaExamples$ExampleObject.x:int
     5: return        
   <|@
end_bytecodes
begin_cfg
  name "After LocationMarker"
  begin_block
    name "B0"
    from_bci -1
    to_bci -1
    predecessors 
    successors 
    xhandlers
    flags 
    probability 4607182418800017408
    begin_IR
      LIR
      nr    0  <|@ instruction [rsi|QWORD[.], rdx|DWORD, rbp|QWORD] = LABEL numbPhis: 0 align: false label: ? <|@ <|@
      nr    2  <|@ instruction stack:16|QWORD = MOVE rbp|QWORD moveKind: QWORD <|@ <|@
      nr    4  <|@ instruction [] = HOTSPOTLOCKSTACK frameMapBuilder: org.graalvm.compiler.lir.amd64.AMD64FrameMapBuilder@7a6ad383 slotKind: QWORD <|@ <|@
      nr   10  <|@ st <@st|@reference-map: []
live-base-pointers: []
JavaExamples.exampleFieldWrite(JavaExamples.java:304) [bci: 0]
locals: Object[null] rdx|DWORD 
>@ <|@ instruction MOV (x: [rsi|QWORD[.] + 12], y: rdx|DWORD) size: DWORD state [bci:0] <|@ <|@
      nr   12  <|@ instruction RETURN (savedRbp: stack:16|QWORD, value: -) isStub: false requiresReservedStackAccessCheck: false thread: r15 scratchForSafepointOnReturn: rcx config: org.graalvm.compiler.hotspot.GraalHotSpotVMConfig@384cadad <|@ <|@
    end_IR
  end_block
end_cfg
begin_bytecodes
     0: aload_0       
     1: iload_1       
     2: putfield      #63         // JavaExamples$ExampleObject.x:int
     5: return        
   <|@
end_bytecodes
begin_cfg
  name "After AllocationStage"
  begin_block
    name "B0"
    from_bci -1
    to_bci -1
    predecessors 
    successors 
    xhandlers
    flags 
    probability 4607182418800017408
    begin_IR
      LIR
      nr    0  <|@ instruction [rsi|QWORD[.], rdx|DWORD, rbp|QWORD] = LABEL numbPhis: 0 align: false label: ? <|@ <|@
      nr    2  <|@ instruction stack:16|QWORD = MOVE rbp|QWORD moveKind: QWORD <|@ <|@
      nr    4  <|@ instruction [] = HOTSPOTLOCKSTACK frameMapBuilder: org.graalvm.compiler.lir.amd64.AMD64FrameMapBuilder@7a6ad383 slotKind: QWORD <|@ <|@
      nr   10  <|@ st <@st|@reference-map: []
live-base-pointers: []
JavaExamples.exampleFieldWrite(JavaExamples.java:304) [bci: 0]
locals: Object[null] rdx|DWORD 
>@ <|@ instruction MOV (x: [rsi|QWORD[.] + 12], y: rdx|DWORD) size: DWORD state [bci:0] <|@ <|@
      nr   12  <|@ instruction RETURN (savedRbp: stack:16|QWORD, value: -) isStub: false requiresReservedStackAccessCheck: false thread: r15 scratchForSafepointOnReturn: rcx config: org.graalvm.compiler.hotspot.GraalHotSpotVMConfig@384cadad <|@ <|@
    end_IR
  end_block
end_cfg
begin_bytecodes
     0: aload_0       
     1: iload_1       
     2: putfield      #63         // JavaExamples$ExampleObject.x:int
     5: return        
   <|@
end_bytecodes
begin_cfg
  name "After EdgeMoveOptimizer"
  begin_block
    name "B0"
    from_bci -1
    to_bci -1
    predecessors 
    successors 
    xhandlers
    flags 
    probability 4607182418800017408
    begin_IR
      LIR
      nr    0  <|@ instruction [rsi|QWORD[.], rdx|DWORD, rbp|QWORD] = LABEL numbPhis: 0 align: false label: ? <|@ <|@
      nr    2  <|@ instruction stack:16|QWORD = MOVE rbp|QWORD moveKind: QWORD <|@ <|@
      nr    4  <|@ instruction [] = HOTSPOTLOCKSTACK frameMapBuilder: org.graalvm.compiler.lir.amd64.AMD64FrameMapBuilder@7a6ad383 slotKind: QWORD <|@ <|@
      nr   10  <|@ st <@st|@reference-map: []
live-base-pointers: []
JavaExamples.exampleFieldWrite(JavaExamples.java:304) [bci: 0]
locals: Object[null] rdx|DWORD 
>@ <|@ instruction MOV (x: [rsi|QWORD[.] + 12], y: rdx|DWORD) size: DWORD state [bci:0] <|@ <|@
      nr   12  <|@ instruction RETURN (savedRbp: stack:16|QWORD, value: -) isStub: false requiresReservedStackAccessCheck: false thread: r15 scratchForSafepointOnReturn: rcx config: org.graalvm.compiler.hotspot.GraalHotSpotVMConfig@384cadad <|@ <|@
    end_IR
  end_block
end_cfg
begin_bytecodes
     0: aload_0       
     1: iload_1       
     2: putfield      #63         // JavaExamples$ExampleObject.x:int
     5: return        
   <|@
end_bytecodes
begin_cfg
  name "After ControlFlowOptimizer"
  begin_block
    name "B0"
    from_bci -1
    to_bci -1
    predecessors 
    successors 
    xhandlers
    flags 
    probability 4607182418800017408
    begin_IR
      LIR
      nr    0  <|@ instruction [rsi|QWORD[.], rdx|DWORD, rbp|QWORD] = LABEL numbPhis: 0 align: false label: ? <|@ <|@
      nr    2  <|@ instruction stack:16|QWORD = MOVE rbp|QWORD moveKind: QWORD <|@ <|@
      nr    4  <|@ instruction [] = HOTSPOTLOCKSTACK frameMapBuilder: org.graalvm.compiler.lir.amd64.AMD64FrameMapBuilder@7a6ad383 slotKind: QWORD <|@ <|@
      nr   10  <|@ st <@st|@reference-map: []
live-base-pointers: []
JavaExamples.exampleFieldWrite(JavaExamples.java:304) [bci: 0]
locals: Object[null] rdx|DWORD 
>@ <|@ instruction MOV (x: [rsi|QWORD[.] + 12], y: rdx|DWORD) size: DWORD state [bci:0] <|@ <|@
      nr   12  <|@ instruction RETURN (savedRbp: stack:16|QWORD, value: -) isStub: false requiresReservedStackAccessCheck: false thread: r15 scratchForSafepointOnReturn: rcx config: org.graalvm.compiler.hotspot.GraalHotSpotVMConfig@384cadad <|@ <|@
    end_IR
  end_block
end_cfg
begin_bytecodes
     0: aload_0       
     1: iload_1       
     2: putfield      #63         // JavaExamples$ExampleObject.x:int
     5: return        
   <|@
end_bytecodes
begin_cfg
  name "After RedundantMoveElimination"
  begin_block
    name "B0"
    from_bci -1
    to_bci -1
    predecessors 
    successors 
    xhandlers
    flags 
    probability 4607182418800017408
    begin_IR
      LIR
      nr    0  <|@ instruction [rsi|QWORD[.], rdx|DWORD, rbp|QWORD] = LABEL numbPhis: 0 align: false label: ? <|@ <|@
      nr    2  <|@ instruction stack:16|QWORD = MOVE rbp|QWORD moveKind: QWORD <|@ <|@
      nr    4  <|@ instruction [] = HOTSPOTLOCKSTACK frameMapBuilder: org.graalvm.compiler.lir.amd64.AMD64FrameMapBuilder@7a6ad383 slotKind: QWORD <|@ <|@
      nr   10  <|@ st <@st|@reference-map: []
live-base-pointers: []
JavaExamples.exampleFieldWrite(JavaExamples.java:304) [bci: 0]
locals: Object[null] rdx|DWORD 
>@ <|@ instruction MOV (x: [rsi|QWORD[.] + 12], y: rdx|DWORD) size: DWORD state [bci:0] <|@ <|@
      nr   12  <|@ instruction RETURN (savedRbp: stack:16|QWORD, value: -) isStub: false requiresReservedStackAccessCheck: false thread: r15 scratchForSafepointOnReturn: rcx config: org.graalvm.compiler.hotspot.GraalHotSpotVMConfig@384cadad <|@ <|@
    end_IR
  end_block
end_cfg
begin_bytecodes
     0: aload_0       
     1: iload_1       
     2: putfield      #63         // JavaExamples$ExampleObject.x:int
     5: return        
   <|@
end_bytecodes
begin_cfg
  name "After NullCheckOptimizer"
  begin_block
    name "B0"
    from_bci -1
    to_bci -1
    predecessors 
    successors 
    xhandlers
    flags 
    probability 4607182418800017408
    begin_IR
      LIR
      nr    0  <|@ instruction [rsi|QWORD[.], rdx|DWORD, rbp|QWORD] = LABEL numbPhis: 0 align: false label: ? <|@ <|@
      nr    2  <|@ instruction stack:16|QWORD = MOVE rbp|QWORD moveKind: QWORD <|@ <|@
      nr    4  <|@ instruction [] = HOTSPOTLOCKSTACK frameMapBuilder: org.graalvm.compiler.lir.amd64.AMD64FrameMapBuilder@7a6ad383 slotKind: QWORD <|@ <|@
      nr   10  <|@ st <@st|@reference-map: []
live-base-pointers: []
JavaExamples.exampleFieldWrite(JavaExamples.java:304) [bci: 0]
locals: Object[null] rdx|DWORD 
>@ <|@ instruction MOV (x: [rsi|QWORD[.] + 12], y: rdx|DWORD) size: DWORD state [bci:0] <|@ <|@
      nr   12  <|@ instruction RETURN (savedRbp: stack:16|QWORD, value: -) isStub: false requiresReservedStackAccessCheck: false thread: r15 scratchForSafepointOnReturn: rcx config: org.graalvm.compiler.hotspot.GraalHotSpotVMConfig@384cadad <|@ <|@
    end_IR
  end_block
end_cfg
begin_bytecodes
     0: aload_0       
     1: iload_1       
     2: putfield      #63         // JavaExamples$ExampleObject.x:int
     5: return        
   <|@
end_bytecodes
begin_cfg
  name "After StackMoveOptimization"
  begin_block
    name "B0"
    from_bci -1
    to_bci -1
    predecessors 
    successors 
    xhandlers
    flags 
    probability 4607182418800017408
    begin_IR
      LIR
      nr    0  <|@ instruction [rsi|QWORD[.], rdx|DWORD, rbp|QWORD] = LABEL numbPhis: 0 align: false label: ? <|@ <|@
      nr    2  <|@ instruction stack:16|QWORD = MOVE rbp|QWORD moveKind: QWORD <|@ <|@
      nr    4  <|@ instruction [] = HOTSPOTLOCKSTACK frameMapBuilder: org.graalvm.compiler.lir.amd64.AMD64FrameMapBuilder@7a6ad383 slotKind: QWORD <|@ <|@
      nr   10  <|@ st <@st|@reference-map: []
live-base-pointers: []
JavaExamples.exampleFieldWrite(JavaExamples.java:304) [bci: 0]
locals: Object[null] rdx|DWORD 
>@ <|@ instruction MOV (x: [rsi|QWORD[.] + 12], y: rdx|DWORD) size: DWORD state [bci:0] <|@ <|@
      nr   12  <|@ instruction RETURN (savedRbp: stack:16|QWORD, value: -) isStub: false requiresReservedStackAccessCheck: false thread: r15 scratchForSafepointOnReturn: rcx config: org.graalvm.compiler.hotspot.GraalHotSpotVMConfig@384cadad <|@ <|@
    end_IR
  end_block
end_cfg
begin_bytecodes
     0: aload_0       
     1: iload_1       
     2: putfield      #63         // JavaExamples$ExampleObject.x:int
     5: return        
   <|@
end_bytecodes
begin_cfg
  name "After PostAllocationOptimizationStage"
  begin_block
    name "B0"
    from_bci -1
    to_bci -1
    predecessors 
    successors 
    xhandlers
    flags 
    probability 4607182418800017408
    begin_IR
      LIR
      nr    0  <|@ instruction [rsi|QWORD[.], rdx|DWORD, rbp|QWORD] = LABEL numbPhis: 0 align: false label: ? <|@ <|@
      nr    2  <|@ instruction stack:16|QWORD = MOVE rbp|QWORD moveKind: QWORD <|@ <|@
      nr    4  <|@ instruction [] = HOTSPOTLOCKSTACK frameMapBuilder: org.graalvm.compiler.lir.amd64.AMD64FrameMapBuilder@7a6ad383 slotKind: QWORD <|@ <|@
      nr   10  <|@ st <@st|@reference-map: []
live-base-pointers: []
JavaExamples.exampleFieldWrite(JavaExamples.java:304) [bci: 0]
locals: Object[null] rdx|DWORD 
>@ <|@ instruction MOV (x: [rsi|QWORD[.] + 12], y: rdx|DWORD) size: DWORD state [bci:0] <|@ <|@
      nr   12  <|@ instruction RETURN (savedRbp: stack:16|QWORD, value: -) isStub: false requiresReservedStackAccessCheck: false thread: r15 scratchForSafepointOnReturn: rcx config: org.graalvm.compiler.hotspot.GraalHotSpotVMConfig@384cadad <|@ <|@
    end_IR
  end_block
end_cfg
begin_bytecodes
     0: aload_0       
     1: iload_1       
     2: putfield      #63         // JavaExamples$ExampleObject.x:int
     5: return        
   <|@
end_bytecodes
begin_cfg
  name "After code generation"
end_cfg
begin_nmethod
  <<<HexCodeFile
  Platform AMD64 64  <||@
  HexCode 0 89842400c0feff4883ec1848896c241089560c488b6c24104883c418850500000000c341c787f4020000f5f7ffff49c7870003000000000000e8000000009090e80000000090e80000000090  <||@
  Comment 0 [stack overflow check]  <||@
  Comment 0 VERIFIED_ENTRY  <||@
  Comment 11 block B0 null  <||@
  Comment 11 0 [rsi|QWORD[.], rdx|DWORD, rbp|QWORD] = LABEL numbPhis: 0 align: false label: ?  <||@
  Comment 11 2 stack:16|QWORD = MOVE rbp|QWORD moveKind: QWORD  <||@
  Comment 11 FRAME_COMPLETE  <||@
  Comment 16 4 [] = HOTSPOTLOCKSTACK frameMapBuilder: org.graalvm.compiler.lir.amd64.AMD64FrameMapBuilder@7a6ad383 slotKind: QWORD  <||@
  Comment 16 10 MOV (x: [rsi|QWORD[.] + 12], y: rdx|DWORD) size: DWORD state [bci:0]  <||@
  Comment 16 []at JavaExamples.exampleFieldWrite(JavaExamples.java:304) [bci: 0, duringCall: false, rethrow: false]
              |0             |1         
     locals:  |Object[null]  |rdx|DWORD   <||@
  Comment 16 {infopoint: IMPLICIT_EXCEPTION}  <||@
  Comment 19 12 RETURN (savedRbp: stack:16|QWORD, value: -) isStub: false requiresReservedStackAccessCheck: false thread: r15 scratchForSafepointOnReturn: rcx config: org.graalvm.compiler.hotspot.GraalHotSpotVMConfig@384cadad  <||@
  Comment 28 POLL_RETURN_NEAR  <||@
  Comment 57 {Field[name=CompilerToVM::Data::SharedRuntime_deopt_blob_uncommon_trap, type=address, offset=0, address=0x10f13fc50, value=4686721854]:0x11759b33e}  <||@
  Comment 62 []at JavaExamples.exampleFieldWrite(JavaExamples.java:304) [bci: 0, duringCall: false, rethrow: false]
              |0             |1         
     locals:  |Object[null]  |rdx|DWORD   <||@
  Comment 64 {Stub<ExceptionHandlerStub.exceptionHandler>@0x1179d6420:CallingConvention[rax|QWORD[.], rdx|QWORD]:CallingConvention[rax|QWORD[.], rdx|QWORD]; temps=rdi|ILLEGAL,xmm14|ILLEGAL,xmm15|ILLEGAL,xmm12|ILLEGAL,xmm13|ILLEGAL,xmm10|ILLEGAL,xmm11|ILLEGAL,xmm7|ILLEGAL,xmm8|ILLEGAL,xmm9|ILLEGAL,xmm0|ILLEGAL,xmm1|ILLEGAL,xmm2|ILLEGAL,xmm3|ILLEGAL,xmm4|ILLEGAL,xmm5|ILLEGAL,xmm6|ILLEGAL,rax|ILLEGAL,rcx|ILLEGAL,rdx|ILLEGAL,rsi|ILLEGAL,r8|ILLEGAL,r9|ILLEGAL,r10|ILLEGAL,r11|ILLEGAL}  <||@
  Comment 64 EXCEPTION_HANDLER_ENTRY  <||@
  Comment 70 {Field[name=CompilerToVM::Data::SharedRuntime_deopt_blob_unpack, type=address, offset=0, address=0x10f13fc40, value=4686721600]:0x11759b240}  <||@
  Comment 70 DEOPT_HANDLER_ENTRY  <||@
  HexCodeFile>>> <|@
end_nmethod
begin_compilation
  name " HotSpotCompilation-138[JavaExamples.exampleFieldWrite(JavaExamples$ExampleObject, int)]"
  method "HotSpotCompilation-138[JavaExamples.exampleFieldWrite(JavaExamples$ExampleObject, int)]"
  date 1612307469657
end_compilation
begin_cfg
  name "After code installation"
end_cfg
begin_nmethod
  <<<HexCodeFile
  Platform AMD64 64  <||@
  HexCode 1183043e0 89842400c0feff4883ec1848896c241089560c488b6c24104883c418850504cc4cf0c341c787f4020000f5f7ffff49c7870003000000000000e8206f29ff9090e8fb1f6dff90e8156e29ff90f4f4f4f4  <||@
  Comment 0 [stack overflow check]  <||@
  Comment 0 VERIFIED_ENTRY  <||@
  Comment 11 block B0 null  <||@
  Comment 11 0 [rsi|QWORD[.], rdx|DWORD, rbp|QWORD] = LABEL numbPhis: 0 align: false label: ?  <||@
  Comment 11 2 stack:16|QWORD = MOVE rbp|QWORD moveKind: QWORD  <||@
  Comment 11 FRAME_COMPLETE  <||@
  Comment 16 4 [] = HOTSPOTLOCKSTACK frameMapBuilder: org.graalvm.compiler.lir.amd64.AMD64FrameMapBuilder@7a6ad383 slotKind: QWORD  <||@
  Comment 16 10 MOV (x: [rsi|QWORD[.] + 12], y: rdx|DWORD) size: DWORD state [bci:0]  <||@
  Comment 16 []at JavaExamples.exampleFieldWrite(JavaExamples.java:304) [bci: 0, duringCall: false, rethrow: false]
              |0             |1         
     locals:  |Object[null]  |rdx|DWORD   <||@
  Comment 16 {infopoint: IMPLICIT_EXCEPTION}  <||@
  Comment 19 12 RETURN (savedRbp: stack:16|QWORD, value: -) isStub: false requiresReservedStackAccessCheck: false thread: r15 scratchForSafepointOnReturn: rcx config: org.graalvm.compiler.hotspot.GraalHotSpotVMConfig@384cadad  <||@
  Comment 28 POLL_RETURN_NEAR  <||@
  Comment 57 {Field[name=CompilerToVM::Data::SharedRuntime_deopt_blob_uncommon_trap, type=address, offset=0, address=0x10f13fc50, value=4686721854]:0x11759b33e}  <||@
  Comment 62 []at JavaExamples.exampleFieldWrite(JavaExamples.java:304) [bci: 0, duringCall: false, rethrow: false]
              |0             |1         
     locals:  |Object[null]  |rdx|DWORD   <||@
  Comment 64 {Stub<ExceptionHandlerStub.exceptionHandler>@0x1179d6420:CallingConvention[rax|QWORD[.], rdx|QWORD]:CallingConvention[rax|QWORD[.], rdx|QWORD]; temps=rdi|ILLEGAL,xmm14|ILLEGAL,xmm15|ILLEGAL,xmm12|ILLEGAL,xmm13|ILLEGAL,xmm10|ILLEGAL,xmm11|ILLEGAL,xmm7|ILLEGAL,xmm8|ILLEGAL,xmm9|ILLEGAL,xmm0|ILLEGAL,xmm1|ILLEGAL,xmm2|ILLEGAL,xmm3|ILLEGAL,xmm4|ILLEGAL,xmm5|ILLEGAL,xmm6|ILLEGAL,rax|ILLEGAL,rcx|ILLEGAL,rdx|ILLEGAL,rsi|ILLEGAL,r8|ILLEGAL,r9|ILLEGAL,r10|ILLEGAL,r11|ILLEGAL}  <||@
  Comment 64 EXCEPTION_HANDLER_ENTRY  <||@
  Comment 70 {Field[name=CompilerToVM::Data::SharedRuntime_deopt_blob_unpack, type=address, offset=0, address=0x10f13fc40, value=4686721600]:0x11759b240}  <||@
  Comment 70 DEOPT_HANDLER_ENTRY  <||@
  HexCodeFile>>> <|@
end_nmethod
