begin_compilation
  name " HotSpotCompilation-370[JavaExamples.exampleLocalSynchronized(int)]"
  method "HotSpotCompilation-370[JavaExamples.exampleLocalSynchronized(int)]"
  date 1583364092233
end_compilation
begin_cfg
  name "Final HIR schedule"
  begin_block
    name "B0"
    from_bci -1
    to_bci -1
    predecessors 
    successors 
    xhandlers
    flags 
    probability 4607182418800017408
    begin_IR
      HIR
f <@#|@fixed with next>@ <|@
tid v0 <|@
d <@d|@=== Debug Properties ===
stamp: void
withSpeculationFence: false
=== Inputs ===
stateAfter: - 
=== Succesors ===
next: v19 
=== Usages ===
=== Predecessor ===
- >@ <|@
instruction <@StartNode|@org.graalvm.compiler.nodes.StartNode>@ stateAfter: - #next: v19  <|@  <|@
f <@#|@fixed with next>@ <|@
tid v19 <|@
d <@d|@=== Debug Properties ===
barriers: 10
location: ANY_LOCATION
stamp: void
=== Inputs ===
=== Succesors ===
next: v17 
=== Usages ===
=== Predecessor ===
v0 >@ <|@
instruction <@Membar|@org.graalvm.compiler.nodes.extended.MembarNode>@ #next: v17  <|@  <|@
f <@~|@floating>@ <|@
tid a14 <|@
d <@d|@=== Debug Properties ===
isDefaultStable: false
nodeSourcePosition: at JavaExamples.exampleLocalSynchronized(JavaExamples.java:350) [bci: 13]
rawvalue: Instance<java.lang.Class>
stableDimension: 0
stamp: a!# Ljava/lang/Class;
stampKind: a -
value: Object[Instance<java.lang.Class>]
=== Inputs ===
=== Succesors ===
=== Usages ===
v18 
=== Predecessor ===
- >@ <|@
instruction <@Constant|@org.graalvm.compiler.nodes.ConstantNode>@  <|@  <|@
f <@~|@floating>@ <|@
tid v18 <|@
d <@d|@=== Debug Properties ===
displacement: 128
scale: Times1
stamp: void*
=== Inputs ===
base: a14 
index: - 
=== Succesors ===
=== Usages ===
v17 
=== Predecessor ===
- >@ <|@
instruction <@AMD64Address|@org.graalvm.compiler.core.amd64.AMD64AddressNode>@ base: a14 index: -  <|@  <|@
f <@~|@floating>@ <|@
tid i1 <|@
d <@d|@=== Debug Properties ===
index: 0
stamp: i32
uncheckedStamp: [null]
=== Inputs ===
=== Succesors ===
=== Usages ===
v17 
=== Predecessor ===
- >@ <|@
instruction <@Parameter|@org.graalvm.compiler.nodes.ParameterNode>@  <|@  <|@
f <@#|@fixed with next>@ <|@
tid v17 <|@
d <@d|@=== Debug Properties ===
barrierType: NONE
location: JavaExamples.intField
nodeSourcePosition: at JavaExamples.exampleLocalSynchronized(JavaExamples.java:350) [bci: 13]
nullCheck: false
stamp: void
volatileAccess: true
=== Inputs ===
stateBefore: - 
guard: - 
address: v18 
value: i1 
stateAfter: - 
lastLocationAccess: - 
=== Succesors ===
next: v20 
=== Usages ===
=== Predecessor ===
v19 >@ <|@
instruction <@Write|@org.graalvm.compiler.nodes.memory.WriteNode>@ stateBefore: - guard: - address: v18 value: i1 stateAfter: - lastLocationAccess: - #next: v20  <|@  <|@
f <@#|@fixed with next>@ <|@
tid v20 <|@
d <@d|@=== Debug Properties ===
barriers: 12
location: ANY_LOCATION
stamp: void
=== Inputs ===
=== Succesors ===
next: v11 
=== Usages ===
=== Predecessor ===
v17 >@ <|@
instruction <@Membar|@org.graalvm.compiler.nodes.extended.MembarNode>@ #next: v11  <|@  <|@
f <@*|@fixed>@ <|@
tid v11 <|@
d <@d|@=== Debug Properties ===
nodeSourcePosition: at JavaExamples.exampleLocalSynchronized(JavaExamples.java:352) [bci: 26]
stamp: void
=== Inputs ===
result: - 
memoryMap: - 
=== Succesors ===
=== Usages ===
=== Predecessor ===
v20 >@ <|@
instruction <@Return|@org.graalvm.compiler.nodes.ReturnNode>@ result: - memoryMap: -  <|@  <|@
    end_IR
  end_block
end_cfg
begin_cfg
  name "After LIRGeneration"
  begin_block
    name "B0"
    from_bci -1
    to_bci -1
    predecessors 
    successors 
    xhandlers
    flags 
    probability 4607182418800017408
    begin_IR
      LIR
      nr   -1  <|@ instruction [rsi|DWORD, rbp|QWORD] = LABEL numbPhis: 0 align: false label: ? <|@ <|@
      nr   -1  <|@ instruction v2|QWORD = MOVE rbp|QWORD moveKind: QWORD <|@ <|@
      nr   -1  <|@ instruction [] = HOTSPOTLOCKSTACK frameMapBuilder: org.graalvm.compiler.lir.amd64.AMD64FrameMapBuilder@13cb46c48 slotKind: QWORD <|@ <|@
      nr   -1  <|@ instruction v0|DWORD = MOVE rsi|DWORD moveKind: DWORD <|@ <|@
      nr   -1  <|@ instruction v1|QWORD[.] = HOTSPOTLOADOBJECTCONSTANT input: Object[Instance<java.lang.Class>] <|@ <|@
      nr   -1  <|@ instruction MOV (x: [v1|QWORD[.] + 128], y: v0|DWORD) size: DWORD <|@ <|@
      nr   -1  <|@ instruction MEMBAR barriers: 4 <|@ <|@
      nr   -1  <|@ instruction RETURN (savedRbp: v2|QWORD, value: -) isStub: false requiresReservedStackAccessCheck: false thread: r15 scratchForSafepointOnReturn: rcx config: org.graalvm.compiler.hotspot.GraalHotSpotVMConfig@13ae06790 <|@ <|@
    end_IR
  end_block
end_cfg
begin_bytecodes
     0: new           #54         // java.lang.Object
     3: dup           
     4: invokespecial #0          // java.lang.Object.<init>:()void
     7: astore_1      
     8: aload_1       
     9: dup           
    10: astore_2      
    11: monitorenter  
    12: iload_0       
    13: putstatic     #54         // intField:int
    16: aload_2       
    17: monitorexit   
    18: goto          26
    21: astore_3      
    22: aload_2       
    23: monitorexit   
    24: aload_3       
    25: athrow        
    26: return        
   <|@
end_bytecodes
begin_cfg
  name "After LIR generation"
  begin_block
    name "B0"
    from_bci -1
    to_bci -1
    predecessors 
    successors 
    xhandlers
    flags 
    probability 4607182418800017408
    begin_IR
      HIR
f <@#|@fixed with next>@ <|@
tid v0 <|@
d <@d|@=== Debug Properties ===
stamp: void
withSpeculationFence: false
=== Inputs ===
stateAfter: - 
=== Succesors ===
next: v19 
=== Usages ===
=== Predecessor ===
- >@ <|@
instruction <@StartNode|@org.graalvm.compiler.nodes.StartNode>@ stateAfter: - #next: v19  <|@  <|@
f <@#|@fixed with next>@ <|@
tid v19 <|@
d <@d|@=== Debug Properties ===
barriers: 10
location: ANY_LOCATION
stamp: void
=== Inputs ===
=== Succesors ===
next: v17 
=== Usages ===
=== Predecessor ===
v0 >@ <|@
instruction <@Membar|@org.graalvm.compiler.nodes.extended.MembarNode>@ #next: v17  <|@  <|@
f <@~|@floating>@ <|@
tid a14 <|@
result v1|QWORD[.] <|@
d <@d|@=== Debug Properties ===
isDefaultStable: false
nodeSourcePosition: at JavaExamples.exampleLocalSynchronized(JavaExamples.java:350) [bci: 13]
rawvalue: Instance<java.lang.Class>
stableDimension: 0
stamp: a!# Ljava/lang/Class;
stampKind: a -
value: Object[Instance<java.lang.Class>]
=== Inputs ===
=== Succesors ===
=== Usages ===
v18 
=== Predecessor ===
- >@ <|@
instruction <@Constant|@org.graalvm.compiler.nodes.ConstantNode>@  <|@  <|@
f <@~|@floating>@ <|@
tid v18 <|@
result [v1|QWORD[.] + 128] <|@
d <@d|@=== Debug Properties ===
displacement: 128
scale: Times1
stamp: void*
=== Inputs ===
base: a14 
index: - 
=== Succesors ===
=== Usages ===
v17 
=== Predecessor ===
- >@ <|@
instruction <@AMD64Address|@org.graalvm.compiler.core.amd64.AMD64AddressNode>@ base: a14 index: -  <|@  <|@
f <@~|@floating>@ <|@
tid i1 <|@
result v0|DWORD <|@
d <@d|@=== Debug Properties ===
index: 0
stamp: i32
uncheckedStamp: [null]
=== Inputs ===
=== Succesors ===
=== Usages ===
v17 
=== Predecessor ===
- >@ <|@
instruction <@Parameter|@org.graalvm.compiler.nodes.ParameterNode>@  <|@  <|@
f <@#|@fixed with next>@ <|@
tid v17 <|@
d <@d|@=== Debug Properties ===
barrierType: NONE
location: JavaExamples.intField
nodeSourcePosition: at JavaExamples.exampleLocalSynchronized(JavaExamples.java:350) [bci: 13]
nullCheck: false
stamp: void
volatileAccess: true
=== Inputs ===
stateBefore: - 
guard: - 
address: v18 
value: i1 
stateAfter: - 
lastLocationAccess: - 
=== Succesors ===
next: v20 
=== Usages ===
=== Predecessor ===
v19 >@ <|@
instruction <@Write|@org.graalvm.compiler.nodes.memory.WriteNode>@ stateBefore: - guard: - address: v18 value: i1 stateAfter: - lastLocationAccess: - #next: v20  <|@  <|@
f <@#|@fixed with next>@ <|@
tid v20 <|@
d <@d|@=== Debug Properties ===
barriers: 12
location: ANY_LOCATION
stamp: void
=== Inputs ===
=== Succesors ===
next: v11 
=== Usages ===
=== Predecessor ===
v17 >@ <|@
instruction <@Membar|@org.graalvm.compiler.nodes.extended.MembarNode>@ #next: v11  <|@  <|@
f <@*|@fixed>@ <|@
tid v11 <|@
d <@d|@=== Debug Properties ===
nodeSourcePosition: at JavaExamples.exampleLocalSynchronized(JavaExamples.java:352) [bci: 26]
stamp: void
=== Inputs ===
result: - 
memoryMap: - 
=== Succesors ===
=== Usages ===
=== Predecessor ===
v20 >@ <|@
instruction <@Return|@org.graalvm.compiler.nodes.ReturnNode>@ result: - memoryMap: -  <|@  <|@
    end_IR
    begin_IR
      LIR
      nr   -1  <|@ instruction [rsi|DWORD, rbp|QWORD] = LABEL numbPhis: 0 align: false label: ? <|@ <|@
      nr   -1  <|@ instruction v2|QWORD = MOVE rbp|QWORD moveKind: QWORD <|@ <|@
      nr   -1  <|@ instruction [] = HOTSPOTLOCKSTACK frameMapBuilder: org.graalvm.compiler.lir.amd64.AMD64FrameMapBuilder@13cb46c48 slotKind: QWORD <|@ <|@
      nr   -1  <|@ instruction v0|DWORD = MOVE rsi|DWORD moveKind: DWORD <|@ <|@
      nr   -1  <|@ instruction v1|QWORD[.] = HOTSPOTLOADOBJECTCONSTANT input: Object[Instance<java.lang.Class>] <|@ <|@
      nr   -1  <|@ instruction MOV (x: [v1|QWORD[.] + 128], y: v0|DWORD) size: DWORD <|@ <|@
      nr   -1  <|@ instruction MEMBAR barriers: 4 <|@ <|@
      nr   -1  <|@ instruction RETURN (savedRbp: v2|QWORD, value: -) isStub: false requiresReservedStackAccessCheck: false thread: r15 scratchForSafepointOnReturn: rcx config: org.graalvm.compiler.hotspot.GraalHotSpotVMConfig@13ae06790 <|@ <|@
    end_IR
  end_block
end_cfg
begin_cfg
  name "After ConstantLoadOptimization"
  begin_block
    name "B0"
    from_bci -1
    to_bci -1
    predecessors 
    successors 
    xhandlers
    flags 
    probability 4607182418800017408
    begin_IR
      LIR
      nr   -1  <|@ instruction [rsi|DWORD, rbp|QWORD] = LABEL numbPhis: 0 align: false label: ? <|@ <|@
      nr   -1  <|@ instruction v2|QWORD = MOVE rbp|QWORD moveKind: QWORD <|@ <|@
      nr   -1  <|@ instruction [] = HOTSPOTLOCKSTACK frameMapBuilder: org.graalvm.compiler.lir.amd64.AMD64FrameMapBuilder@13cb46c48 slotKind: QWORD <|@ <|@
      nr   -1  <|@ instruction v0|DWORD = MOVE rsi|DWORD moveKind: DWORD <|@ <|@
      nr   -1  <|@ instruction v1|QWORD[.] = HOTSPOTLOADOBJECTCONSTANT input: Object[Instance<java.lang.Class>] <|@ <|@
      nr   -1  <|@ instruction MOV (x: [v1|QWORD[.] + 128], y: v0|DWORD) size: DWORD <|@ <|@
      nr   -1  <|@ instruction MEMBAR barriers: 4 <|@ <|@
      nr   -1  <|@ instruction RETURN (savedRbp: v2|QWORD, value: -) isStub: false requiresReservedStackAccessCheck: false thread: r15 scratchForSafepointOnReturn: rcx config: org.graalvm.compiler.hotspot.GraalHotSpotVMConfig@13ae06790 <|@ <|@
    end_IR
  end_block
end_cfg
begin_bytecodes
     0: new           #54         // java.lang.Object
     3: dup           
     4: invokespecial #0          // java.lang.Object.<init>:()void
     7: astore_1      
     8: aload_1       
     9: dup           
    10: astore_2      
    11: monitorenter  
    12: iload_0       
    13: putstatic     #54         // intField:int
    16: aload_2       
    17: monitorexit   
    18: goto          26
    21: astore_3      
    22: aload_2       
    23: monitorexit   
    24: aload_3       
    25: athrow        
    26: return        
   <|@
end_bytecodes
begin_cfg
  name "After SaveCalleeSaveRegisters"
  begin_block
    name "B0"
    from_bci -1
    to_bci -1
    predecessors 
    successors 
    xhandlers
    flags 
    probability 4607182418800017408
    begin_IR
      LIR
      nr   -1  <|@ instruction [rsi|DWORD, rbp|QWORD] = LABEL numbPhis: 0 align: false label: ? <|@ <|@
      nr   -1  <|@ instruction v2|QWORD = MOVE rbp|QWORD moveKind: QWORD <|@ <|@
      nr   -1  <|@ instruction [] = HOTSPOTLOCKSTACK frameMapBuilder: org.graalvm.compiler.lir.amd64.AMD64FrameMapBuilder@13cb46c48 slotKind: QWORD <|@ <|@
      nr   -1  <|@ instruction v0|DWORD = MOVE rsi|DWORD moveKind: DWORD <|@ <|@
      nr   -1  <|@ instruction v1|QWORD[.] = HOTSPOTLOADOBJECTCONSTANT input: Object[Instance<java.lang.Class>] <|@ <|@
      nr   -1  <|@ instruction MOV (x: [v1|QWORD[.] + 128], y: v0|DWORD) size: DWORD <|@ <|@
      nr   -1  <|@ instruction MEMBAR barriers: 4 <|@ <|@
      nr   -1  <|@ instruction RETURN (savedRbp: v2|QWORD, value: -) isStub: false requiresReservedStackAccessCheck: false thread: r15 scratchForSafepointOnReturn: rcx config: org.graalvm.compiler.hotspot.GraalHotSpotVMConfig@13ae06790 <|@ <|@
    end_IR
  end_block
end_cfg
begin_bytecodes
     0: new           #54         // java.lang.Object
     3: dup           
     4: invokespecial #0          // java.lang.Object.<init>:()void
     7: astore_1      
     8: aload_1       
     9: dup           
    10: astore_2      
    11: monitorenter  
    12: iload_0       
    13: putstatic     #54         // intField:int
    16: aload_2       
    17: monitorexit   
    18: goto          26
    21: astore_3      
    22: aload_2       
    23: monitorexit   
    24: aload_3       
    25: athrow        
    26: return        
   <|@
end_bytecodes
begin_cfg
  name "After PreAllocationOptimizationStage"
  begin_block
    name "B0"
    from_bci -1
    to_bci -1
    predecessors 
    successors 
    xhandlers
    flags 
    probability 4607182418800017408
    begin_IR
      LIR
      nr   -1  <|@ instruction [rsi|DWORD, rbp|QWORD] = LABEL numbPhis: 0 align: false label: ? <|@ <|@
      nr   -1  <|@ instruction v2|QWORD = MOVE rbp|QWORD moveKind: QWORD <|@ <|@
      nr   -1  <|@ instruction [] = HOTSPOTLOCKSTACK frameMapBuilder: org.graalvm.compiler.lir.amd64.AMD64FrameMapBuilder@13cb46c48 slotKind: QWORD <|@ <|@
      nr   -1  <|@ instruction v0|DWORD = MOVE rsi|DWORD moveKind: DWORD <|@ <|@
      nr   -1  <|@ instruction v1|QWORD[.] = HOTSPOTLOADOBJECTCONSTANT input: Object[Instance<java.lang.Class>] <|@ <|@
      nr   -1  <|@ instruction MOV (x: [v1|QWORD[.] + 128], y: v0|DWORD) size: DWORD <|@ <|@
      nr   -1  <|@ instruction MEMBAR barriers: 4 <|@ <|@
      nr   -1  <|@ instruction RETURN (savedRbp: v2|QWORD, value: -) isStub: false requiresReservedStackAccessCheck: false thread: r15 scratchForSafepointOnReturn: rcx config: org.graalvm.compiler.hotspot.GraalHotSpotVMConfig@13ae06790 <|@ <|@
    end_IR
  end_block
end_cfg
begin_bytecodes
     0: new           #54         // java.lang.Object
     3: dup           
     4: invokespecial #0          // java.lang.Object.<init>:()void
     7: astore_1      
     8: aload_1       
     9: dup           
    10: astore_2      
    11: monitorenter  
    12: iload_0       
    13: putstatic     #54         // intField:int
    16: aload_2       
    17: monitorexit   
    18: goto          26
    21: astore_3      
    22: aload_2       
    23: monitorexit   
    24: aload_3       
    25: athrow        
    26: return        
   <|@
end_bytecodes
begin_cfg
  name "After MarkBasePointers"
  begin_block
    name "B0"
    from_bci -1
    to_bci -1
    predecessors 
    successors 
    xhandlers
    flags 
    probability 4607182418800017408
    begin_IR
      LIR
      nr   -1  <|@ instruction [rsi|DWORD, rbp|QWORD] = LABEL numbPhis: 0 align: false label: ? <|@ <|@
      nr   -1  <|@ instruction v2|QWORD = MOVE rbp|QWORD moveKind: QWORD <|@ <|@
      nr   -1  <|@ instruction [] = HOTSPOTLOCKSTACK frameMapBuilder: org.graalvm.compiler.lir.amd64.AMD64FrameMapBuilder@13cb46c48 slotKind: QWORD <|@ <|@
      nr   -1  <|@ instruction v0|DWORD = MOVE rsi|DWORD moveKind: DWORD <|@ <|@
      nr   -1  <|@ instruction v1|QWORD[.] = HOTSPOTLOADOBJECTCONSTANT input: Object[Instance<java.lang.Class>] <|@ <|@
      nr   -1  <|@ instruction MOV (x: [v1|QWORD[.] + 128], y: v0|DWORD) size: DWORD <|@ <|@
      nr   -1  <|@ instruction MEMBAR barriers: 4 <|@ <|@
      nr   -1  <|@ instruction RETURN (savedRbp: v2|QWORD, value: -) isStub: false requiresReservedStackAccessCheck: false thread: r15 scratchForSafepointOnReturn: rcx config: org.graalvm.compiler.hotspot.GraalHotSpotVMConfig@13ae06790 <|@ <|@
    end_IR
  end_block
end_cfg
begin_bytecodes
     0: new           #54         // java.lang.Object
     3: dup           
     4: invokespecial #0          // java.lang.Object.<init>:()void
     7: astore_1      
     8: aload_1       
     9: dup           
    10: astore_2      
    11: monitorenter  
    12: iload_0       
    13: putstatic     #54         // intField:int
    16: aload_2       
    17: monitorexit   
    18: goto          26
    21: astore_3      
    22: aload_2       
    23: monitorexit   
    24: aload_3       
    25: athrow        
    26: return        
   <|@
end_bytecodes
begin_cfg
  name "Before register allocation"
  begin_block
    name "B0"
    from_bci -1
    to_bci -1
    predecessors 
    successors 
    xhandlers
    flags 
    probability 4607182418800017408
    begin_IR
      LIR
      nr    0  <|@ instruction [rsi|DWORD, rbp|QWORD] = LABEL numbPhis: 0 align: false label: ? <|@ <|@
      nr    2  <|@ instruction v2|QWORD = MOVE rbp|QWORD moveKind: QWORD <|@ <|@
      nr    4  <|@ instruction [] = HOTSPOTLOCKSTACK frameMapBuilder: org.graalvm.compiler.lir.amd64.AMD64FrameMapBuilder@13cb46c48 slotKind: QWORD <|@ <|@
      nr    6  <|@ instruction v0|DWORD = MOVE rsi|DWORD moveKind: DWORD <|@ <|@
      nr    8  <|@ instruction v1|QWORD[.] = HOTSPOTLOADOBJECTCONSTANT input: Object[Instance<java.lang.Class>] <|@ <|@
      nr   10  <|@ instruction MOV (x: [v1|QWORD[.] + 128], y: v0|DWORD) size: DWORD <|@ <|@
      nr   12  <|@ instruction MEMBAR barriers: 4 <|@ <|@
      nr   14  <|@ instruction RETURN (savedRbp: v2|QWORD, value: -) isStub: false requiresReservedStackAccessCheck: false thread: r15 scratchForSafepointOnReturn: rcx config: org.graalvm.compiler.hotspot.GraalHotSpotVMConfig@13ae06790 <|@ <|@
    end_IR
  end_block
end_cfg
begin_bytecodes
     0: new           #54         // java.lang.Object
     3: dup           
     4: invokespecial #0          // java.lang.Object.<init>:()void
     7: astore_1      
     8: aload_1       
     9: dup           
    10: astore_2      
    11: monitorenter  
    12: iload_0       
    13: putstatic     #54         // intField:int
    16: aload_2       
    17: monitorexit   
    18: goto          26
    21: astore_3      
    22: aload_2       
    23: monitorexit   
    24: aload_3       
    25: athrow        
    26: return        
   <|@
end_bytecodes
begin_cfg
  name "After SSALinearScanLifetimeAnalysis"
  begin_block
    name "B0"
    from_bci -1
    to_bci -1
    predecessors 
    successors 
    xhandlers
    flags 
    probability 4607182418800017408
    begin_IR
      LIR
      nr    0  <|@ instruction [rsi|DWORD, rbp|QWORD] = LABEL numbPhis: 0 align: false label: ? <|@ <|@
      nr    2  <|@ instruction v2|QWORD = MOVE rbp|QWORD moveKind: QWORD <|@ <|@
      nr    4  <|@ instruction [] = HOTSPOTLOCKSTACK frameMapBuilder: org.graalvm.compiler.lir.amd64.AMD64FrameMapBuilder@13cb46c48 slotKind: QWORD <|@ <|@
      nr    6  <|@ instruction v0|DWORD = MOVE rsi|DWORD moveKind: DWORD <|@ <|@
      nr    8  <|@ instruction v1|QWORD[.] = HOTSPOTLOADOBJECTCONSTANT input: Object[Instance<java.lang.Class>] <|@ <|@
      nr   10  <|@ instruction MOV (x: [v1|QWORD[.] + 128], y: v0|DWORD) size: DWORD <|@ <|@
      nr   12  <|@ instruction MEMBAR barriers: 4 <|@ <|@
      nr   14  <|@ instruction RETURN (savedRbp: v2|QWORD, value: -) isStub: false requiresReservedStackAccessCheck: false thread: r15 scratchForSafepointOnReturn: rcx config: org.graalvm.compiler.hotspot.GraalHotSpotVMConfig@13ae06790 <|@ <|@
    end_IR
  end_block
end_cfg
begin_bytecodes
     0: new           #54         // java.lang.Object
     3: dup           
     4: invokespecial #0          // java.lang.Object.<init>:()void
     7: astore_1      
     8: aload_1       
     9: dup           
    10: astore_2      
    11: monitorenter  
    12: iload_0       
    13: putstatic     #54         // intField:int
    16: aload_2       
    17: monitorexit   
    18: goto          26
    21: astore_3      
    22: aload_2       
    23: monitorexit   
    24: aload_3       
    25: athrow        
    26: return        
   <|@
end_bytecodes
begin_intervals
  name "Before register allocation"
  rbp|q fixed "[rbp|q]" rbp|q -1 [0, 2[ "NoSpillStore"
  rsi|d fixed "[rsi|d]" rsi|d -1 [0, 6[ "NoSpillStore"
  v0|d DWORD "[v0|d]" v0|d rsi|d [6, 10[6 MustHaveRegister 10 MustHaveRegister  "NoSpillStore"
  v1|q QWORD "[v1|q]" v1|q -1 [8, 10[8 MustHaveRegister 10 MustHaveRegister  "NoSpillStore"
  v2|q QWORD "[v2|q]" v2|q rbp|q [2, 14[2 MustHaveRegister 14 ShouldHaveRegister  "NoSpillStore"
end_intervals
begin_intervals
  name "After register allocation"
  rbp|q fixed "[rbp|q]" rbp|q -1 [0, 2[ "NoSpillStore"
  rsi|d fixed "[rsi|d]" rsi|d -1 [0, 6[ "NoSpillStore"
  v0|d DWORD "[rsi|d]" v0|d rsi|d [6, 10[6 MustHaveRegister 10 MustHaveRegister  "NoSpillStore"
  v1|q QWORD "[r10|q]" v1|q -1 [8, 10[8 MustHaveRegister 10 MustHaveRegister  "NoSpillStore"
  v2|q QWORD "[rbp|q]" v2|q rbp|q [2, 14[2 MustHaveRegister 14 ShouldHaveRegister  "NoSpillStore"
end_intervals
begin_cfg
  name "After LinearScanRegisterAllocation"
  begin_block
    name "B0"
    from_bci -1
    to_bci -1
    predecessors 
    successors 
    xhandlers
    flags 
    probability 4607182418800017408
    begin_IR
      LIR
      nr    0  <|@ instruction [rsi|DWORD, rbp|QWORD] = LABEL numbPhis: 0 align: false label: ? <|@ <|@
      nr    2  <|@ instruction v2|QWORD = MOVE rbp|QWORD moveKind: QWORD <|@ <|@
      nr    4  <|@ instruction [] = HOTSPOTLOCKSTACK frameMapBuilder: org.graalvm.compiler.lir.amd64.AMD64FrameMapBuilder@13cb46c48 slotKind: QWORD <|@ <|@
      nr    6  <|@ instruction v0|DWORD = MOVE rsi|DWORD moveKind: DWORD <|@ <|@
      nr    8  <|@ instruction v1|QWORD[.] = HOTSPOTLOADOBJECTCONSTANT input: Object[Instance<java.lang.Class>] <|@ <|@
      nr   10  <|@ instruction MOV (x: [v1|QWORD[.] + 128], y: v0|DWORD) size: DWORD <|@ <|@
      nr   12  <|@ instruction MEMBAR barriers: 4 <|@ <|@
      nr   14  <|@ instruction RETURN (savedRbp: v2|QWORD, value: -) isStub: false requiresReservedStackAccessCheck: false thread: r15 scratchForSafepointOnReturn: rcx config: org.graalvm.compiler.hotspot.GraalHotSpotVMConfig@13ae06790 <|@ <|@
    end_IR
  end_block
end_cfg
begin_bytecodes
     0: new           #54         // java.lang.Object
     3: dup           
     4: invokespecial #0          // java.lang.Object.<init>:()void
     7: astore_1      
     8: aload_1       
     9: dup           
    10: astore_2      
    11: monitorenter  
    12: iload_0       
    13: putstatic     #54         // intField:int
    16: aload_2       
    17: monitorexit   
    18: goto          26
    21: astore_3      
    22: aload_2       
    23: monitorexit   
    24: aload_3       
    25: athrow        
    26: return        
   <|@
end_bytecodes
begin_intervals
  name "After optimize spill position"
  rbp|q fixed "[rbp|q]" rbp|q -1 [0, 2[ "NoSpillStore"
  rsi|d fixed "[rsi|d]" rsi|d -1 [0, 6[ "NoSpillStore"
  v0|d DWORD "[rsi|d]" v0|d rsi|d [6, 10[6 MustHaveRegister 10 MustHaveRegister  "NoSpillStore"
  v1|q QWORD "[r10|q]" v1|q -1 [8, 10[8 MustHaveRegister 10 MustHaveRegister  "NoSpillStore"
  v2|q QWORD "[rbp|q]" v2|q rbp|q [2, 14[2 MustHaveRegister 14 ShouldHaveRegister  "NoSpillStore"
end_intervals
begin_cfg
  name "After LinearScanOptimizeSpillPosition"
  begin_block
    name "B0"
    from_bci -1
    to_bci -1
    predecessors 
    successors 
    xhandlers
    flags 
    probability 4607182418800017408
    begin_IR
      LIR
      nr    0  <|@ instruction [rsi|DWORD, rbp|QWORD] = LABEL numbPhis: 0 align: false label: ? <|@ <|@
      nr    2  <|@ instruction v2|QWORD = MOVE rbp|QWORD moveKind: QWORD <|@ <|@
      nr    4  <|@ instruction [] = HOTSPOTLOCKSTACK frameMapBuilder: org.graalvm.compiler.lir.amd64.AMD64FrameMapBuilder@13cb46c48 slotKind: QWORD <|@ <|@
      nr    6  <|@ instruction v0|DWORD = MOVE rsi|DWORD moveKind: DWORD <|@ <|@
      nr    8  <|@ instruction v1|QWORD[.] = HOTSPOTLOADOBJECTCONSTANT input: Object[Instance<java.lang.Class>] <|@ <|@
      nr   10  <|@ instruction MOV (x: [v1|QWORD[.] + 128], y: v0|DWORD) size: DWORD <|@ <|@
      nr   12  <|@ instruction MEMBAR barriers: 4 <|@ <|@
      nr   14  <|@ instruction RETURN (savedRbp: v2|QWORD, value: -) isStub: false requiresReservedStackAccessCheck: false thread: r15 scratchForSafepointOnReturn: rcx config: org.graalvm.compiler.hotspot.GraalHotSpotVMConfig@13ae06790 <|@ <|@
    end_IR
  end_block
end_cfg
begin_bytecodes
     0: new           #54         // java.lang.Object
     3: dup           
     4: invokespecial #0          // java.lang.Object.<init>:()void
     7: astore_1      
     8: aload_1       
     9: dup           
    10: astore_2      
    11: monitorenter  
    12: iload_0       
    13: putstatic     #54         // intField:int
    16: aload_2       
    17: monitorexit   
    18: goto          26
    21: astore_3      
    22: aload_2       
    23: monitorexit   
    24: aload_3       
    25: athrow        
    26: return        
   <|@
end_bytecodes
begin_intervals
  name "After resolve data flow"
  rbp|q fixed "[rbp|q]" rbp|q -1 [0, 2[ "NoSpillStore"
  rsi|d fixed "[rsi|d]" rsi|d -1 [0, 6[ "NoSpillStore"
  v0|d DWORD "[rsi|d]" v0|d rsi|d [6, 10[6 MustHaveRegister 10 MustHaveRegister  "NoSpillStore"
  v1|q QWORD "[r10|q]" v1|q -1 [8, 10[8 MustHaveRegister 10 MustHaveRegister  "NoSpillStore"
  v2|q QWORD "[rbp|q]" v2|q rbp|q [2, 14[2 MustHaveRegister 14 ShouldHaveRegister  "NoSpillStore"
end_intervals
begin_cfg
  name "After SSALinearScanResolveDataFlow"
  begin_block
    name "B0"
    from_bci -1
    to_bci -1
    predecessors 
    successors 
    xhandlers
    flags 
    probability 4607182418800017408
    begin_IR
      LIR
      nr    0  <|@ instruction [rsi|DWORD, rbp|QWORD] = LABEL numbPhis: 0 align: false label: ? <|@ <|@
      nr    2  <|@ instruction v2|QWORD = MOVE rbp|QWORD moveKind: QWORD <|@ <|@
      nr    4  <|@ instruction [] = HOTSPOTLOCKSTACK frameMapBuilder: org.graalvm.compiler.lir.amd64.AMD64FrameMapBuilder@13cb46c48 slotKind: QWORD <|@ <|@
      nr    6  <|@ instruction v0|DWORD = MOVE rsi|DWORD moveKind: DWORD <|@ <|@
      nr    8  <|@ instruction v1|QWORD[.] = HOTSPOTLOADOBJECTCONSTANT input: Object[Instance<java.lang.Class>] <|@ <|@
      nr   10  <|@ instruction MOV (x: [v1|QWORD[.] + 128], y: v0|DWORD) size: DWORD <|@ <|@
      nr   12  <|@ instruction MEMBAR barriers: 4 <|@ <|@
      nr   14  <|@ instruction RETURN (savedRbp: v2|QWORD, value: -) isStub: false requiresReservedStackAccessCheck: false thread: r15 scratchForSafepointOnReturn: rcx config: org.graalvm.compiler.hotspot.GraalHotSpotVMConfig@13ae06790 <|@ <|@
    end_IR
  end_block
end_cfg
begin_bytecodes
     0: new           #54         // java.lang.Object
     3: dup           
     4: invokespecial #0          // java.lang.Object.<init>:()void
     7: astore_1      
     8: aload_1       
     9: dup           
    10: astore_2      
    11: monitorenter  
    12: iload_0       
    13: putstatic     #54         // intField:int
    16: aload_2       
    17: monitorexit   
    18: goto          26
    21: astore_3      
    22: aload_2       
    23: monitorexit   
    24: aload_3       
    25: athrow        
    26: return        
   <|@
end_bytecodes
begin_cfg
  name "After SSALinearScanEliminateSpillMove"
  begin_block
    name "B0"
    from_bci -1
    to_bci -1
    predecessors 
    successors 
    xhandlers
    flags 
    probability 4607182418800017408
    begin_IR
      LIR
      nr    0  <|@ instruction [rsi|DWORD, rbp|QWORD] = LABEL numbPhis: 0 align: false label: ? <|@ <|@
      nr    2  <|@ instruction v2|QWORD = MOVE rbp|QWORD moveKind: QWORD <|@ <|@
      nr    4  <|@ instruction [] = HOTSPOTLOCKSTACK frameMapBuilder: org.graalvm.compiler.lir.amd64.AMD64FrameMapBuilder@13cb46c48 slotKind: QWORD <|@ <|@
      nr    6  <|@ instruction v0|DWORD = MOVE rsi|DWORD moveKind: DWORD <|@ <|@
      nr    8  <|@ instruction v1|QWORD[.] = HOTSPOTLOADOBJECTCONSTANT input: Object[Instance<java.lang.Class>] <|@ <|@
      nr   10  <|@ instruction MOV (x: [v1|QWORD[.] + 128], y: v0|DWORD) size: DWORD <|@ <|@
      nr   12  <|@ instruction MEMBAR barriers: 4 <|@ <|@
      nr   14  <|@ instruction RETURN (savedRbp: v2|QWORD, value: -) isStub: false requiresReservedStackAccessCheck: false thread: r15 scratchForSafepointOnReturn: rcx config: org.graalvm.compiler.hotspot.GraalHotSpotVMConfig@13ae06790 <|@ <|@
    end_IR
  end_block
end_cfg
begin_bytecodes
     0: new           #54         // java.lang.Object
     3: dup           
     4: invokespecial #0          // java.lang.Object.<init>:()void
     7: astore_1      
     8: aload_1       
     9: dup           
    10: astore_2      
    11: monitorenter  
    12: iload_0       
    13: putstatic     #54         // intField:int
    16: aload_2       
    17: monitorexit   
    18: goto          26
    21: astore_3      
    22: aload_2       
    23: monitorexit   
    24: aload_3       
    25: athrow        
    26: return        
   <|@
end_bytecodes
begin_cfg
  name "After LinearScanAssignLocations"
  begin_block
    name "B0"
    from_bci -1
    to_bci -1
    predecessors 
    successors 
    xhandlers
    flags 
    probability 4607182418800017408
    begin_IR
      LIR
      nr    0  <|@ instruction [rsi|DWORD, rbp|QWORD] = LABEL numbPhis: 0 align: false label: ? <|@ <|@
      nr    4  <|@ instruction [] = HOTSPOTLOCKSTACK frameMapBuilder: org.graalvm.compiler.lir.amd64.AMD64FrameMapBuilder@13cb46c48 slotKind: QWORD <|@ <|@
      nr    8  <|@ instruction r10|QWORD[.] = HOTSPOTLOADOBJECTCONSTANT input: Object[Instance<java.lang.Class>] <|@ <|@
      nr   10  <|@ instruction MOV (x: [r10|QWORD[.] + 128], y: rsi|DWORD) size: DWORD <|@ <|@
      nr   12  <|@ instruction MEMBAR barriers: 4 <|@ <|@
      nr   14  <|@ instruction RETURN (savedRbp: rbp|QWORD, value: -) isStub: false requiresReservedStackAccessCheck: false thread: r15 scratchForSafepointOnReturn: rcx config: org.graalvm.compiler.hotspot.GraalHotSpotVMConfig@13ae06790 <|@ <|@
    end_IR
  end_block
end_cfg
begin_bytecodes
     0: new           #54         // java.lang.Object
     3: dup           
     4: invokespecial #0          // java.lang.Object.<init>:()void
     7: astore_1      
     8: aload_1       
     9: dup           
    10: astore_2      
    11: monitorenter  
    12: iload_0       
    13: putstatic     #54         // intField:int
    16: aload_2       
    17: monitorexit   
    18: goto          26
    21: astore_3      
    22: aload_2       
    23: monitorexit   
    24: aload_3       
    25: athrow        
    26: return        
   <|@
end_bytecodes
begin_cfg
  name "After LinearScan"
  begin_block
    name "B0"
    from_bci -1
    to_bci -1
    predecessors 
    successors 
    xhandlers
    flags 
    probability 4607182418800017408
    begin_IR
      LIR
      nr    0  <|@ instruction [rsi|DWORD, rbp|QWORD] = LABEL numbPhis: 0 align: false label: ? <|@ <|@
      nr    4  <|@ instruction [] = HOTSPOTLOCKSTACK frameMapBuilder: org.graalvm.compiler.lir.amd64.AMD64FrameMapBuilder@13cb46c48 slotKind: QWORD <|@ <|@
      nr    8  <|@ instruction r10|QWORD[.] = HOTSPOTLOADOBJECTCONSTANT input: Object[Instance<java.lang.Class>] <|@ <|@
      nr   10  <|@ instruction MOV (x: [r10|QWORD[.] + 128], y: rsi|DWORD) size: DWORD <|@ <|@
      nr   12  <|@ instruction MEMBAR barriers: 4 <|@ <|@
      nr   14  <|@ instruction RETURN (savedRbp: rbp|QWORD, value: -) isStub: false requiresReservedStackAccessCheck: false thread: r15 scratchForSafepointOnReturn: rcx config: org.graalvm.compiler.hotspot.GraalHotSpotVMConfig@13ae06790 <|@ <|@
    end_IR
  end_block
end_cfg
begin_bytecodes
     0: new           #54         // java.lang.Object
     3: dup           
     4: invokespecial #0          // java.lang.Object.<init>:()void
     7: astore_1      
     8: aload_1       
     9: dup           
    10: astore_2      
    11: monitorenter  
    12: iload_0       
    13: putstatic     #54         // intField:int
    16: aload_2       
    17: monitorexit   
    18: goto          26
    21: astore_3      
    22: aload_2       
    23: monitorexit   
    24: aload_3       
    25: athrow        
    26: return        
   <|@
end_bytecodes
begin_cfg
  name "After LSStackSlotAllocator"
  begin_block
    name "B0"
    from_bci -1
    to_bci -1
    predecessors 
    successors 
    xhandlers
    flags 
    probability 4607182418800017408
    begin_IR
      LIR
      nr    0  <|@ instruction [rsi|DWORD, rbp|QWORD] = LABEL numbPhis: 0 align: false label: ? <|@ <|@
      nr    4  <|@ instruction [] = HOTSPOTLOCKSTACK frameMapBuilder: org.graalvm.compiler.lir.amd64.AMD64FrameMapBuilder@13cb46c48 slotKind: QWORD <|@ <|@
      nr    8  <|@ instruction r10|QWORD[.] = HOTSPOTLOADOBJECTCONSTANT input: Object[Instance<java.lang.Class>] <|@ <|@
      nr   10  <|@ instruction MOV (x: [r10|QWORD[.] + 128], y: rsi|DWORD) size: DWORD <|@ <|@
      nr   12  <|@ instruction MEMBAR barriers: 4 <|@ <|@
      nr   14  <|@ instruction RETURN (savedRbp: rbp|QWORD, value: -) isStub: false requiresReservedStackAccessCheck: false thread: r15 scratchForSafepointOnReturn: rcx config: org.graalvm.compiler.hotspot.GraalHotSpotVMConfig@13ae06790 <|@ <|@
    end_IR
  end_block
end_cfg
begin_bytecodes
     0: new           #54         // java.lang.Object
     3: dup           
     4: invokespecial #0          // java.lang.Object.<init>:()void
     7: astore_1      
     8: aload_1       
     9: dup           
    10: astore_2      
    11: monitorenter  
    12: iload_0       
    13: putstatic     #54         // intField:int
    16: aload_2       
    17: monitorexit   
    18: goto          26
    21: astore_3      
    22: aload_2       
    23: monitorexit   
    24: aload_3       
    25: athrow        
    26: return        
   <|@
end_bytecodes
begin_cfg
  name "After LocationMarker"
  begin_block
    name "B0"
    from_bci -1
    to_bci -1
    predecessors 
    successors 
    xhandlers
    flags 
    probability 4607182418800017408
    begin_IR
      LIR
      nr    0  <|@ instruction [rsi|DWORD, rbp|QWORD] = LABEL numbPhis: 0 align: false label: ? <|@ <|@
      nr    4  <|@ instruction [] = HOTSPOTLOCKSTACK frameMapBuilder: org.graalvm.compiler.lir.amd64.AMD64FrameMapBuilder@13cb46c48 slotKind: QWORD <|@ <|@
      nr    8  <|@ instruction r10|QWORD[.] = HOTSPOTLOADOBJECTCONSTANT input: Object[Instance<java.lang.Class>] <|@ <|@
      nr   10  <|@ instruction MOV (x: [r10|QWORD[.] + 128], y: rsi|DWORD) size: DWORD <|@ <|@
      nr   12  <|@ instruction MEMBAR barriers: 4 <|@ <|@
      nr   14  <|@ instruction RETURN (savedRbp: rbp|QWORD, value: -) isStub: false requiresReservedStackAccessCheck: false thread: r15 scratchForSafepointOnReturn: rcx config: org.graalvm.compiler.hotspot.GraalHotSpotVMConfig@13ae06790 <|@ <|@
    end_IR
  end_block
end_cfg
begin_bytecodes
     0: new           #54         // java.lang.Object
     3: dup           
     4: invokespecial #0          // java.lang.Object.<init>:()void
     7: astore_1      
     8: aload_1       
     9: dup           
    10: astore_2      
    11: monitorenter  
    12: iload_0       
    13: putstatic     #54         // intField:int
    16: aload_2       
    17: monitorexit   
    18: goto          26
    21: astore_3      
    22: aload_2       
    23: monitorexit   
    24: aload_3       
    25: athrow        
    26: return        
   <|@
end_bytecodes
begin_cfg
  name "After AllocationStage"
  begin_block
    name "B0"
    from_bci -1
    to_bci -1
    predecessors 
    successors 
    xhandlers
    flags 
    probability 4607182418800017408
    begin_IR
      LIR
      nr    0  <|@ instruction [rsi|DWORD, rbp|QWORD] = LABEL numbPhis: 0 align: false label: ? <|@ <|@
      nr    4  <|@ instruction [] = HOTSPOTLOCKSTACK frameMapBuilder: org.graalvm.compiler.lir.amd64.AMD64FrameMapBuilder@13cb46c48 slotKind: QWORD <|@ <|@
      nr    8  <|@ instruction r10|QWORD[.] = HOTSPOTLOADOBJECTCONSTANT input: Object[Instance<java.lang.Class>] <|@ <|@
      nr   10  <|@ instruction MOV (x: [r10|QWORD[.] + 128], y: rsi|DWORD) size: DWORD <|@ <|@
      nr   12  <|@ instruction MEMBAR barriers: 4 <|@ <|@
      nr   14  <|@ instruction RETURN (savedRbp: rbp|QWORD, value: -) isStub: false requiresReservedStackAccessCheck: false thread: r15 scratchForSafepointOnReturn: rcx config: org.graalvm.compiler.hotspot.GraalHotSpotVMConfig@13ae06790 <|@ <|@
    end_IR
  end_block
end_cfg
begin_bytecodes
     0: new           #54         // java.lang.Object
     3: dup           
     4: invokespecial #0          // java.lang.Object.<init>:()void
     7: astore_1      
     8: aload_1       
     9: dup           
    10: astore_2      
    11: monitorenter  
    12: iload_0       
    13: putstatic     #54         // intField:int
    16: aload_2       
    17: monitorexit   
    18: goto          26
    21: astore_3      
    22: aload_2       
    23: monitorexit   
    24: aload_3       
    25: athrow        
    26: return        
   <|@
end_bytecodes
begin_cfg
  name "After EdgeMoveOptimizer"
  begin_block
    name "B0"
    from_bci -1
    to_bci -1
    predecessors 
    successors 
    xhandlers
    flags 
    probability 4607182418800017408
    begin_IR
      LIR
      nr    0  <|@ instruction [rsi|DWORD, rbp|QWORD] = LABEL numbPhis: 0 align: false label: ? <|@ <|@
      nr    4  <|@ instruction [] = HOTSPOTLOCKSTACK frameMapBuilder: org.graalvm.compiler.lir.amd64.AMD64FrameMapBuilder@13cb46c48 slotKind: QWORD <|@ <|@
      nr    8  <|@ instruction r10|QWORD[.] = HOTSPOTLOADOBJECTCONSTANT input: Object[Instance<java.lang.Class>] <|@ <|@
      nr   10  <|@ instruction MOV (x: [r10|QWORD[.] + 128], y: rsi|DWORD) size: DWORD <|@ <|@
      nr   12  <|@ instruction MEMBAR barriers: 4 <|@ <|@
      nr   14  <|@ instruction RETURN (savedRbp: rbp|QWORD, value: -) isStub: false requiresReservedStackAccessCheck: false thread: r15 scratchForSafepointOnReturn: rcx config: org.graalvm.compiler.hotspot.GraalHotSpotVMConfig@13ae06790 <|@ <|@
    end_IR
  end_block
end_cfg
begin_bytecodes
     0: new           #54         // java.lang.Object
     3: dup           
     4: invokespecial #0          // java.lang.Object.<init>:()void
     7: astore_1      
     8: aload_1       
     9: dup           
    10: astore_2      
    11: monitorenter  
    12: iload_0       
    13: putstatic     #54         // intField:int
    16: aload_2       
    17: monitorexit   
    18: goto          26
    21: astore_3      
    22: aload_2       
    23: monitorexit   
    24: aload_3       
    25: athrow        
    26: return        
   <|@
end_bytecodes
begin_cfg
  name "After ControlFlowOptimizer"
  begin_block
    name "B0"
    from_bci -1
    to_bci -1
    predecessors 
    successors 
    xhandlers
    flags 
    probability 4607182418800017408
    begin_IR
      LIR
      nr    0  <|@ instruction [rsi|DWORD, rbp|QWORD] = LABEL numbPhis: 0 align: false label: ? <|@ <|@
      nr    4  <|@ instruction [] = HOTSPOTLOCKSTACK frameMapBuilder: org.graalvm.compiler.lir.amd64.AMD64FrameMapBuilder@13cb46c48 slotKind: QWORD <|@ <|@
      nr    8  <|@ instruction r10|QWORD[.] = HOTSPOTLOADOBJECTCONSTANT input: Object[Instance<java.lang.Class>] <|@ <|@
      nr   10  <|@ instruction MOV (x: [r10|QWORD[.] + 128], y: rsi|DWORD) size: DWORD <|@ <|@
      nr   12  <|@ instruction MEMBAR barriers: 4 <|@ <|@
      nr   14  <|@ instruction RETURN (savedRbp: rbp|QWORD, value: -) isStub: false requiresReservedStackAccessCheck: false thread: r15 scratchForSafepointOnReturn: rcx config: org.graalvm.compiler.hotspot.GraalHotSpotVMConfig@13ae06790 <|@ <|@
    end_IR
  end_block
end_cfg
begin_bytecodes
     0: new           #54         // java.lang.Object
     3: dup           
     4: invokespecial #0          // java.lang.Object.<init>:()void
     7: astore_1      
     8: aload_1       
     9: dup           
    10: astore_2      
    11: monitorenter  
    12: iload_0       
    13: putstatic     #54         // intField:int
    16: aload_2       
    17: monitorexit   
    18: goto          26
    21: astore_3      
    22: aload_2       
    23: monitorexit   
    24: aload_3       
    25: athrow        
    26: return        
   <|@
end_bytecodes
begin_cfg
  name "After RedundantMoveElimination"
  begin_block
    name "B0"
    from_bci -1
    to_bci -1
    predecessors 
    successors 
    xhandlers
    flags 
    probability 4607182418800017408
    begin_IR
      LIR
      nr    0  <|@ instruction [rsi|DWORD, rbp|QWORD] = LABEL numbPhis: 0 align: false label: ? <|@ <|@
      nr    4  <|@ instruction [] = HOTSPOTLOCKSTACK frameMapBuilder: org.graalvm.compiler.lir.amd64.AMD64FrameMapBuilder@13cb46c48 slotKind: QWORD <|@ <|@
      nr    8  <|@ instruction r10|QWORD[.] = HOTSPOTLOADOBJECTCONSTANT input: Object[Instance<java.lang.Class>] <|@ <|@
      nr   10  <|@ instruction MOV (x: [r10|QWORD[.] + 128], y: rsi|DWORD) size: DWORD <|@ <|@
      nr   12  <|@ instruction MEMBAR barriers: 4 <|@ <|@
      nr   14  <|@ instruction RETURN (savedRbp: rbp|QWORD, value: -) isStub: false requiresReservedStackAccessCheck: false thread: r15 scratchForSafepointOnReturn: rcx config: org.graalvm.compiler.hotspot.GraalHotSpotVMConfig@13ae06790 <|@ <|@
    end_IR
  end_block
end_cfg
begin_bytecodes
     0: new           #54         // java.lang.Object
     3: dup           
     4: invokespecial #0          // java.lang.Object.<init>:()void
     7: astore_1      
     8: aload_1       
     9: dup           
    10: astore_2      
    11: monitorenter  
    12: iload_0       
    13: putstatic     #54         // intField:int
    16: aload_2       
    17: monitorexit   
    18: goto          26
    21: astore_3      
    22: aload_2       
    23: monitorexit   
    24: aload_3       
    25: athrow        
    26: return        
   <|@
end_bytecodes
begin_cfg
  name "After NullCheckOptimizer"
  begin_block
    name "B0"
    from_bci -1
    to_bci -1
    predecessors 
    successors 
    xhandlers
    flags 
    probability 4607182418800017408
    begin_IR
      LIR
      nr    0  <|@ instruction [rsi|DWORD, rbp|QWORD] = LABEL numbPhis: 0 align: false label: ? <|@ <|@
      nr    4  <|@ instruction [] = HOTSPOTLOCKSTACK frameMapBuilder: org.graalvm.compiler.lir.amd64.AMD64FrameMapBuilder@13cb46c48 slotKind: QWORD <|@ <|@
      nr    8  <|@ instruction r10|QWORD[.] = HOTSPOTLOADOBJECTCONSTANT input: Object[Instance<java.lang.Class>] <|@ <|@
      nr   10  <|@ instruction MOV (x: [r10|QWORD[.] + 128], y: rsi|DWORD) size: DWORD <|@ <|@
      nr   12  <|@ instruction MEMBAR barriers: 4 <|@ <|@
      nr   14  <|@ instruction RETURN (savedRbp: rbp|QWORD, value: -) isStub: false requiresReservedStackAccessCheck: false thread: r15 scratchForSafepointOnReturn: rcx config: org.graalvm.compiler.hotspot.GraalHotSpotVMConfig@13ae06790 <|@ <|@
    end_IR
  end_block
end_cfg
begin_bytecodes
     0: new           #54         // java.lang.Object
     3: dup           
     4: invokespecial #0          // java.lang.Object.<init>:()void
     7: astore_1      
     8: aload_1       
     9: dup           
    10: astore_2      
    11: monitorenter  
    12: iload_0       
    13: putstatic     #54         // intField:int
    16: aload_2       
    17: monitorexit   
    18: goto          26
    21: astore_3      
    22: aload_2       
    23: monitorexit   
    24: aload_3       
    25: athrow        
    26: return        
   <|@
end_bytecodes
begin_cfg
  name "After StackMoveOptimization"
  begin_block
    name "B0"
    from_bci -1
    to_bci -1
    predecessors 
    successors 
    xhandlers
    flags 
    probability 4607182418800017408
    begin_IR
      LIR
      nr    0  <|@ instruction [rsi|DWORD, rbp|QWORD] = LABEL numbPhis: 0 align: false label: ? <|@ <|@
      nr    4  <|@ instruction [] = HOTSPOTLOCKSTACK frameMapBuilder: org.graalvm.compiler.lir.amd64.AMD64FrameMapBuilder@13cb46c48 slotKind: QWORD <|@ <|@
      nr    8  <|@ instruction r10|QWORD[.] = HOTSPOTLOADOBJECTCONSTANT input: Object[Instance<java.lang.Class>] <|@ <|@
      nr   10  <|@ instruction MOV (x: [r10|QWORD[.] + 128], y: rsi|DWORD) size: DWORD <|@ <|@
      nr   12  <|@ instruction MEMBAR barriers: 4 <|@ <|@
      nr   14  <|@ instruction RETURN (savedRbp: rbp|QWORD, value: -) isStub: false requiresReservedStackAccessCheck: false thread: r15 scratchForSafepointOnReturn: rcx config: org.graalvm.compiler.hotspot.GraalHotSpotVMConfig@13ae06790 <|@ <|@
    end_IR
  end_block
end_cfg
begin_bytecodes
     0: new           #54         // java.lang.Object
     3: dup           
     4: invokespecial #0          // java.lang.Object.<init>:()void
     7: astore_1      
     8: aload_1       
     9: dup           
    10: astore_2      
    11: monitorenter  
    12: iload_0       
    13: putstatic     #54         // intField:int
    16: aload_2       
    17: monitorexit   
    18: goto          26
    21: astore_3      
    22: aload_2       
    23: monitorexit   
    24: aload_3       
    25: athrow        
    26: return        
   <|@
end_bytecodes
begin_cfg
  name "After PostAllocationOptimizationStage"
  begin_block
    name "B0"
    from_bci -1
    to_bci -1
    predecessors 
    successors 
    xhandlers
    flags 
    probability 4607182418800017408
    begin_IR
      LIR
      nr    0  <|@ instruction [rsi|DWORD, rbp|QWORD] = LABEL numbPhis: 0 align: false label: ? <|@ <|@
      nr    4  <|@ instruction [] = HOTSPOTLOCKSTACK frameMapBuilder: org.graalvm.compiler.lir.amd64.AMD64FrameMapBuilder@13cb46c48 slotKind: QWORD <|@ <|@
      nr    8  <|@ instruction r10|QWORD[.] = HOTSPOTLOADOBJECTCONSTANT input: Object[Instance<java.lang.Class>] <|@ <|@
      nr   10  <|@ instruction MOV (x: [r10|QWORD[.] + 128], y: rsi|DWORD) size: DWORD <|@ <|@
      nr   12  <|@ instruction MEMBAR barriers: 4 <|@ <|@
      nr   14  <|@ instruction RETURN (savedRbp: rbp|QWORD, value: -) isStub: false requiresReservedStackAccessCheck: false thread: r15 scratchForSafepointOnReturn: rcx config: org.graalvm.compiler.hotspot.GraalHotSpotVMConfig@13ae06790 <|@ <|@
    end_IR
  end_block
end_cfg
begin_bytecodes
     0: new           #54         // java.lang.Object
     3: dup           
     4: invokespecial #0          // java.lang.Object.<init>:()void
     7: astore_1      
     8: aload_1       
     9: dup           
    10: astore_2      
    11: monitorenter  
    12: iload_0       
    13: putstatic     #54         // intField:int
    16: aload_2       
    17: monitorexit   
    18: goto          26
    21: astore_3      
    22: aload_2       
    23: monitorexit   
    24: aload_3       
    25: athrow        
    26: return        
   <|@
end_bytecodes
begin_cfg
  name "After code generation"
end_cfg
begin_nmethod
  <<<HexCodeFile
  Platform AMD64 64  <||@
  HexCode 0 0f1f44000049baaddeaddeaddeadde4189b280000000f083042400850500000000c5f877c3e80000000090e80000000090  <||@
  Comment 0 3  <||@
  Comment 0 1  <||@
  Comment 5 block B0 null  <||@
  Comment 5 0 [rsi|DWORD, rbp|QWORD] = LABEL numbPhis: 0 align: false label: ?  <||@
  Comment 5 4 [] = HOTSPOTLOCKSTACK frameMapBuilder: org.graalvm.compiler.lir.amd64.AMD64FrameMapBuilder@13cb46c48 slotKind: QWORD  <||@
  Comment 5 8 r10|QWORD[.] = HOTSPOTLOADOBJECTCONSTANT input: Object[Instance<java.lang.Class>]  <||@
  Comment 5 {Object[Instance<java.lang.Class>]}  <||@
  Comment 15 10 MOV (x: [r10|QWORD[.] + 128], y: rsi|DWORD) size: DWORD  <||@
  Comment 22 12 MEMBAR barriers: 4  <||@
  Comment 27 14 RETURN (savedRbp: rbp|QWORD, value: -) isStub: false requiresReservedStackAccessCheck: false thread: r15 scratchForSafepointOnReturn: rcx config: org.graalvm.compiler.hotspot.GraalHotSpotVMConfig@13ae06790  <||@
  Comment 27 12  <||@
  Comment 37 {Stub<ExceptionHandlerStub.exceptionHandler>@0x112e24320:CallingConvention[rax|QWORD[.], rdx|QWORD]:CallingConvention[rax|QWORD[.], rdx|QWORD]; temps=rdi|ILLEGAL,xmm14|ILLEGAL,xmm15|ILLEGAL,xmm12|ILLEGAL,xmm13|ILLEGAL,xmm10|ILLEGAL,xmm11|ILLEGAL,xmm7|ILLEGAL,xmm8|ILLEGAL,xmm9|ILLEGAL,xmm0|ILLEGAL,xmm1|ILLEGAL,xmm2|ILLEGAL,xmm3|ILLEGAL,xmm4|ILLEGAL,xmm5|ILLEGAL,xmm6|ILLEGAL,rax|ILLEGAL,rcx|ILLEGAL,rdx|ILLEGAL,rsi|ILLEGAL,r8|ILLEGAL,r9|ILLEGAL,r10|ILLEGAL,r11|ILLEGAL}  <||@
  Comment 37 4  <||@
  Comment 43 {Field[name=CompilerToVM::Data::SharedRuntime_deopt_blob_unpack, type=address, offset=0, address=0x1108bc128, value=4610474560]:0x112ce4240}  <||@
  Comment 43 5  <||@
  HexCodeFile>>> <|@
end_nmethod
begin_compilation
  name " HotSpotCompilation-370[JavaExamples.exampleLocalSynchronized(int)]"
  method "HotSpotCompilation-370[JavaExamples.exampleLocalSynchronized(int)]"
  date 1583364092263
end_compilation
begin_cfg
  name "After code installation"
end_cfg
begin_nmethod
  <<<HexCodeFile
  Platform AMD64 64  <||@
  HexCode 112e37be0 0f1f44000049bab0275f15070000004189b280000000f0830424008505053493fbc5f877c3e816c7feff90e830c6eaff90f4f4f4f4f4f4f4  <||@
  Comment 0 3  <||@
  Comment 0 1  <||@
  Comment 5 block B0 null  <||@
  Comment 5 0 [rsi|DWORD, rbp|QWORD] = LABEL numbPhis: 0 align: false label: ?  <||@
  Comment 5 4 [] = HOTSPOTLOCKSTACK frameMapBuilder: org.graalvm.compiler.lir.amd64.AMD64FrameMapBuilder@13cb46c48 slotKind: QWORD  <||@
  Comment 5 8 r10|QWORD[.] = HOTSPOTLOADOBJECTCONSTANT input: Object[Instance<java.lang.Class>]  <||@
  Comment 5 {Object[Instance<java.lang.Class>]}  <||@
  Comment 15 10 MOV (x: [r10|QWORD[.] + 128], y: rsi|DWORD) size: DWORD  <||@
  Comment 22 12 MEMBAR barriers: 4  <||@
  Comment 27 14 RETURN (savedRbp: rbp|QWORD, value: -) isStub: false requiresReservedStackAccessCheck: false thread: r15 scratchForSafepointOnReturn: rcx config: org.graalvm.compiler.hotspot.GraalHotSpotVMConfig@13ae06790  <||@
  Comment 27 12  <||@
  Comment 37 {Stub<ExceptionHandlerStub.exceptionHandler>@0x112e24320:CallingConvention[rax|QWORD[.], rdx|QWORD]:CallingConvention[rax|QWORD[.], rdx|QWORD]; temps=rdi|ILLEGAL,xmm14|ILLEGAL,xmm15|ILLEGAL,xmm12|ILLEGAL,xmm13|ILLEGAL,xmm10|ILLEGAL,xmm11|ILLEGAL,xmm7|ILLEGAL,xmm8|ILLEGAL,xmm9|ILLEGAL,xmm0|ILLEGAL,xmm1|ILLEGAL,xmm2|ILLEGAL,xmm3|ILLEGAL,xmm4|ILLEGAL,xmm5|ILLEGAL,xmm6|ILLEGAL,rax|ILLEGAL,rcx|ILLEGAL,rdx|ILLEGAL,rsi|ILLEGAL,r8|ILLEGAL,r9|ILLEGAL,r10|ILLEGAL,r11|ILLEGAL}  <||@
  Comment 37 4  <||@
  Comment 43 {Field[name=CompilerToVM::Data::SharedRuntime_deopt_blob_unpack, type=address, offset=0, address=0x1108bc128, value=4610474560]:0x112ce4240}  <||@
  Comment 43 5  <||@
  HexCodeFile>>> <|@
end_nmethod
